Workbook

Sheet Waybill
A1: 批次号 | B1: 运单号 | C1: 停靠点顺序 | D1: 门店名称 | E1: 经度 | F1: 纬度 | G1: 详细地址 | H1: 门店联系电话 | I1: 货物信息 | J1: 配送日期 | K1: 司机姓名 | L1: 司机电话 | M1: 车牌号 | N1: 供应商名称 | O1: 仓库名称
A2: =数据输入表!B1 -> LC20260421000980 | B2: FS-WB-SAMPLE-01 | C2: =IF(D2<>"",ROW()-1,"") | E2: =IF(D2="","",IFERROR(_xlfn.XLOOKUP(D2,客户信息底表!B:B,客户信息底表!Q:Q,,0),IFERROR(_xlfn.XLOOKUP(D2,客户信息底表!BB:BB,客户信息底表!Q:Q,,0),IFERROR(_xlfn.XLOOKUP(D2,客户信息底表!BC:BC,客户信息底表!Q:Q,,0),IFERROR(_xlfn.XLOOKUP(D2,客户信息底表!BD:BD,客户信息底表!Q:Q,,0),"底表未登记"))))) | F2: =IF(D2="","",IFERROR(_xlfn.XLOOKUP(D2,客户信息底表!B:B,客户信息底表!R:R,,0),IFERROR(_xlfn.XLOOKUP(D2,客户信息底表!BB:BB,客户信息底表!R:R,,0),IFERROR(_xlfn.XLOOKUP(D2,客户信息底表!BC:BC,客户信息底表!R:R,,0),IFERROR(_xlfn.XLOOKUP(D2,客户信息底表!BD:BD,客户信息底表!R:R,,0),"底表未登记"))))) | G2: =IF(D2="","",IFERROR(_xlfn.XLOOKUP(D2,客户信息底表!B:B,客户信息底表!L:L,,0),IFERROR(_xlfn.XLOOKUP(D2,客户信息底表!BB:BB,客户信息底表!L:L,,0),IFERROR(_xlfn.XLOOKUP(D2,客户信息底表!BC:BC,客户信息底表!L:L,,0),IFERROR(_xlfn.XLOOKUP(D2,客户信息底表!BD:BD,客户信息底表!L:L,,0),"底表未登记"))))) | H2: =IF(D2="","",IFERROR(_xlfn.XLOOKUP(D2,客户信息底表!B:B,客户信息底表!G:G,,0),IFERROR(_xlfn.XLOOKUP(D2,客户信息底表!BB:BB,客户信息底表!G:G,,0),IFERROR(_xlfn.XLOOKUP(D2,客户信息底表!BC:BC,客户信息底表!G:G,,0),IFERROR(_xlfn.XLOOKUP(D2,客户信息底表!BD:BD,客户信息底表!G:G,,0),"底表未登记"))))) | I2: =IF(D2="","","整："&数据输入表!J5&"，散："&数据输入表!K5&"；重量kg："&数据输入表!L5&"，体积："&数据输入表!M5) | J2: 46136 | O2: WH
A3: =IF(D3<>"",$A$2,"") -> LC20260421000980 | B3: FS-WB-SAMPLE-02 | C3: =IF(D3<>"",ROW()-1,"") -> 2 | D3: =IF(数据输入表!H6="","",数据输入表!H6) -> 鲸选超市（广州板桥店) | E3: =IF(D3="","",IFERROR(_xlfn.XLOOKUP(D3,客户信息底表!B:B,客户信息底表!Q:Q,,0),IFERROR(_xlfn.XLOOKUP(D3,客户信息底表!BB:BB,客户信息底表!Q:Q,,0),IFERROR(_xlfn.XLOOKUP(D3,客户信息底表!BC:BC,客户信息底表!Q:Q,,0),IFERROR(_xlfn.XLOOKUP(D3,客户信息底表!BD:BD,客户信息底表!Q:Q,,0),"底表未登记"))))) -> 113.38793 | F3: =IF(D3="","",IFERROR(_xlfn.XLOOKUP(D3,客户信息底表!B:B,客户信息底表!R:R,,0),IFERROR(_xlfn.XLOOKUP(D3,客户信息底表!BB:BB,客户信息底表!R:R,,0),IFERROR(_xlfn.XLOOKUP(D3,客户信息底表!BC:BC,客户信息底表!R:R,,0),IFERROR(_xlfn.XLOOKUP(D3,客户信息底表!BD:BD,客户信息底表!R:R,,0),"底表未登记"))))) -> 23.009784 | G3: =IF(D3="","",IFERROR(_xlfn.XLOOKUP(D3,客户信息底表!B:B,客户信息底表!L:L,,0),IFERROR(_xlfn.XLOOKUP(D3,客户信息底表!BB:BB,客户信息底表!L:L,,0),IFERROR(_xlfn.XLOOKUP(D3,客户信息底表!BC:BC,客户信息底表!L:L,,0),IFERROR(_xlfn.XLOOKUP(D3,客户信息底表!BD:BD,客户信息底表!L:L,,0),"底表未登记"))))) -> 南村镇兴南大道902号板桥商务大厦3楼315号 | H3: =IF(D3="","",IFERROR(_xlfn.XLOOKUP(D3,客户信息底表!B:B,客户信息底表!G:G,,0),IFERROR(_xlfn.XLOOKUP(D3,客户信息底表!BB:BB,客户信息底表!G:G,,0),IFERROR(_xlfn.XLOOKUP(D3,客户信息底表!BC:BC,客户信息底表!G:G,,0),IFERROR(_xlfn.XLOOKUP(D3,客户信息底表!BD:BD,客户信息底表!G:G,,0),"底表未登记"))))) -> 13533764129 | I3: =IF(D3="","","整："&数据输入表!J6&"，散："&数据输入表!K6&"；重量kg："&数据输入表!L6&"，体积："&数据输入表!M6) -> 整：11，散：190；重量kg：190，体积：0.03 | J3: 46136 | O3: WH
A4: =IF(D4<>"",$A$2,"") -> LC20260421000980 | B4: FS-WB-SAMPLE-03 | C4: =IF(D4<>"",ROW()-1,"") -> 3 | D4: =IF(数据输入表!H7="","",数据输入表!H7) -> 鲸选超市（广州番禺店) | E4: =IF(D4="","",IFERROR(_xlfn.XLOOKUP(D4,客户信息底表!B:B,客户信息底表!Q:Q,,0),IFERROR(_xlfn.XLOOKUP(D4,客户信息底表!BB:BB,客户信息底表!Q:Q,,0),IFERROR(_xlfn.XLOOKUP(D4,客户信息底表!BC:BC,客户信息底表!Q:Q,,0),IFERROR(_xlfn.XLOOKUP(D4,客户信息底表!BD:BD,客户信息底表!Q:Q,,0),"底表未登记"))))) -> 113.35109 | F4: =IF(D4="","",IFERROR(_xlfn.XLOOKUP(D4,客户信息底表!B:B,客户信息底表!R:R,,0),IFERROR(_xlfn.XLOOKUP(D4,客户信息底表!BB:BB,客户信息底表!R:R,,0),IFERROR(_xlfn.XLOOKUP(D4,客户信息底表!BC:BC,客户信息底表!R:R,,0),IFERROR(_xlfn.XLOOKUP(D4,客户信息底表!BD:BD,客户信息底表!R:R,,0),"底表未登记"))))) -> 23.001303 | G4: =IF(D4="","",IFERROR(_xlfn.XLOOKUP(D4,客户信息底表!B:B,客户信息底表!L:L,,0),IFERROR(_xlfn.XLOOKUP(D4,客户信息底表!BB:BB,客户信息底表!L:L,,0),IFERROR(_xlfn.XLOOKUP(D4,客户信息底表!BC:BC,客户信息底表!L:L,,0),IFERROR(_xlfn.XLOOKUP(D4,客户信息底表!BD:BD,客户信息底表!L:L,,0),"底表未登记"))))) -> 南村镇敏捷上城国际【2期2座112店铺2楼京东便利店仓库】 | H4: =IF(D4="","",IFERROR(_xlfn.XLOOKUP(D4,客户信息底表!B:B,客户信息底表!G:G,,0),IFERROR(_xlfn.XLOOKUP(D4,客户信息底表!BB:BB,客户信息底表!G:G,,0),IFERROR(_xlfn.XLOOKUP(D4,客户信息底表!BC:BC,客户信息底表!G:G,,0),IFERROR(_xlfn.XLOOKUP(D4,客户信息底表!BD:BD,客户信息底表!G:G,,0),"底表未登记"))))) -> 13533764129 | I4: =IF(D4="","","整："&数据输入表!J7&"，散："&数据输入表!K7&"；重量kg："&数据输入表!L7&"，体积："&数据输入表!M7) -> 整：4，散：110；重量kg：110，体积：0.01 | J4: 46136 | O4: WH
A5: =IF(D5<>"",$A$2,"") -> LC20260421000980 | B5: FS-WB-SAMPLE-04 | C5: =IF(D5<>"",ROW()-1,"") -> 4 | D5: =IF(数据输入表!H8="","",数据输入表!H8) -> 时光里便利超市（广州番禺万博店） | E5: =IF(D5="","",IFERROR(_xlfn.XLOOKUP(D5,客户信息底表!B:B,客户信息底表!Q:Q,,0),IFERROR(_xlfn.XLOOKUP(D5,客户信息底表!BB:BB,客户信息底表!Q:Q,,0),IFERROR(_xlfn.XLOOKUP(D5,客户信息底表!BC:BC,客户信息底表!Q:Q,,0),IFERROR(_xlfn.XLOOKUP(D5,客户信息底表!BD:BD,客户信息底表!Q:Q,,0),"底表未登记"))))) -> 113.34426 | F5: =IF(D5="","",IFERROR(_xlfn.XLOOKUP(D5,客户信息底表!B:B,客户信息底表!R:R,,0),IFERROR(_xlfn.XLOOKUP(D5,客户信息底表!BB:BB,客户信息底表!R:R,,0),IFERROR(_xlfn.XLOOKUP(D5,客户信息底表!BC:BC,客户信息底表!R:R,,0),IFERROR(_xlfn.XLOOKUP(D5,客户信息底表!BD:BD,客户信息底表!R:R,,0),"底表未登记"))))) -> 23.013173 | G5: =IF(D5="","",IFERROR(_xlfn.XLOOKUP(D5,客户信息底表!B:B,客户信息底表!L:L,,0),IFERROR(_xlfn.XLOOKUP(D5,客户信息底表!BB:BB,客户信息底表!L:L,,0),IFERROR(_xlfn.XLOOKUP(D5,客户信息底表!BC:BC,客户信息底表!L:L,,0),IFERROR(_xlfn.XLOOKUP(D5,客户信息底表!BD:BD,客户信息底表!L:L,,0),"底表未登记"))))) -> 南村镇登云大路2号之六105房 | H5: =IF(D5="","",IFERROR(_xlfn.XLOOKUP(D5,客户信息底表!B:B,客户信息底表!G:G,,0),IFERROR(_xlfn.XLOOKUP(D5,客户信息底表!BB:BB,客户信息底表!G:G,,0),IFERROR(_xlfn.XLOOKUP(D5,客户信息底表!BC:BC,客户信息底表!G:G,,0),IFERROR(_xlfn.XLOOKUP(D5,客户信息底表!BD:BD,客户信息底表!G:G,,0),"底表未登记"))))) -> 13318758760 | I5: =IF(D5="","","整："&数据输入表!J8&"，散："&数据输入表!K8&"；重量kg："&数据输入表!L8&"，体积："&数据输入表!M8) -> 整：6，散：107；重量kg：107，体积：0.05 | J5: 46136 | O5: WH
A6: =IF(D6<>"",$A$2,"") -> LC20260421000980 | B6: FS-WB-SAMPLE-05 | C6: =IF(D6<>"",ROW()-1,"") -> 5 | D6: =IF(数据输入表!H9="","",数据输入表!H9) -> 熊猫很忙（大石店-广东广州） | E6: =IF(D6="","",IFERROR(_xlfn.XLOOKUP(D6,客户信息底表!B:B,客户信息底表!Q:Q,,0),IFERROR(_xlfn.XLOOKUP(D6,客户信息底表!BB:BB,客户信息底表!Q:Q,,0),IFERROR(_xlfn.XLOOKUP(D6,客户信息底表!BC:BC,客户信息底表!Q:Q,,0),IFERROR(_xlfn.XLOOKUP(D6,客户信息底表!BD:BD,客户信息底表!Q:Q,,0),"底表未登记"))))) -> 113.32446 | F6: =IF(D6="","",IFERROR(_xlfn.XLOOKUP(D6,客户信息底表!B:B,客户信息底表!R:R,,0),IFERROR(_xlfn.XLOOKUP(D6,客户信息底表!BB:BB,客户信息底表!R:R,,0),IFERROR(_xlfn.XLOOKUP(D6,客户信息底表!BC:BC,客户信息底表!R:R,,0),IFERROR(_xlfn.XLOOKUP(D6,客户信息底表!BD:BD,客户信息底表!R:R,,0),"底表未登记"))))) -> 23.023298 | G6: =IF(D6="","",IFERROR(_xlfn.XLOOKUP(D6,客户信息底表!B:B,客户信息底表!L:L,,0),IFERROR(_xlfn.XLOOKUP(D6,客户信息底表!BB:BB,客户信息底表!L:L,,0),IFERROR(_xlfn.XLOOKUP(D6,客户信息底表!BC:BC,客户信息底表!L:L,,0),IFERROR(_xlfn.XLOOKUP(D6,客户信息底表!BD:BD,客户信息底表!L:L,,0),"底表未登记"))))) -> 大石街大山村富山路四街1号胜文工业园2栋1楼103室 | H6: =IF(D6="","",IFERROR(_xlfn.XLOOKUP(D6,客户信息底表!B:B,客户信息底表!G:G,,0),IFERROR(_xlfn.XLOOKUP(D6,客户信息底表!BB:BB,客户信息底表!G:G,,0),IFERROR(_xlfn.XLOOKUP(D6,客户信息底表!BC:BC,客户信息底表!G:G,,0),IFERROR(_xlfn.XLOOKUP(D6,客户信息底表!BD:BD,客户信息底表!G:G,,0),"底表未登记"))))) -> 15018430593 | I6: =IF(D6="","","整："&数据输入表!J9&"，散："&数据输入表!K9&"；重量kg："&数据输入表!L9&"，体积："&数据输入表!M9) -> 整：2，散：125；重量kg：125，体积：0.01 | J6: 46136 | O6: WH
A7: =IF(D7<>"",$A$2,"") -> LC20260421000980 | B7: FS-WB-SAMPLE-06 | C7: =IF(D7<>"",ROW()-1,"") -> 6 | D7: =IF(数据输入表!H10="","",数据输入表!H10) -> 值小团（广州大石店） | E7: =IF(D7="","",IFERROR(_xlfn.XLOOKUP(D7,客户信息底表!B:B,客户信息底表!Q:Q,,0),IFERROR(_xlfn.XLOOKUP(D7,客户信息底表!BB:BB,客户信息底表!Q:Q,,0),IFERROR(_xlfn.XLOOKUP(D7,客户信息底表!BC:BC,客户信息底表!Q:Q,,0),IFERROR(_xlfn.XLOOKUP(D7,客户信息底表!BD:BD,客户信息底表!Q:Q,,0),"底表未登记"))))) -> 113.3196 | F7: =IF(D7="","",IFERROR(_xlfn.XLOOKUP(D7,客户信息底表!B:B,客户信息底表!R:R,,0),IFERROR(_xlfn.XLOOKUP(D7,客户信息底表!BB:BB,客户信息底表!R:R,,0),IFERROR(_xlfn.XLOOKUP(D7,客户信息底表!BC:BC,客户信息底表!R:R,,0),IFERROR(_xlfn.XLOOKUP(D7,客户信息底表!BD:BD,客户信息底表!R:R,,0),"底表未登记"))))) -> 23.026733 | G7: =IF(D7="","",IFERROR(_xlfn.XLOOKUP(D7,客户信息底表!B:B,客户信息底表!L:L,,0),IFERROR(_xlfn.XLOOKUP(D7,客户信息底表!BB:BB,客户信息底表!L:L,,0),IFERROR(_xlfn.XLOOKUP(D7,客户信息底表!BC:BC,客户信息底表!L:L,,0),IFERROR(_xlfn.XLOOKUP(D7,客户信息底表!BD:BD,客户信息底表!L:L,,0),"底表未登记"))))) -> 大石街道大石镇朝阳东路170号201房值小团超市（原玲丰服饰） | H7: =IF(D7="","",IFERROR(_xlfn.XLOOKUP(D7,客户信息底表!B:B,客户信息底表!G:G,,0),IFERROR(_xlfn.XLOOKUP(D7,客户信息底表!BB:BB,客户信息底表!G:G,,0),IFERROR(_xlfn.XLOOKUP(D7,客户信息底表!BC:BC,客户信息底表!G:G,,0),IFERROR(_xlfn.XLOOKUP(D7,客户信息底表!BD:BD,客户信息底表!G:G,,0),"底表未登记"))))) -> 19068527315 | I7: =IF(D7="","","整："&数据输入表!J10&"，散："&数据输入表!K10&"；重量kg："&数据输入表!L10&"，体积："&数据输入表!M10) -> 整：3，散：60；重量kg：60，体积：0.01 | J7: 46136 | O7: WH
A8: =IF(D8<>"",$A$2,"") -> LC20260421000980 | B8: FS-WB-SAMPLE-07 | C8: =IF(D8<>"",ROW()-1,"") -> 7 | D8: =IF(数据输入表!H11="","",数据输入表!H11) -> 鲸选超市（广州大石店) | E8: =IF(D8="","",IFERROR(_xlfn.XLOOKUP(D8,客户信息底表!B:B,客户信息底表!Q:Q,,0),IFERROR(_xlfn.XLOOKUP(D8,客户信息底表!BB:BB,客户信息底表!Q:Q,,0),IFERROR(_xlfn.XLOOKUP(D8,客户信息底表!BC:BC,客户信息底表!Q:Q,,0),IFERROR(_xlfn.XLOOKUP(D8,客户信息底表!BD:BD,客户信息底表!Q:Q,,0),"底表未登记"))))) -> 113.31744 | F8: =IF(D8="","",IFERROR(_xlfn.XLOOKUP(D8,客户信息底表!B:B,客户信息底表!R:R,,0),IFERROR(_xlfn.XLOOKUP(D8,客户信息底表!BB:BB,客户信息底表!R:R,,0),IFERROR(_xlfn.XLOOKUP(D8,客户信息底表!BC:BC,客户信息底表!R:R,,0),IFERROR(_xlfn.XLOOKUP(D8,客户信息底表!BD:BD,客户信息底表!R:R,,0),"底表未登记"))))) -> 23.022374 | G8: =IF(D8="","",IFERROR(_xlfn.XLOOKUP(D8,客户信息底表!B:B,客户信息底表!L:L,,0),IFERROR(_xlfn.XLOOKUP(D8,客户信息底表!BB:BB,客户信息底表!L:L,,0),IFERROR(_xlfn.XLOOKUP(D8,客户信息底表!BC:BC,客户信息底表!L:L,,0),IFERROR(_xlfn.XLOOKUP(D8,客户信息底表!BD:BD,客户信息底表!L:L,,0),"底表未登记"))))) -> 大石街道大涌路157号大石伟讯电子数码城4楼421铺 | H8: =IF(D8="","",IFERROR(_xlfn.XLOOKUP(D8,客户信息底表!B:B,客户信息底表!G:G,,0),IFERROR(_xlfn.XLOOKUP(D8,客户信息底表!BB:BB,客户信息底表!G:G,,0),IFERROR(_xlfn.XLOOKUP(D8,客户信息底表!BC:BC,客户信息底表!G:G,,0),IFERROR(_xlfn.XLOOKUP(D8,客户信息底表!BD:BD,客户信息底表!G:G,,0),"底表未登记"))))) -> 13533764129 | I8: =IF(D8="","","整："&数据输入表!J11&"，散："&数据输入表!K11&"；重量kg："&数据输入表!L11&"，体积："&数据输入表!M11) -> 整：9，散：207；重量kg：207，体积：0.03 | J8: 46136 | O8: WH
A9: =IF(D9<>"",$A$2,"") -> LC20260421000980 | B9: FS-WB-SAMPLE-08 | C9: =IF(D9<>"",ROW()-1,"") -> 8 | D9: =IF(数据输入表!H12="","",数据输入表!H12) -> 熊猫很忙（鹤洞店-广东广州）（直营） | E9: =IF(D9="","",IFERROR(_xlfn.XLOOKUP(D9,客户信息底表!B:B,客户信息底表!Q:Q,,0),IFERROR(_xlfn.XLOOKUP(D9,客户信息底表!BB:BB,客户信息底表!Q:Q,,0),IFERROR(_xlfn.XLOOKUP(D9,客户信息底表!BC:BC,客户信息底表!Q:Q,,0),IFERROR(_xlfn.XLOOKUP(D9,客户信息底表!BD:BD,客户信息底表!Q:Q,,0),"底表未登记"))))) -> 113.236 | F9: =IF(D9="","",IFERROR(_xlfn.XLOOKUP(D9,客户信息底表!B:B,客户信息底表!R:R,,0),IFERROR(_xlfn.XLOOKUP(D9,客户信息底表!BB:BB,客户信息底表!R:R,,0),IFERROR(_xlfn.XLOOKUP(D9,客户信息底表!BC:BC,客户信息底表!R:R,,0),IFERROR(_xlfn.XLOOKUP(D9,客户信息底表!BD:BD,客户信息底表!R:R,,0),"底表未登记"))))) -> 23.068962 | G9: =IF(D9="","",IFERROR(_xlfn.XLOOKUP(D9,客户信息底表!B:B,客户信息底表!L:L,,0),IFERROR(_xlfn.XLOOKUP(D9,客户信息底表!BB:BB,客户信息底表!L:L,,0),IFERROR(_xlfn.XLOOKUP(D9,客户信息底表!BC:BC,客户信息底表!L:L,,0),IFERROR(_xlfn.XLOOKUP(D9,客户信息底表!BD:BD,客户信息底表!L:L,,0),"底表未登记"))))) -> 鹤洞路346号218室2楼送货上门6688不放驿站 | H9: =IF(D9="","",IFERROR(_xlfn.XLOOKUP(D9,客户信息底表!B:B,客户信息底表!G:G,,0),IFERROR(_xlfn.XLOOKUP(D9,客户信息底表!BB:BB,客户信息底表!G:G,,0),IFERROR(_xlfn.XLOOKUP(D9,客户信息底表!BC:BC,客户信息底表!G:G,,0),IFERROR(_xlfn.XLOOKUP(D9,客户信息底表!BD:BD,客户信息底表!G:G,,0),"底表未登记"))))) -> 17722262342 | I9: =IF(D9="","","整："&数据输入表!J12&"，散："&数据输入表!K12&"；重量kg："&数据输入表!L12&"，体积："&数据输入表!M12) -> 整：6，散：102；重量kg：102，体积：0.01 | J9: 46136 | O9: WH
A10: =IF(D10<>"",$A$2,"") -> LC20260421000980 | B10: FS-WB-SAMPLE-09 | C10: =IF(D10<>"",ROW()-1,"") -> 9 | D10: =IF(数据输入表!H13="","",数据输入表!H13) -> 值小团（广州芳村店） | E10: =IF(D10="","",IFERROR(_xlfn.XLOOKUP(D10,客户信息底表!B:B,客户信息底表!Q:Q,,0),IFERROR(_xlfn.XLOOKUP(D10,客户信息底表!BB:BB,客户信息底表!Q:Q,,0),IFERROR(_xlfn.XLOOKUP(D10,客户信息底表!BC:BC,客户信息底表!Q:Q,,0),IFERROR(_xlfn.XLOOKUP(D10,客户信息底表!BD:BD,客户信息底表!Q:Q,,0),"底表未登记"))))) -> 113.23805 | F10: =IF(D10="","",IFERROR(_xlfn.XLOOKUP(D10,客户信息底表!B:B,客户信息底表!R:R,,0),IFERROR(_xlfn.XLOOKUP(D10,客户信息底表!BB:BB,客户信息底表!R:R,,0),IFERROR(_xlfn.XLOOKUP(D10,客户信息底表!BC:BC,客户信息底表!R:R,,0),IFERROR(_xlfn.XLOOKUP(D10,客户信息底表!BD:BD,客户信息底表!R:R,,0),"底表未登记"))))) -> 23.076417 | G10: =IF(D10="","",IFERROR(_xlfn.XLOOKUP(D10,客户信息底表!B:B,客户信息底表!L:L,,0),IFERROR(_xlfn.XLOOKUP(D10,客户信息底表!BB:BB,客户信息底表!L:L,,0),IFERROR(_xlfn.XLOOKUP(D10,客户信息底表!BC:BC,客户信息底表!L:L,,0),IFERROR(_xlfn.XLOOKUP(D10,客户信息底表!BD:BD,客户信息底表!L:L,,0),"底表未登记"))))) -> 坑口大街 138 号红岗工业区1 号首层 101、102 室 | H10: =IF(D10="","",IFERROR(_xlfn.XLOOKUP(D10,客户信息底表!B:B,客户信息底表!G:G,,0),IFERROR(_xlfn.XLOOKUP(D10,客户信息底表!BB:BB,客户信息底表!G:G,,0),IFERROR(_xlfn.XLOOKUP(D10,客户信息底表!BC:BC,客户信息底表!G:G,,0),IFERROR(_xlfn.XLOOKUP(D10,客户信息底表!BD:BD,客户信息底表!G:G,,0),"底表未登记"))))) -> 17575037885 | I10: =IF(D10="","","整："&数据输入表!J13&"，散："&数据输入表!K13&"；重量kg："&数据输入表!L13&"，体积："&数据输入表!M13) -> 整：7，散：114；重量kg：114，体积：0.03 | J10: 46136 | O10: WH
A11: =IF(D11<>"",$A$2,"") -> LC20260421000980 | B11: FS-WB-SAMPLE-10 | C11: =IF(D11<>"",ROW()-1,"") -> 10 | D11: =IF(数据输入表!H14="","",数据输入表!H14) -> 鲸选超市（广州芳村店) | E11: =IF(D11="","",IFERROR(_xlfn.XLOOKUP(D11,客户信息底表!B:B,客户信息底表!Q:Q,,0),IFERROR(_xlfn.XLOOKUP(D11,客户信息底表!BB:BB,客户信息底表!Q:Q,,0),IFERROR(_xlfn.XLOOKUP(D11,客户信息底表!BC:BC,客户信息底表!Q:Q,,0),IFERROR(_xlfn.XLOOKUP(D11,客户信息底表!BD:BD,客户信息底表!Q:Q,,0),"底表未登记"))))) -> 113.23658 | F11: =IF(D11="","",IFERROR(_xlfn.XLOOKUP(D11,客户信息底表!B:B,客户信息底表!R:R,,0),IFERROR(_xlfn.XLOOKUP(D11,客户信息底表!BB:BB,客户信息底表!R:R,,0),IFERROR(_xlfn.XLOOKUP(D11,客户信息底表!BC:BC,客户信息底表!R:R,,0),IFERROR(_xlfn.XLOOKUP(D11,客户信息底表!BD:BD,客户信息底表!R:R,,0),"底表未登记"))))) -> 23.076887 | G11: =IF(D11="","",IFERROR(_xlfn.XLOOKUP(D11,客户信息底表!B:B,客户信息底表!L:L,,0),IFERROR(_xlfn.XLOOKUP(D11,客户信息底表!BB:BB,客户信息底表!L:L,,0),IFERROR(_xlfn.XLOOKUP(D11,客户信息底表!BC:BC,客户信息底表!L:L,,0),IFERROR(_xlfn.XLOOKUP(D11,客户信息底表!BD:BD,客户信息底表!L:L,,0),"底表未登记"))))) -> 花溪路3号 坑口工业区1栋2楼215鲸选超市里面(有电梯) | H11: =IF(D11="","",IFERROR(_xlfn.XLOOKUP(D11,客户信息底表!B:B,客户信息底表!G:G,,0),IFERROR(_xlfn.XLOOKUP(D11,客户信息底表!BB:BB,客户信息底表!G:G,,0),IFERROR(_xlfn.XLOOKUP(D11,客户信息底表!BC:BC,客户信息底表!G:G,,0),IFERROR(_xlfn.XLOOKUP(D11,客户信息底表!BD:BD,客户信息底表!G:G,,0),"底表未登记"))))) -> 13533764129 | I11: =IF(D11="","","整："&数据输入表!J14&"，散："&数据输入表!K14&"；重量kg："&数据输入表!L14&"，体积："&数据输入表!M14) -> 整：6，散：162；重量kg：162，体积：0.02 | J11: 46136 | O11: WH
A12: =IF(D12<>"",$A$2,"") -> LC20260421000980 | B12: FS-WB-SAMPLE-11 | C12: =IF(D12<>"",ROW()-1,"") -> 11 | D12: =IF(数据输入表!H15="","",数据输入表!H15) -> 畅盈到家超市（广州海珠店） | E12: =IF(D12="","",IFERROR(_xlfn.XLOOKUP(D12,客户信息底表!B:B,客户信息底表!Q:Q,,0),IFERROR(_xlfn.XLOOKUP(D12,客户信息底表!BB:BB,客户信息底表!Q:Q,,0),IFERROR(_xlfn.XLOOKUP(D12,客户信息底表!BC:BC,客户信息底表!Q:Q,,0),IFERROR(_xlfn.XLOOKUP(D12,客户信息底表!BD:BD,客户信息底表!Q:Q,,0),"底表未登记"))))) -> 113.26735 | F12: =IF(D12="","",IFERROR(_xlfn.XLOOKUP(D12,客户信息底表!B:B,客户信息底表!R:R,,0),IFERROR(_xlfn.XLOOKUP(D12,客户信息底表!BB:BB,客户信息底表!R:R,,0),IFERROR(_xlfn.XLOOKUP(D12,客户信息底表!BC:BC,客户信息底表!R:R,,0),IFERROR(_xlfn.XLOOKUP(D12,客户信息底表!BD:BD,客户信息底表!R:R,,0),"底表未登记"))))) -> 23.079249 | G12: =IF(D12="","",IFERROR(_xlfn.XLOOKUP(D12,客户信息底表!B:B,客户信息底表!L:L,,0),IFERROR(_xlfn.XLOOKUP(D12,客户信息底表!BB:BB,客户信息底表!L:L,,0),IFERROR(_xlfn.XLOOKUP(D12,客户信息底表!BC:BC,客户信息底表!L:L,,0),IFERROR(_xlfn.XLOOKUP(D12,客户信息底表!BD:BD,客户信息底表!L:L,,0),"底表未登记"))))) -> 南石头街道工业大道中路385号大院11号楼224房 | H12: =IF(D12="","",IFERROR(_xlfn.XLOOKUP(D12,客户信息底表!B:B,客户信息底表!G:G,,0),IFERROR(_xlfn.XLOOKUP(D12,客户信息底表!BB:BB,客户信息底表!G:G,,0),IFERROR(_xlfn.XLOOKUP(D12,客户信息底表!BC:BC,客户信息底表!G:G,,0),IFERROR(_xlfn.XLOOKUP(D12,客户信息底表!BD:BD,客户信息底表!G:G,,0),"底表未登记"))))) -> 13435657776 | I12: =IF(D12="","","整："&数据输入表!J15&"，散："&数据输入表!K15&"；重量kg："&数据输入表!L15&"，体积："&数据输入表!M15) -> 整：9，散：178；重量kg：178，体积：0.12 | J12: 46136 | O12: WH
A13: =IF(D13<>"",$A$2,"") -> LC20260421000980 | B13: FS-WB-SAMPLE-12 | C13: =IF(D13<>"",ROW()-1,"") -> 12 | D13: =IF(数据输入表!H16="","",数据输入表!H16) -> 值小团（广州海珠店） | E13: =IF(D13="","",IFERROR(_xlfn.XLOOKUP(D13,客户信息底表!B:B,客户信息底表!Q:Q,,0),IFERROR(_xlfn.XLOOKUP(D13,客户信息底表!BB:BB,客户信息底表!Q:Q,,0),IFERROR(_xlfn.XLOOKUP(D13,客户信息底表!BC:BC,客户信息底表!Q:Q,,0),IFERROR(_xlfn.XLOOKUP(D13,客户信息底表!BD:BD,客户信息底表!Q:Q,,0),"底表未登记"))))) -> 113.276 | F13: =IF(D13="","",IFERROR(_xlfn.XLOOKUP(D13,客户信息底表!B:B,客户信息底表!R:R,,0),IFERROR(_xlfn.XLOOKUP(D13,客户信息底表!BB:BB,客户信息底表!R:R,,0),IFERROR(_xlfn.XLOOKUP(D13,客户信息底表!BC:BC,客户信息底表!R:R,,0),IFERROR(_xlfn.XLOOKUP(D13,客户信息底表!BD:BD,客户信息底表!R:R,,0),"底表未登记"))))) -> 23.085416 | G13: =IF(D13="","",IFERROR(_xlfn.XLOOKUP(D13,客户信息底表!B:B,客户信息底表!L:L,,0),IFERROR(_xlfn.XLOOKUP(D13,客户信息底表!BB:BB,客户信息底表!L:L,,0),IFERROR(_xlfn.XLOOKUP(D13,客户信息底表!BC:BC,客户信息底表!L:L,,0),IFERROR(_xlfn.XLOOKUP(D13,客户信息底表!BD:BD,客户信息底表!L:L,,0),"底表未登记"))))) -> 信雅路54 | H13: =IF(D13="","",IFERROR(_xlfn.XLOOKUP(D13,客户信息底表!B:B,客户信息底表!G:G,,0),IFERROR(_xlfn.XLOOKUP(D13,客户信息底表!BB:BB,客户信息底表!G:G,,0),IFERROR(_xlfn.XLOOKUP(D13,客户信息底表!BC:BC,客户信息底表!G:G,,0),IFERROR(_xlfn.XLOOKUP(D13,客户信息底表!BD:BD,客户信息底表!G:G,,0),"底表未登记"))))) -> 13710664156 | I13: =IF(D13="","","整："&数据输入表!J16&"，散："&数据输入表!K16&"；重量kg："&数据输入表!L16&"，体积："&数据输入表!M16) -> 整：12，散：135；重量kg：135，体积：0.17 | J13: 46136 | O13: WH
A14: =IF(D14<>"",$A$2,"") | C14: =IF(D14<>"",ROW()-1,"") | D14: =IF(数据输入表!H17="","",数据输入表!H17) | E14: =IF(D14="","",IFERROR(_xlfn.XLOOKUP(D14,客户信息底表!B:B,客户信息底表!Q:Q,,0),IFERROR(_xlfn.XLOOKUP(D14,客户信息底表!BB:BB,客户信息底表!Q:Q,,0),IFERROR(_xlfn.XLOOKUP(D14,客户信息底表!BC:BC,客户信息底表!Q:Q,,0),IFERROR(_xlfn.XLOOKUP(D14,客户信息底表!BD:BD,客户信息底表!Q:Q,,0),"底表未登记"))))) | F14: =IF(D14="","",IFERROR(_xlfn.XLOOKUP(D14,客户信息底表!B:B,客户信息底表!R:R,,0),IFERROR(_xlfn.XLOOKUP(D14,客户信息底表!BB:BB,客户信息底表!R:R,,0),IFERROR(_xlfn.XLOOKUP(D14,客户信息底表!BC:BC,客户信息底表!R:R,,0),IFERROR(_xlfn.XLOOKUP(D14,客户信息底表!BD:BD,客户信息底表!R:R,,0),"底表未登记"))))) | G14: =IF(D14="","",IFERROR(_xlfn.XLOOKUP(D14,客户信息底表!B:B,客户信息底表!L:L,,0),IFERROR(_xlfn.XLOOKUP(D14,客户信息底表!BB:BB,客户信息底表!L:L,,0),IFERROR(_xlfn.XLOOKUP(D14,客户信息底表!BC:BC,客户信息底表!L:L,,0),IFERROR(_xlfn.XLOOKUP(D14,客户信息底表!BD:BD,客户信息底表!L:L,,0),"底表未登记"))))) | H14: =IF(D14="","",IFERROR(_xlfn.XLOOKUP(D14,客户信息底表!B:B,客户信息底表!G:G,,0),IFERROR(_xlfn.XLOOKUP(D14,客户信息底表!BB:BB,客户信息底表!G:G,,0),IFERROR(_xlfn.XLOOKUP(D14,客户信息底表!BC:BC,客户信息底表!G:G,,0),IFERROR(_xlfn.XLOOKUP(D14,客户信息底表!BD:BD,客户信息底表!G:G,,0),"底表未登记"))))) | I14: =IF(D14="","","整："&数据输入表!J17&"，散："&数据输入表!K17&"；重量kg："&数据输入表!L17&"，体积："&数据输入表!M17)
A15: =IF(D15<>"",$A$2,"") | C15: =IF(D15<>"",ROW()-1,"") | D15: =IF(数据输入表!H18="","",数据输入表!H18) | E15: =IF(D15="","",IFERROR(_xlfn.XLOOKUP(D15,客户信息底表!B:B,客户信息底表!Q:Q,,0),IFERROR(_xlfn.XLOOKUP(D15,客户信息底表!BB:BB,客户信息底表!Q:Q,,0),IFERROR(_xlfn.XLOOKUP(D15,客户信息底表!BC:BC,客户信息底表!Q:Q,,0),IFERROR(_xlfn.XLOOKUP(D15,客户信息底表!BD:BD,客户信息底表!Q:Q,,0),"底表未登记"))))) | F15: =IF(D15="","",IFERROR(_xlfn.XLOOKUP(D15,客户信息底表!B:B,客户信息底表!R:R,,0),IFERROR(_xlfn.XLOOKUP(D15,客户信息底表!BB:BB,客户信息底表!R:R,,0),IFERROR(_xlfn.XLOOKUP(D15,客户信息底表!BC:BC,客户信息底表!R:R,,0),IFERROR(_xlfn.XLOOKUP(D15,客户信息底表!BD:BD,客户信息底表!R:R,,0),"底表未登记"))))) | G15: =IF(D15="","",IFERROR(_xlfn.XLOOKUP(D15,客户信息底表!B:B,客户信息底表!L:L,,0),IFERROR(_xlfn.XLOOKUP(D15,客户信息底表!BB:BB,客户信息底表!L:L,,0),IFERROR(_xlfn.XLOOKUP(D15,客户信息底表!BC:BC,客户信息底表!L:L,,0),IFERROR(_xlfn.XLOOKUP(D15,客户信息底表!BD:BD,客户信息底表!L:L,,0),"底表未登记"))))) | H15: =IF(D15="","",IFERROR(_xlfn.XLOOKUP(D15,客户信息底表!B:B,客户信息底表!G:G,,0),IFERROR(_xlfn.XLOOKUP(D15,客户信息底表!BB:BB,客户信息底表!G:G,,0),IFERROR(_xlfn.XLOOKUP(D15,客户信息底表!BC:BC,客户信息底表!G:G,,0),IFERROR(_xlfn.XLOOKUP(D15,客户信息底表!BD:BD,客户信息底表!G:G,,0),"底表未登记"))))) | I15: =IF(D15="","","整："&数据输入表!J18&"，散："&数据输入表!K18&"；重量kg："&数据输入表!L18&"，体积："&数据输入表!M18)
A16: =IF(D16<>"",$A$2,"") | C16: =IF(D16<>"",ROW()-1,"") | D16: =IF(数据输入表!H19="","",数据输入表!H19) | E16: =IF(D16="","",IFERROR(_xlfn.XLOOKUP(D16,客户信息底表!B:B,客户信息底表!Q:Q,,0),IFERROR(_xlfn.XLOOKUP(D16,客户信息底表!BB:BB,客户信息底表!Q:Q,,0),IFERROR(_xlfn.XLOOKUP(D16,客户信息底表!BC:BC,客户信息底表!Q:Q,,0),IFERROR(_xlfn.XLOOKUP(D16,客户信息底表!BD:BD,客户信息底表!Q:Q,,0),"底表未登记"))))) | F16: =IF(D16="","",IFERROR(_xlfn.XLOOKUP(D16,客户信息底表!B:B,客户信息底表!R:R,,0),IFERROR(_xlfn.XLOOKUP(D16,客户信息底表!BB:BB,客户信息底表!R:R,,0),IFERROR(_xlfn.XLOOKUP(D16,客户信息底表!BC:BC,客户信息底表!R:R,,0),IFERROR(_xlfn.XLOOKUP(D16,客户信息底表!BD:BD,客户信息底表!R:R,,0),"底表未登记"))))) | G16: =IF(D16="","",IFERROR(_xlfn.XLOOKUP(D16,客户信息底表!B:B,客户信息底表!L:L,,0),IFERROR(_xlfn.XLOOKUP(D16,客户信息底表!BB:BB,客户信息底表!L:L,,0),IFERROR(_xlfn.XLOOKUP(D16,客户信息底表!BC:BC,客户信息底表!L:L,,0),IFERROR(_xlfn.XLOOKUP(D16,客户信息底表!BD:BD,客户信息底表!L:L,,0),"底表未登记"))))) | H16: =IF(D16="","",IFERROR(_xlfn.XLOOKUP(D16,客户信息底表!B:B,客户信息底表!G:G,,0),IFERROR(_xlfn.XLOOKUP(D16,客户信息底表!BB:BB,客户信息底表!G:G,,0),IFERROR(_xlfn.XLOOKUP(D16,客户信息底表!BC:BC,客户信息底表!G:G,,0),IFERROR(_xlfn.XLOOKUP(D16,客户信息底表!BD:BD,客户信息底表!G:G,,0),"底表未登记"))))) | I16: =IF(D16="","","整："&数据输入表!J19&"，散："&数据输入表!K19&"；重量kg："&数据输入表!L19&"，体积："&数据输入表!M19)
A17: =IF(D17<>"",$A$2,"") | C17: =IF(D17<>"",ROW()-1,"") | D17: =IF(数据输入表!H20="","",数据输入表!H20) | E17: =IF(D17="","",IFERROR(_xlfn.XLOOKUP(D17,客户信息底表!B:B,客户信息底表!Q:Q,,0),IFERROR(_xlfn.XLOOKUP(D17,客户信息底表!BB:BB,客户信息底表!Q:Q,,0),IFERROR(_xlfn.XLOOKUP(D17,客户信息底表!BC:BC,客户信息底表!Q:Q,,0),IFERROR(_xlfn.XLOOKUP(D17,客户信息底表!BD:BD,客户信息底表!Q:Q,,0),"底表未登记"))))) | F17: =IF(D17="","",IFERROR(_xlfn.XLOOKUP(D17,客户信息底表!B:B,客户信息底表!R:R,,0),IFERROR(_xlfn.XLOOKUP(D17,客户信息底表!BB:BB,客户信息底表!R:R,,0),IFERROR(_xlfn.XLOOKUP(D17,客户信息底表!BC:BC,客户信息底表!R:R,,0),IFERROR(_xlfn.XLOOKUP(D17,客户信息底表!BD:BD,客户信息底表!R:R,,0),"底表未登记"))))) | G17: =IF(D17="","",IFERROR(_xlfn.XLOOKUP(D17,客户信息底表!B:B,客户信息底表!L:L,,0),IFERROR(_xlfn.XLOOKUP(D17,客户信息底表!BB:BB,客户信息底表!L:L,,0),IFERROR(_xlfn.XLOOKUP(D17,客户信息底表!BC:BC,客户信息底表!L:L,,0),IFERROR(_xlfn.XLOOKUP(D17,客户信息底表!BD:BD,客户信息底表!L:L,,0),"底表未登记"))))) | H17: =IF(D17="","",IFERROR(_xlfn.XLOOKUP(D17,客户信息底表!B:B,客户信息底表!G:G,,0),IFERROR(_xlfn.XLOOKUP(D17,客户信息底表!BB:BB,客户信息底表!G:G,,0),IFERROR(_xlfn.XLOOKUP(D17,客户信息底表!BC:BC,客户信息底表!G:G,,0),IFERROR(_xlfn.XLOOKUP(D17,客户信息底表!BD:BD,客户信息底表!G:G,,0),"底表未登记"))))) | I17: =IF(D17="","","整："&数据输入表!J20&"，散："&数据输入表!K20&"；重量kg："&数据输入表!L20&"，体积："&数据输入表!M20)
A18: =IF(D18<>"",$A$2,"") | C18: =IF(D18<>"",ROW()-1,"") | D18: =IF(数据输入表!H21="","",数据输入表!H21) | E18: =IF(D18="","",IFERROR(_xlfn.XLOOKUP(D18,客户信息底表!B:B,客户信息底表!Q:Q,,0),IFERROR(_xlfn.XLOOKUP(D18,客户信息底表!BB:BB,客户信息底表!Q:Q,,0),IFERROR(_xlfn.XLOOKUP(D18,客户信息底表!BC:BC,客户信息底表!Q:Q,,0),IFERROR(_xlfn.XLOOKUP(D18,客户信息底表!BD:BD,客户信息底表!Q:Q,,0),"底表未登记"))))) | F18: =IF(D18="","",IFERROR(_xlfn.XLOOKUP(D18,客户信息底表!B:B,客户信息底表!R:R,,0),IFERROR(_xlfn.XLOOKUP(D18,客户信息底表!BB:BB,客户信息底表!R:R,,0),IFERROR(_xlfn.XLOOKUP(D18,客户信息底表!BC:BC,客户信息底表!R:R,,0),IFERROR(_xlfn.XLOOKUP(D18,客户信息底表!BD:BD,客户信息底表!R:R,,0),"底表未登记"))))) | G18: =IF(D18="","",IFERROR(_xlfn.XLOOKUP(D18,客户信息底表!B:B,客户信息底表!L:L,,0),IFERROR(_xlfn.XLOOKUP(D18,客户信息底表!BB:BB,客户信息底表!L:L,,0),IFERROR(_xlfn.XLOOKUP(D18,客户信息底表!BC:BC,客户信息底表!L:L,,0),IFERROR(_xlfn.XLOOKUP(D18,客户信息底表!BD:BD,客户信息底表!L:L,,0),"底表未登记"))))) | H18: =IF(D18="","",IFERROR(_xlfn.XLOOKUP(D18,客户信息底表!B:B,客户信息底表!G:G,,0),IFERROR(_xlfn.XLOOKUP(D18,客户信息底表!BB:BB,客户信息底表!G:G,,0),IFERROR(_xlfn.XLOOKUP(D18,客户信息底表!BC:BC,客户信息底表!G:G,,0),IFERROR(_xlfn.XLOOKUP(D18,客户信息底表!BD:BD,客户信息底表!G:G,,0),"底表未登记"))))) | I18: =IF(D18="","","整："&数据输入表!J21&"，散："&数据输入表!K21&"；重量kg："&数据输入表!L21&"，体积："&数据输入表!M21)
A19: =IF(D19<>"",$A$2,"") | C19: =IF(D19<>"",ROW()-1,"") | D19: =IF(数据输入表!H22="","",数据输入表!H22) | E19: =IF(D19="","",IFERROR(_xlfn.XLOOKUP(D19,客户信息底表!B:B,客户信息底表!Q:Q,,0),IFERROR(_xlfn.XLOOKUP(D19,客户信息底表!BB:BB,客户信息底表!Q:Q,,0),IFERROR(_xlfn.XLOOKUP(D19,客户信息底表!BC:BC,客户信息底表!Q:Q,,0),IFERROR(_xlfn.XLOOKUP(D19,客户信息底表!BD:BD,客户信息底表!Q:Q,,0),"底表未登记"))))) | F19: =IF(D19="","",IFERROR(_xlfn.XLOOKUP(D19,客户信息底表!B:B,客户信息底表!R:R,,0),IFERROR(_xlfn.XLOOKUP(D19,客户信息底表!BB:BB,客户信息底表!R:R,,0),IFERROR(_xlfn.XLOOKUP(D19,客户信息底表!BC:BC,客户信息底表!R:R,,0),IFERROR(_xlfn.XLOOKUP(D19,客户信息底表!BD:BD,客户信息底表!R:R,,0),"底表未登记"))))) | G19: =IF(D19="","",IFERROR(_xlfn.XLOOKUP(D19,客户信息底表!B:B,客户信息底表!L:L,,0),IFERROR(_xlfn.XLOOKUP(D19,客户信息底表!BB:BB,客户信息底表!L:L,,0),IFERROR(_xlfn.XLOOKUP(D19,客户信息底表!BC:BC,客户信息底表!L:L,,0),IFERROR(_xlfn.XLOOKUP(D19,客户信息底表!BD:BD,客户信息底表!L:L,,0),"底表未登记"))))) | H19: =IF(D19="","",IFERROR(_xlfn.XLOOKUP(D19,客户信息底表!B:B,客户信息底表!G:G,,0),IFERROR(_xlfn.XLOOKUP(D19,客户信息底表!BB:BB,客户信息底表!G:G,,0),IFERROR(_xlfn.XLOOKUP(D19,客户信息底表!BC:BC,客户信息底表!G:G,,0),IFERROR(_xlfn.XLOOKUP(D19,客户信息底表!BD:BD,客户信息底表!G:G,,0),"底表未登记"))))) | I19: =IF(D19="","","整："&数据输入表!J22&"，散："&数据输入表!K22&"；重量kg："&数据输入表!L22&"，体积："&数据输入表!M22)
A20: =IF(D20<>"",$A$2,"") | C20: =IF(D20<>"",ROW()-1,"") | D20: =IF(数据输入表!H23="","",数据输入表!H23) | E20: =IF(D20="","",IFERROR(_xlfn.XLOOKUP(D20,客户信息底表!B:B,客户信息底表!Q:Q,,0),IFERROR(_xlfn.XLOOKUP(D20,客户信息底表!BB:BB,客户信息底表!Q:Q,,0),IFERROR(_xlfn.XLOOKUP(D20,客户信息底表!BC:BC,客户信息底表!Q:Q,,0),IFERROR(_xlfn.XLOOKUP(D20,客户信息底表!BD:BD,客户信息底表!Q:Q,,0),"底表未登记"))))) | F20: =IF(D20="","",IFERROR(_xlfn.XLOOKUP(D20,客户信息底表!B:B,客户信息底表!R:R,,0),IFERROR(_xlfn.XLOOKUP(D20,客户信息底表!BB:BB,客户信息底表!R:R,,0),IFERROR(_xlfn.XLOOKUP(D20,客户信息底表!BC:BC,客户信息底表!R:R,,0),IFERROR(_xlfn.XLOOKUP(D20,客户信息底表!BD:BD,客户信息底表!R:R,,0),"底表未登记"))))) | G20: =IF(D20="","",IFERROR(_xlfn.XLOOKUP(D20,客户信息底表!B:B,客户信息底表!L:L,,0),IFERROR(_xlfn.XLOOKUP(D20,客户信息底表!BB:BB,客户信息底表!L:L,,0),IFERROR(_xlfn.XLOOKUP(D20,客户信息底表!BC:BC,客户信息底表!L:L,,0),IFERROR(_xlfn.XLOOKUP(D20,客户信息底表!BD:BD,客户信息底表!L:L,,0),"底表未登记"))))) | H20: =IF(D20="","",IFERROR(_xlfn.XLOOKUP(D20,客户信息底表!B:B,客户信息底表!G:G,,0),IFERROR(_xlfn.XLOOKUP(D20,客户信息底表!BB:BB,客户信息底表!G:G,,0),IFERROR(_xlfn.XLOOKUP(D20,客户信息底表!BC:BC,客户信息底表!G:G,,0),IFERROR(_xlfn.XLOOKUP(D20,客户信息底表!BD:BD,客户信息底表!G:G,,0),"底表未登记"))))) | I20: =IF(D20="","","整："&数据输入表!J23&"，散："&数据输入表!K23&"；重量kg："&数据输入表!L23&"，体积："&数据输入表!M23)
A21: =IF(D21<>"",$A$2,"") | C21: =IF(D21<>"",ROW()-1,"") | D21: =IF(数据输入表!H24="","",数据输入表!H24) | E21: =IF(D21="","",IFERROR(_xlfn.XLOOKUP(D21,客户信息底表!B:B,客户信息底表!Q:Q,,0),IFERROR(_xlfn.XLOOKUP(D21,客户信息底表!BB:BB,客户信息底表!Q:Q,,0),IFERROR(_xlfn.XLOOKUP(D21,客户信息底表!BC:BC,客户信息底表!Q:Q,,0),IFERROR(_xlfn.XLOOKUP(D21,客户信息底表!BD:BD,客户信息底表!Q:Q,,0),"底表未登记"))))) | F21: =IF(D21="","",IFERROR(_xlfn.XLOOKUP(D21,客户信息底表!B:B,客户信息底表!R:R,,0),IFERROR(_xlfn.XLOOKUP(D21,客户信息底表!BB:BB,客户信息底表!R:R,,0),IFERROR(_xlfn.XLOOKUP(D21,客户信息底表!BC:BC,客户信息底表!R:R,,0),IFERROR(_xlfn.XLOOKUP(D21,客户信息底表!BD:BD,客户信息底表!R:R,,0),"底表未登记"))))) | G21: =IF(D21="","",IFERROR(_xlfn.XLOOKUP(D21,客户信息底表!B:B,客户信息底表!L:L,,0),IFERROR(_xlfn.XLOOKUP(D21,客户信息底表!BB:BB,客户信息底表!L:L,,0),IFERROR(_xlfn.XLOOKUP(D21,客户信息底表!BC:BC,客户信息底表!L:L,,0),IFERROR(_xlfn.XLOOKUP(D21,客户信息底表!BD:BD,客户信息底表!L:L,,0),"底表未登记"))))) | H21: =IF(D21="","",IFERROR(_xlfn.XLOOKUP(D21,客户信息底表!B:B,客户信息底表!G:G,,0),IFERROR(_xlfn.XLOOKUP(D21,客户信息底表!BB:BB,客户信息底表!G:G,,0),IFERROR(_xlfn.XLOOKUP(D21,客户信息底表!BC:BC,客户信息底表!G:G,,0),IFERROR(_xlfn.XLOOKUP(D21,客户信息底表!BD:BD,客户信息底表!G:G,,0),"底表未登记"))))) | I21: =IF(D21="","","整："&数据输入表!J24&"，散："&数据输入表!K24&"；重量kg："&数据输入表!L24&"，体积："&数据输入表!M24)
A22: =IF(D22<>"",$A$2,"") | C22: =IF(D22<>"",ROW()-1,"") | D22: =IF(数据输入表!H25="","",数据输入表!H25) | E22: =IF(D22="","",IFERROR(_xlfn.XLOOKUP(D22,客户信息底表!B:B,客户信息底表!Q:Q,,0),IFERROR(_xlfn.XLOOKUP(D22,客户信息底表!BB:BB,客户信息底表!Q:Q,,0),IFERROR(_xlfn.XLOOKUP(D22,客户信息底表!BC:BC,客户信息底表!Q:Q,,0),IFERROR(_xlfn.XLOOKUP(D22,客户信息底表!BD:BD,客户信息底表!Q:Q,,0),"底表未登记"))))) | F22: =IF(D22="","",IFERROR(_xlfn.XLOOKUP(D22,客户信息底表!B:B,客户信息底表!R:R,,0),IFERROR(_xlfn.XLOOKUP(D22,客户信息底表!BB:BB,客户信息底表!R:R,,0),IFERROR(_xlfn.XLOOKUP(D22,客户信息底表!BC:BC,客户信息底表!R:R,,0),IFERROR(_xlfn.XLOOKUP(D22,客户信息底表!BD:BD,客户信息底表!R:R,,0),"底表未登记"))))) | G22: =IF(D22="","",IFERROR(_xlfn.XLOOKUP(D22,客户信息底表!B:B,客户信息底表!L:L,,0),IFERROR(_xlfn.XLOOKUP(D22,客户信息底表!BB:BB,客户信息底表!L:L,,0),IFERROR(_xlfn.XLOOKUP(D22,客户信息底表!BC:BC,客户信息底表!L:L,,0),IFERROR(_xlfn.XLOOKUP(D22,客户信息底表!BD:BD,客户信息底表!L:L,,0),"底表未登记"))))) | H22: =IF(D22="","",IFERROR(_xlfn.XLOOKUP(D22,客户信息底表!B:B,客户信息底表!G:G,,0),IFERROR(_xlfn.XLOOKUP(D22,客户信息底表!BB:BB,客户信息底表!G:G,,0),IFERROR(_xlfn.XLOOKUP(D22,客户信息底表!BC:BC,客户信息底表!G:G,,0),IFERROR(_xlfn.XLOOKUP(D22,客户信息底表!BD:BD,客户信息底表!G:G,,0),"底表未登记"))))) | I22: =IF(D22="","","整："&数据输入表!J25&"，散："&数据输入表!K25&"；重量kg："&数据输入表!L25&"，体积："&数据输入表!M25)
A23: =IF(D23<>"",$A$2,"") | C23: =IF(D23<>"",ROW()-1,"") | D23: =IF(数据输入表!H26="","",数据输入表!H26) | E23: =IF(D23="","",IFERROR(_xlfn.XLOOKUP(D23,客户信息底表!B:B,客户信息底表!Q:Q,,0),IFERROR(_xlfn.XLOOKUP(D23,客户信息底表!BB:BB,客户信息底表!Q:Q,,0),IFERROR(_xlfn.XLOOKUP(D23,客户信息底表!BC:BC,客户信息底表!Q:Q,,0),IFERROR(_xlfn.XLOOKUP(D23,客户信息底表!BD:BD,客户信息底表!Q:Q,,0),"底表未登记"))))) | F23: =IF(D23="","",IFERROR(_xlfn.XLOOKUP(D23,客户信息底表!B:B,客户信息底表!R:R,,0),IFERROR(_xlfn.XLOOKUP(D23,客户信息底表!BB:BB,客户信息底表!R:R,,0),IFERROR(_xlfn.XLOOKUP(D23,客户信息底表!BC:BC,客户信息底表!R:R,,0),IFERROR(_xlfn.XLOOKUP(D23,客户信息底表!BD:BD,客户信息底表!R:R,,0),"底表未登记"))))) | G23: =IF(D23="","",IFERROR(_xlfn.XLOOKUP(D23,客户信息底表!B:B,客户信息底表!L:L,,0),IFERROR(_xlfn.XLOOKUP(D23,客户信息底表!BB:BB,客户信息底表!L:L,,0),IFERROR(_xlfn.XLOOKUP(D23,客户信息底表!BC:BC,客户信息底表!L:L,,0),IFERROR(_xlfn.XLOOKUP(D23,客户信息底表!BD:BD,客户信息底表!L:L,,0),"底表未登记"))))) | H23: =IF(D23="","",IFERROR(_xlfn.XLOOKUP(D23,客户信息底表!B:B,客户信息底表!G:G,,0),IFERROR(_xlfn.XLOOKUP(D23,客户信息底表!BB:BB,客户信息底表!G:G,,0),IFERROR(_xlfn.XLOOKUP(D23,客户信息底表!BC:BC,客户信息底表!G:G,,0),IFERROR(_xlfn.XLOOKUP(D23,客户信息底表!BD:BD,客户信息底表!G:G,,0),"底表未登记"))))) | I23: =IF(D23="","","整："&数据输入表!J26&"，散："&数据输入表!K26&"；重量kg："&数据输入表!L26&"，体积："&数据输入表!M26)
A24: =IF(D24<>"",$A$2,"") | C24: =IF(D24<>"",ROW()-1,"") | D24: =IF(数据输入表!H27="","",数据输入表!H27) | E24: =IF(D24="","",IFERROR(_xlfn.XLOOKUP(D24,客户信息底表!B:B,客户信息底表!Q:Q,,0),IFERROR(_xlfn.XLOOKUP(D24,客户信息底表!BB:BB,客户信息底表!Q:Q,,0),IFERROR(_xlfn.XLOOKUP(D24,客户信息底表!BC:BC,客户信息底表!Q:Q,,0),IFERROR(_xlfn.XLOOKUP(D24,客户信息底表!BD:BD,客户信息底表!Q:Q,,0),"底表未登记"))))) | F24: =IF(D24="","",IFERROR(_xlfn.XLOOKUP(D24,客户信息底表!B:B,客户信息底表!R:R,,0),IFERROR(_xlfn.XLOOKUP(D24,客户信息底表!BB:BB,客户信息底表!R:R,,0),IFERROR(_xlfn.XLOOKUP(D24,客户信息底表!BC:BC,客户信息底表!R:R,,0),IFERROR(_xlfn.XLOOKUP(D24,客户信息底表!BD:BD,客户信息底表!R:R,,0),"底表未登记"))))) | G24: =IF(D24="","",IFERROR(_xlfn.XLOOKUP(D24,客户信息底表!B:B,客户信息底表!L:L,,0),IFERROR(_xlfn.XLOOKUP(D24,客户信息底表!BB:BB,客户信息底表!L:L,,0),IFERROR(_xlfn.XLOOKUP(D24,客户信息底表!BC:BC,客户信息底表!L:L,,0),IFERROR(_xlfn.XLOOKUP(D24,客户信息底表!BD:BD,客户信息底表!L:L,,0),"底表未登记"))))) | H24: =IF(D24="","",IFERROR(_xlfn.XLOOKUP(D24,客户信息底表!B:B,客户信息底表!G:G,,0),IFERROR(_xlfn.XLOOKUP(D24,客户信息底表!BB:BB,客户信息底表!G:G,,0),IFERROR(_xlfn.XLOOKUP(D24,客户信息底表!BC:BC,客户信息底表!G:G,,0),IFERROR(_xlfn.XLOOKUP(D24,客户信息底表!BD:BD,客户信息底表!G:G,,0),"底表未登记"))))) | I24: =IF(D24="","","整："&数据输入表!J27&"，散："&数据输入表!K27&"；重量kg："&数据输入表!L27&"，体积："&数据输入表!M27)
A25: =IF(D25<>"",$A$2,"") | C25: =IF(D25<>"",ROW()-1,"") | D25: =IF(数据输入表!H28="","",数据输入表!H28) | E25: =IF(D25="","",IFERROR(_xlfn.XLOOKUP(D25,客户信息底表!B:B,客户信息底表!Q:Q,,0),IFERROR(_xlfn.XLOOKUP(D25,客户信息底表!BB:BB,客户信息底表!Q:Q,,0),IFERROR(_xlfn.XLOOKUP(D25,客户信息底表!BC:BC,客户信息底表!Q:Q,,0),IFERROR(_xlfn.XLOOKUP(D25,客户信息底表!BD:BD,客户信息底表!Q:Q,,0),"底表未登记"))))) | F25: =IF(D25="","",IFERROR(_xlfn.XLOOKUP(D25,客户信息底表!B:B,客户信息底表!R:R,,0),IFERROR(_xlfn.XLOOKUP(D25,客户信息底表!BB:BB,客户信息底表!R:R,,0),IFERROR(_xlfn.XLOOKUP(D25,客户信息底表!BC:BC,客户信息底表!R:R,,0),IFERROR(_xlfn.XLOOKUP(D25,客户信息底表!BD:BD,客户信息底表!R:R,,0),"底表未登记"))))) | G25: =IF(D25="","",IFERROR(_xlfn.XLOOKUP(D25,客户信息底表!B:B,客户信息底表!L:L,,0),IFERROR(_xlfn.XLOOKUP(D25,客户信息底表!BB:BB,客户信息底表!L:L,,0),IFERROR(_xlfn.XLOOKUP(D25,客户信息底表!BC:BC,客户信息底表!L:L,,0),IFERROR(_xlfn.XLOOKUP(D25,客户信息底表!BD:BD,客户信息底表!L:L,,0),"底表未登记"))))) | H25: =IF(D25="","",IFERROR(_xlfn.XLOOKUP(D25,客户信息底表!B:B,客户信息底表!G:G,,0),IFERROR(_xlfn.XLOOKUP(D25,客户信息底表!BB:BB,客户信息底表!G:G,,0),IFERROR(_xlfn.XLOOKUP(D25,客户信息底表!BC:BC,客户信息底表!G:G,,0),IFERROR(_xlfn.XLOOKUP(D25,客户信息底表!BD:BD,客户信息底表!G:G,,0),"底表未登记"))))) | I25: =IF(D25="","","整："&数据输入表!J28&"，散："&数据输入表!K28&"；重量kg："&数据输入表!L28&"，体积："&数据输入表!M28)
... A37: =IF(D37<>"",$A$2,"") | C37: =IF(D37<>"",ROW()-1,"") | D37: =IF(数据输入表!H40="","",数据输入表!H40) | E37: =IF(D37="","",IFERROR(_xlfn.XLOOKUP(D37,客户信息底表!B:B,客户信息底表!Q:Q,,0),IFERROR(_xlfn.XLOOKUP(D37,客户信息底表!BB:BB,客户信息底表!Q:Q,,0),IFERROR(_xlfn.XLOOKUP(D37,客户信息底表!BC:BC,客户信息底表!Q:Q,,0),IFERROR(_xlfn.XLOOKUP(D37,客户信息底表!BD:BD,客户信息底表!Q:Q,,0),"底表未登记"))))) | F37: =IF(D37="","",IFERROR(_xlfn.XLOOKUP(D37,客户信息底表!B:B,客户信息底表!R:R,,0),IFERROR(_xlfn.XLOOKUP(D37,客户信息底表!BB:BB,客户信息底表!R:R,,0),IFERROR(_xlfn.XLOOKUP(D37,客户信息底表!BC:BC,客户信息底表!R:R,,0),IFERROR(_xlfn.XLOOKUP(D37,客户信息底表!BD:BD,客户信息底表!R:R,,0),"底表未登记"))))) | G37: =IF(D37="","",IFERROR(_xlfn.XLOOKUP(D37,客户信息底表!B:B,客户信息底表!L:L,,0),IFERROR(_xlfn.XLOOKUP(D37,客户信息底表!BB:BB,客户信息底表!L:L,,0),IFERROR(_xlfn.XLOOKUP(D37,客户信息底表!BC:BC,客户信息底表!L:L,,0),IFERROR(_xlfn.XLOOKUP(D37,客户信息底表!BD:BD,客户信息底表!L:L,,0),"底表未登记"))))) | H37: =IF(D37="","",IFERROR(_xlfn.XLOOKUP(D37,客户信息底表!B:B,客户信息底表!G:G,,0),IFERROR(_xlfn.XLOOKUP(D37,客户信息底表!BB:BB,客户信息底表!G:G,,0),IFERROR(_xlfn.XLOOKUP(D37,客户信息底表!BC:BC,客户信息底表!G:G,,0),IFERROR(_xlfn.XLOOKUP(D37,客户信息底表!BD:BD,客户信息底表!G:G,,0),"底表未登记"))))) | I37: =IF(D37="","","整："&数据输入表!J40&"，散："&数据输入表!K40&"；重量kg："&数据输入表!L40&"，体积："&数据输入表!M40)
A38: =IF(D38<>"",$A$2,"") | C38: =IF(D38<>"",ROW()-1,"") | E38: =IF(D38="","",IFERROR(_xlfn.XLOOKUP(D38,客户信息底表!B:B,客户信息底表!Q:Q,,0),IFERROR(_xlfn.XLOOKUP(D38,客户信息底表!BB:BB,客户信息底表!Q:Q,,0),IFERROR(_xlfn.XLOOKUP(D38,客户信息底表!BC:BC,客户信息底表!Q:Q,,0),IFERROR(_xlfn.XLOOKUP(D38,客户信息底表!BD:BD,客户信息底表!Q:Q,,0),"底表未登记"))))) | F38: =IF(D38="","",IFERROR(_xlfn.XLOOKUP(D38,客户信息底表!B:B,客户信息底表!R:R,,0),IFERROR(_xlfn.XLOOKUP(D38,客户信息底表!BB:BB,客户信息底表!R:R,,0),IFERROR(_xlfn.XLOOKUP(D38,客户信息底表!BC:BC,客户信息底表!R:R,,0),IFERROR(_xlfn.XLOOKUP(D38,客户信息底表!BD:BD,客户信息底表!R:R,,0),"底表未登记"))))) | G38: =IF(D38="","",IFERROR(_xlfn.XLOOKUP(D38,客户信息底表!B:B,客户信息底表!L:L,,0),IFERROR(_xlfn.XLOOKUP(D38,客户信息底表!BB:BB,客户信息底表!L:L,,0),IFERROR(_xlfn.XLOOKUP(D38,客户信息底表!BC:BC,客户信息底表!L:L,,0),IFERROR(_xlfn.XLOOKUP(D38,客户信息底表!BD:BD,客户信息底表!L:L,,0),"底表未登记"))))) | H38: =IF(D38="","",IFERROR(_xlfn.XLOOKUP(D38,客户信息底表!B:B,客户信息底表!G:G,,0),IFERROR(_xlfn.XLOOKUP(D38,客户信息底表!BB:BB,客户信息底表!G:G,,0),IFERROR(_xlfn.XLOOKUP(D38,客户信息底表!BC:BC,客户信息底表!G:G,,0),IFERROR(_xlfn.XLOOKUP(D38,客户信息底表!BD:BD,客户信息底表!G:G,,0),"底表未登记"))))) | I38: =IF(D38="","","整："&数据输入表!J41&"，散："&数据输入表!K41&"；重量kg："&数据输入表!L41&"，体积："&数据输入表!M41)
A39: =IF(D39<>"",$A$2,"") | C39: =IF(D39<>"",ROW()-1,"") | E39: =IF(D39="","",IFERROR(_xlfn.XLOOKUP(D39,客户信息底表!B:B,客户信息底表!Q:Q,,0),IFERROR(_xlfn.XLOOKUP(D39,客户信息底表!BB:BB,客户信息底表!Q:Q,,0),IFERROR(_xlfn.XLOOKUP(D39,客户信息底表!BC:BC,客户信息底表!Q:Q,,0),IFERROR(_xlfn.XLOOKUP(D39,客户信息底表!BD:BD,客户信息底表!Q:Q,,0),"底表未登记"))))) | F39: =IF(D39="","",IFERROR(_xlfn.XLOOKUP(D39,客户信息底表!B:B,客户信息底表!R:R,,0),IFERROR(_xlfn.XLOOKUP(D39,客户信息底表!BB:BB,客户信息底表!R:R,,0),IFERROR(_xlfn.XLOOKUP(D39,客户信息底表!BC:BC,客户信息底表!R:R,,0),IFERROR(_xlfn.XLOOKUP(D39,客户信息底表!BD:BD,客户信息底表!R:R,,0),"底表未登记"))))) | G39: =IF(D39="","",IFERROR(_xlfn.XLOOKUP(D39,客户信息底表!B:B,客户信息底表!L:L,,0),IFERROR(_xlfn.XLOOKUP(D39,客户信息底表!BB:BB,客户信息底表!L:L,,0),IFERROR(_xlfn.XLOOKUP(D39,客户信息底表!BC:BC,客户信息底表!L:L,,0),IFERROR(_xlfn.XLOOKUP(D39,客户信息底表!BD:BD,客户信息底表!L:L,,0),"底表未登记"))))) | H39: =IF(D39="","",IFERROR(_xlfn.XLOOKUP(D39,客户信息底表!B:B,客户信息底表!G:G,,0),IFERROR(_xlfn.XLOOKUP(D39,客户信息底表!BB:BB,客户信息底表!G:G,,0),IFERROR(_xlfn.XLOOKUP(D39,客户信息底表!BC:BC,客户信息底表!G:G,,0),IFERROR(_xlfn.XLOOKUP(D39,客户信息底表!BD:BD,客户信息底表!G:G,,0),"底表未登记"))))) | I39: =IF(D39="","","整："&数据输入表!J42&"，散："&数据输入表!K42&"；重量kg："&数据输入表!L42&"，体积："&数据输入表!M42)
A40: =IF(D40<>"",$A$2,"") | C40: =IF(D40<>"",ROW()-1,"") | E40: =IF(D40="","",IFERROR(_xlfn.XLOOKUP(D40,客户信息底表!B:B,客户信息底表!Q:Q,,0),IFERROR(_xlfn.XLOOKUP(D40,客户信息底表!BB:BB,客户信息底表!Q:Q,,0),IFERROR(_xlfn.XLOOKUP(D40,客户信息底表!BC:BC,客户信息底表!Q:Q,,0),IFERROR(_xlfn.XLOOKUP(D40,客户信息底表!BD:BD,客户信息底表!Q:Q,,0),"底表未登记"))))) | F40: =IF(D40="","",IFERROR(_xlfn.XLOOKUP(D40,客户信息底表!B:B,客户信息底表!R:R,,0),IFERROR(_xlfn.XLOOKUP(D40,客户信息底表!BB:BB,客户信息底表!R:R,,0),IFERROR(_xlfn.XLOOKUP(D40,客户信息底表!BC:BC,客户信息底表!R:R,,0),IFERROR(_xlfn.XLOOKUP(D40,客户信息底表!BD:BD,客户信息底表!R:R,,0),"底表未登记"))))) | G40: =IF(D40="","",IFERROR(_xlfn.XLOOKUP(D40,客户信息底表!B:B,客户信息底表!L:L,,0),IFERROR(_xlfn.XLOOKUP(D40,客户信息底表!BB:BB,客户信息底表!L:L,,0),IFERROR(_xlfn.XLOOKUP(D40,客户信息底表!BC:BC,客户信息底表!L:L,,0),IFERROR(_xlfn.XLOOKUP(D40,客户信息底表!BD:BD,客户信息底表!L:L,,0),"底表未登记"))))) | H40: =IF(D40="","",IFERROR(_xlfn.XLOOKUP(D40,客户信息底表!B:B,客户信息底表!G:G,,0),IFERROR(_xlfn.XLOOKUP(D40,客户信息底表!BB:BB,客户信息底表!G:G,,0),IFERROR(_xlfn.XLOOKUP(D40,客户信息底表!BC:BC,客户信息底表!G:G,,0),IFERROR(_xlfn.XLOOKUP(D40,客户信息底表!BD:BD,客户信息底表!G:G,,0),"底表未登记"))))) | I40: =IF(D40="","","整："&数据输入表!J43&"，散："&数据输入表!K43&"；重量kg："&数据输入表!L43&"，体积："&数据输入表!M43)
A41: =IF(D41<>"",$A$2,"") | C41: =IF(D41<>"",ROW()-1,"") | E41: =IF(D41="","",IFERROR(_xlfn.XLOOKUP(D41,客户信息底表!B:B,客户信息底表!Q:Q,,0),IFERROR(_xlfn.XLOOKUP(D41,客户信息底表!BB:BB,客户信息底表!Q:Q,,0),IFERROR(_xlfn.XLOOKUP(D41,客户信息底表!BC:BC,客户信息底表!Q:Q,,0),IFERROR(_xlfn.XLOOKUP(D41,客户信息底表!BD:BD,客户信息底表!Q:Q,,0),"底表未登记"))))) | F41: =IF(D41="","",IFERROR(_xlfn.XLOOKUP(D41,客户信息底表!B:B,客户信息底表!R:R,,0),IFERROR(_xlfn.XLOOKUP(D41,客户信息底表!BB:BB,客户信息底表!R:R,,0),IFERROR(_xlfn.XLOOKUP(D41,客户信息底表!BC:BC,客户信息底表!R:R,,0),IFERROR(_xlfn.XLOOKUP(D41,客户信息底表!BD:BD,客户信息底表!R:R,,0),"底表未登记"))))) | G41: =IF(D41="","",IFERROR(_xlfn.XLOOKUP(D41,客户信息底表!B:B,客户信息底表!L:L,,0),IFERROR(_xlfn.XLOOKUP(D41,客户信息底表!BB:BB,客户信息底表!L:L,,0),IFERROR(_xlfn.XLOOKUP(D41,客户信息底表!BC:BC,客户信息底表!L:L,,0),IFERROR(_xlfn.XLOOKUP(D41,客户信息底表!BD:BD,客户信息底表!L:L,,0),"底表未登记"))))) | H41: =IF(D41="","",IFERROR(_xlfn.XLOOKUP(D41,客户信息底表!B:B,客户信息底表!G:G,,0),IFERROR(_xlfn.XLOOKUP(D41,客户信息底表!BB:BB,客户信息底表!G:G,,0),IFERROR(_xlfn.XLOOKUP(D41,客户信息底表!BC:BC,客户信息底表!G:G,,0),IFERROR(_xlfn.XLOOKUP(D41,客户信息底表!BD:BD,客户信息底表!G:G,,0),"底表未登记"))))) | I41: =IF(D41="","","整："&数据输入表!J44&"，散："&数据输入表!K44&"；重量kg："&数据输入表!L44&"，体积："&数据输入表!M44)
A42: =IF(D42<>"",$A$2,"") | C42: =IF(D42<>"",ROW()-1,"") | E42: =IF(D42="","",IFERROR(_xlfn.XLOOKUP(D42,客户信息底表!B:B,客户信息底表!Q:Q,,0),IFERROR(_xlfn.XLOOKUP(D42,客户信息底表!BB:BB,客户信息底表!Q:Q,,0),IFERROR(_xlfn.XLOOKUP(D42,客户信息底表!BC:BC,客户信息底表!Q:Q,,0),IFERROR(_xlfn.XLOOKUP(D42,客户信息底表!BD:BD,客户信息底表!Q:Q,,0),"底表未登记"))))) | F42: =IF(D42="","",IFERROR(_xlfn.XLOOKUP(D42,客户信息底表!B:B,客户信息底表!R:R,,0),IFERROR(_xlfn.XLOOKUP(D42,客户信息底表!BB:BB,客户信息底表!R:R,,0),IFERROR(_xlfn.XLOOKUP(D42,客户信息底表!BC:BC,客户信息底表!R:R,,0),IFERROR(_xlfn.XLOOKUP(D42,客户信息底表!BD:BD,客户信息底表!R:R,,0),"底表未登记"))))) | G42: =IF(D42="","",IFERROR(_xlfn.XLOOKUP(D42,客户信息底表!B:B,客户信息底表!L:L,,0),IFERROR(_xlfn.XLOOKUP(D42,客户信息底表!BB:BB,客户信息底表!L:L,,0),IFERROR(_xlfn.XLOOKUP(D42,客户信息底表!BC:BC,客户信息底表!L:L,,0),IFERROR(_xlfn.XLOOKUP(D42,客户信息底表!BD:BD,客户信息底表!L:L,,0),"底表未登记"))))) | H42: =IF(D42="","",IFERROR(_xlfn.XLOOKUP(D42,客户信息底表!B:B,客户信息底表!G:G,,0),IFERROR(_xlfn.XLOOKUP(D42,客户信息底表!BB:BB,客户信息底表!G:G,,0),IFERROR(_xlfn.XLOOKUP(D42,客户信息底表!BC:BC,客户信息底表!G:G,,0),IFERROR(_xlfn.XLOOKUP(D42,客户信息底表!BD:BD,客户信息底表!G:G,,0),"底表未登记"))))) | I42: =IF(D42="","","整："&数据输入表!J45&"，散："&数据输入表!K45&"；重量kg："&数据输入表!L45&"，体积："&数据输入表!M45)
A43: =IF(D43<>"",$A$2,"") | C43: =IF(D43<>"",ROW()-1,"") | E43: =IF(D43="","",IFERROR(_xlfn.XLOOKUP(D43,客户信息底表!B:B,客户信息底表!Q:Q,,0),IFERROR(_xlfn.XLOOKUP(D43,客户信息底表!BB:BB,客户信息底表!Q:Q,,0),IFERROR(_xlfn.XLOOKUP(D43,客户信息底表!BC:BC,客户信息底表!Q:Q,,0),IFERROR(_xlfn.XLOOKUP(D43,客户信息底表!BD:BD,客户信息底表!Q:Q,,0),"底表未登记"))))) | G43: =IF(D43="","",IFERROR(_xlfn.XLOOKUP(D43,客户信息底表!B:B,客户信息底表!L:L,,0),IFERROR(_xlfn.XLOOKUP(D43,客户信息底表!BB:BB,客户信息底表!L:L,,0),IFERROR(_xlfn.XLOOKUP(D43,客户信息底表!BC:BC,客户信息底表!L:L,,0),IFERROR(_xlfn.XLOOKUP(D43,客户信息底表!BD:BD,客户信息底表!L:L,,0),"底表未登记"))))) | H43: =IF(D43="","",IFERROR(_xlfn.XLOOKUP(D43,客户信息底表!B:B,客户信息底表!G:G,,0),IFERROR(_xlfn.XLOOKUP(D43,客户信息底表!BB:BB,客户信息底表!G:G,,0),IFERROR(_xlfn.XLOOKUP(D43,客户信息底表!BC:BC,客户信息底表!G:G,,0),IFERROR(_xlfn.XLOOKUP(D43,客户信息底表!BD:BD,客户信息底表!G:G,,0),"底表未登记"))))) | I43: =IF(D43="","","整："&数据输入表!J46&"，散："&数据输入表!K46&"；重量kg："&数据输入表!L46&"，体积："&数据输入表!M46)
A44: =IF(D44<>"",$A$2,"") | C44: =IF(D44<>"",ROW()-1,"") | E44: =IF(D44="","",IFERROR(_xlfn.XLOOKUP(D44,客户信息底表!B:B,客户信息底表!Q:Q,,0),IFERROR(_xlfn.XLOOKUP(D44,客户信息底表!BB:BB,客户信息底表!Q:Q,,0),IFERROR(_xlfn.XLOOKUP(D44,客户信息底表!BC:BC,客户信息底表!Q:Q,,0),IFERROR(_xlfn.XLOOKUP(D44,客户信息底表!BD:BD,客户信息底表!Q:Q,,0),"底表未登记"))))) | G44: =IF(D44="","",IFERROR(_xlfn.XLOOKUP(D44,客户信息底表!B:B,客户信息底表!L:L,,0),IFERROR(_xlfn.XLOOKUP(D44,客户信息底表!BB:BB,客户信息底表!L:L,,0),IFERROR(_xlfn.XLOOKUP(D44,客户信息底表!BC:BC,客户信息底表!L:L,,0),IFERROR(_xlfn.XLOOKUP(D44,客户信息底表!BD:BD,客户信息底表!L:L,,0),"底表未登记"))))) | H44: =IF(D44="","",IFERROR(_xlfn.XLOOKUP(D44,客户信息底表!B:B,客户信息底表!G:G,,0),IFERROR(_xlfn.XLOOKUP(D44,客户信息底表!BB:BB,客户信息底表!G:G,,0),IFERROR(_xlfn.XLOOKUP(D44,客户信息底表!BC:BC,客户信息底表!G:G,,0),IFERROR(_xlfn.XLOOKUP(D44,客户信息底表!BD:BD,客户信息底表!G:G,,0),"底表未登记"))))) | I44: =IF(D44="","","整："&数据输入表!J47&"，散："&数据输入表!K47&"；重量kg："&数据输入表!L47&"，体积："&数据输入表!M47)
A45: =IF(D45<>"",$A$2,"") | C45: =IF(D45<>"",ROW()-1,"") | E45: =IF(D45="","",IFERROR(_xlfn.XLOOKUP(D45,客户信息底表!B:B,客户信息底表!Q:Q,,0),IFERROR(_xlfn.XLOOKUP(D45,客户信息底表!BB:BB,客户信息底表!Q:Q,,0),IFERROR(_xlfn.XLOOKUP(D45,客户信息底表!BC:BC,客户信息底表!Q:Q,,0),IFERROR(_xlfn.XLOOKUP(D45,客户信息底表!BD:BD,客户信息底表!Q:Q,,0),"底表未登记"))))) | G45: =IF(D45="","",IFERROR(_xlfn.XLOOKUP(D45,客户信息底表!B:B,客户信息底表!L:L,,0),IFERROR(_xlfn.XLOOKUP(D45,客户信息底表!BB:BB,客户信息底表!L:L,,0),IFERROR(_xlfn.XLOOKUP(D45,客户信息底表!BC:BC,客户信息底表!L:L,,0),IFERROR(_xlfn.XLOOKUP(D45,客户信息底表!BD:BD,客户信息底表!L:L,,0),"底表未登记"))))) | H45: =IF(D45="","",IFERROR(_xlfn.XLOOKUP(D45,客户信息底表!B:B,客户信息底表!G:G,,0),IFERROR(_xlfn.XLOOKUP(D45,客户信息底表!BB:BB,客户信息底表!G:G,,0),IFERROR(_xlfn.XLOOKUP(D45,客户信息底表!BC:BC,客户信息底表!G:G,,0),IFERROR(_xlfn.XLOOKUP(D45,客户信息底表!BD:BD,客户信息底表!G:G,,0),"底表未登记"))))) | I45: =IF(D45="","","整："&数据输入表!J48&"，散："&数据输入表!K48&"；重量kg："&数据输入表!L48&"，体积："&数据输入表!M48)
A46: =IF(D46<>"",$A$2,"") | C46: =IF(D46<>"",ROW()-1,"") | E46: =IF(D46="","",IFERROR(_xlfn.XLOOKUP(D46,客户信息底表!B:B,客户信息底表!Q:Q,,0),IFERROR(_xlfn.XLOOKUP(D46,客户信息底表!BB:BB,客户信息底表!Q:Q,,0),IFERROR(_xlfn.XLOOKUP(D46,客户信息底表!BC:BC,客户信息底表!Q:Q,,0),IFERROR(_xlfn.XLOOKUP(D46,客户信息底表!BD:BD,客户信息底表!Q:Q,,0),"底表未登记"))))) | G46: =IF(D46="","",IFERROR(_xlfn.XLOOKUP(D46,客户信息底表!B:B,客户信息底表!L:L,,0),IFERROR(_xlfn.XLOOKUP(D46,客户信息底表!BB:BB,客户信息底表!L:L,,0),IFERROR(_xlfn.XLOOKUP(D46,客户信息底表!BC:BC,客户信息底表!L:L,,0),IFERROR(_xlfn.XLOOKUP(D46,客户信息底表!BD:BD,客户信息底表!L:L,,0),"底表未登记"))))) | H46: =IF(D46="","",IFERROR(_xlfn.XLOOKUP(D46,客户信息底表!B:B,客户信息底表!G:G,,0),IFERROR(_xlfn.XLOOKUP(D46,客户信息底表!BB:BB,客户信息底表!G:G,,0),IFERROR(_xlfn.XLOOKUP(D46,客户信息底表!BC:BC,客户信息底表!G:G,,0),IFERROR(_xlfn.XLOOKUP(D46,客户信息底表!BD:BD,客户信息底表!G:G,,0),"底表未登记"))))) | I46: =IF(D46="","","整："&数据输入表!J49&"，散："&数据输入表!K49&"；重量kg："&数据输入表!L49&"，体积："&数据输入表!M49)
A47: =IF(D47<>"",$A$2,"") | C47: =IF(D47<>"",ROW()-1,"") | E47: =IF(D47="","",IFERROR(_xlfn.XLOOKUP(D47,客户信息底表!B:B,客户信息底表!Q:Q,,0),IFERROR(_xlfn.XLOOKUP(D47,客户信息底表!BB:BB,客户信息底表!Q:Q,,0),IFERROR(_xlfn.XLOOKUP(D47,客户信息底表!BC:BC,客户信息底表!Q:Q,,0),IFERROR(_xlfn.XLOOKUP(D47,客户信息底表!BD:BD,客户信息底表!Q:Q,,0),"底表未登记"))))) | G47: =IF(D47="","",IFERROR(_xlfn.XLOOKUP(D47,客户信息底表!B:B,客户信息底表!L:L,,0),IFERROR(_xlfn.XLOOKUP(D47,客户信息底表!BB:BB,客户信息底表!L:L,,0),IFERROR(_xlfn.XLOOKUP(D47,客户信息底表!BC:BC,客户信息底表!L:L,,0),IFERROR(_xlfn.XLOOKUP(D47,客户信息底表!BD:BD,客户信息底表!L:L,,0),"底表未登记"))))) | H47: =IF(D47="","",IFERROR(_xlfn.XLOOKUP(D47,客户信息底表!B:B,客户信息底表!G:G,,0),IFERROR(_xlfn.XLOOKUP(D47,客户信息底表!BB:BB,客户信息底表!G:G,,0),IFERROR(_xlfn.XLOOKUP(D47,客户信息底表!BC:BC,客户信息底表!G:G,,0),IFERROR(_xlfn.XLOOKUP(D47,客户信息底表!BD:BD,客户信息底表!G:G,,0),"底表未登记"))))) | I47: =IF(D47="","","整："&数据输入表!J50&"，散："&数据输入表!K50&"；重量kg："&数据输入表!L50&"，体积："&数据输入表!M50)
A48: =IF(D48<>"",$A$2,"") | C48: =IF(D48<>"",ROW()-1,"") | E48: =IF(D48="","",IFERROR(_xlfn.XLOOKUP(D48,客户信息底表!B:B,客户信息底表!Q:Q,,0),IFERROR(_xlfn.XLOOKUP(D48,客户信息底表!BB:BB,客户信息底表!Q:Q,,0),IFERROR(_xlfn.XLOOKUP(D48,客户信息底表!BC:BC,客户信息底表!Q:Q,,0),IFERROR(_xlfn.XLOOKUP(D48,客户信息底表!BD:BD,客户信息底表!Q:Q,,0),"底表未登记"))))) | G48: =IF(D48="","",IFERROR(_xlfn.XLOOKUP(D48,客户信息底表!B:B,客户信息底表!L:L,,0),IFERROR(_xlfn.XLOOKUP(D48,客户信息底表!BB:BB,客户信息底表!L:L,,0),IFERROR(_xlfn.XLOOKUP(D48,客户信息底表!BC:BC,客户信息底表!L:L,,0),IFERROR(_xlfn.XLOOKUP(D48,客户信息底表!BD:BD,客户信息底表!L:L,,0),"底表未登记"))))) | H48: =IF(D48="","",IFERROR(_xlfn.XLOOKUP(D48,客户信息底表!B:B,客户信息底表!G:G,,0),IFERROR(_xlfn.XLOOKUP(D48,客户信息底表!BB:BB,客户信息底表!G:G,,0),IFERROR(_xlfn.XLOOKUP(D48,客户信息底表!BC:BC,客户信息底表!G:G,,0),IFERROR(_xlfn.XLOOKUP(D48,客户信息底表!BD:BD,客户信息底表!G:G,,0),"底表未登记"))))) | I48: =IF(D48="","","整："&数据输入表!J51&"，散："&数据输入表!K51&"；重量kg："&数据输入表!L51&"，体积："&数据输入表!M51)
A49: =IF(D49<>"",$A$2,"") | C49: =IF(D49<>"",ROW()-1,"") | E49: =IF(D49="","",IFERROR(_xlfn.XLOOKUP(D49,客户信息底表!B:B,客户信息底表!Q:Q,,0),IFERROR(_xlfn.XLOOKUP(D49,客户信息底表!BB:BB,客户信息底表!Q:Q,,0),IFERROR(_xlfn.XLOOKUP(D49,客户信息底表!BC:BC,客户信息底表!Q:Q,,0),IFERROR(_xlfn.XLOOKUP(D49,客户信息底表!BD:BD,客户信息底表!Q:Q,,0),"底表未登记"))))) | G49: =IF(D49="","",IFERROR(_xlfn.XLOOKUP(D49,客户信息底表!B:B,客户信息底表!L:L,,0),IFERROR(_xlfn.XLOOKUP(D49,客户信息底表!BB:BB,客户信息底表!L:L,,0),IFERROR(_xlfn.XLOOKUP(D49,客户信息底表!BC:BC,客户信息底表!L:L,,0),IFERROR(_xlfn.XLOOKUP(D49,客户信息底表!BD:BD,客户信息底表!L:L,,0),"底表未登记"))))) | H49: =IF(D49="","",IFERROR(_xlfn.XLOOKUP(D49,客户信息底表!B:B,客户信息底表!G:G,,0),IFERROR(_xlfn.XLOOKUP(D49,客户信息底表!BB:BB,客户信息底表!G:G,,0),IFERROR(_xlfn.XLOOKUP(D49,客户信息底表!BC:BC,客户信息底表!G:G,,0),IFERROR(_xlfn.XLOOKUP(D49,客户信息底表!BD:BD,客户信息底表!G:G,,0),"底表未登记"))))) | I49: =IF(D49="","","整："&数据输入表!J52&"，散："&数据输入表!K52&"；重量kg："&数据输入表!L52&"，体积："&数据输入表!M52)
A50: =IF(D50<>"",$A$2,"") | C50: =IF(D50<>"",ROW()-1,"") | E50: =IF(D50="","",IFERROR(_xlfn.XLOOKUP(D50,客户信息底表!B:B,客户信息底表!Q:Q,,0),IFERROR(_xlfn.XLOOKUP(D50,客户信息底表!BB:BB,客户信息底表!Q:Q,,0),IFERROR(_xlfn.XLOOKUP(D50,客户信息底表!BC:BC,客户信息底表!Q:Q,,0),IFERROR(_xlfn.XLOOKUP(D50,客户信息底表!BD:BD,客户信息底表!Q:Q,,0),"底表未登记"))))) | G50: =IF(D50="","",IFERROR(_xlfn.XLOOKUP(D50,客户信息底表!B:B,客户信息底表!L:L,,0),IFERROR(_xlfn.XLOOKUP(D50,客户信息底表!BB:BB,客户信息底表!L:L,,0),IFERROR(_xlfn.XLOOKUP(D50,客户信息底表!BC:BC,客户信息底表!L:L,,0),IFERROR(_xlfn.XLOOKUP(D50,客户信息底表!BD:BD,客户信息底表!L:L,,0),"底表未登记"))))) | H50: =IF(D50="","",IFERROR(_xlfn.XLOOKUP(D50,客户信息底表!B:B,客户信息底表!G:G,,0),IFERROR(_xlfn.XLOOKUP(D50,客户信息底表!BB:BB,客户信息底表!G:G,,0),IFERROR(_xlfn.XLOOKUP(D50,客户信息底表!BC:BC,客户信息底表!G:G,,0),IFERROR(_xlfn.XLOOKUP(D50,客户信息底表!BD:BD,客户信息底表!G:G,,0),"底表未登记"))))) | I50: =IF(D50="","","整："&数据输入表!J53&"，散："&数据输入表!K53&"；重量kg："&数据输入表!L53&"，体积："&数据输入表!M53)
A51: =IF(D51<>"",$A$2,"") | C51: =IF(D51<>"",ROW()-1,"") | E51: =IF(D51="","",IFERROR(_xlfn.XLOOKUP(D51,客户信息底表!B:B,客户信息底表!Q:Q,,0),IFERROR(_xlfn.XLOOKUP(D51,客户信息底表!BB:BB,客户信息底表!Q:Q,,0),IFERROR(_xlfn.XLOOKUP(D51,客户信息底表!BC:BC,客户信息底表!Q:Q,,0),IFERROR(_xlfn.XLOOKUP(D51,客户信息底表!BD:BD,客户信息底表!Q:Q,,0),"底表未登记"))))) | G51: =IF(D51="","",IFERROR(_xlfn.XLOOKUP(D51,客户信息底表!B:B,客户信息底表!L:L,,0),IFERROR(_xlfn.XLOOKUP(D51,客户信息底表!BB:BB,客户信息底表!L:L,,0),IFERROR(_xlfn.XLOOKUP(D51,客户信息底表!BC:BC,客户信息底表!L:L,,0),IFERROR(_xlfn.XLOOKUP(D51,客户信息底表!BD:BD,客户信息底表!L:L,,0),"底表未登记"))))) | H51: =IF(D51="","",IFERROR(_xlfn.XLOOKUP(D51,客户信息底表!B:B,客户信息底表!G:G,,0),IFERROR(_xlfn.XLOOKUP(D51,客户信息底表!BB:BB,客户信息底表!G:G,,0),IFERROR(_xlfn.XLOOKUP(D51,客户信息底表!BC:BC,客户信息底表!G:G,,0),IFERROR(_xlfn.XLOOKUP(D51,客户信息底表!BD:BD,客户信息底表!G:G,,0),"底表未登记"))))) | I51: =IF(D51="","","整："&数据输入表!J54&"，散："&数据输入表!K54&"；重量kg："&数据输入表!L54&"，体积："&数据输入表!M54)
A52: =IF(D52<>"",$A$2,"") | C52: =IF(D52<>"",ROW()-1,"") | E52: =IF(D52="","",IFERROR(_xlfn.XLOOKUP(D52,客户信息底表!B:B,客户信息底表!Q:Q,,0),IFERROR(_xlfn.XLOOKUP(D52,客户信息底表!BB:BB,客户信息底表!Q:Q,,0),IFERROR(_xlfn.XLOOKUP(D52,客户信息底表!BC:BC,客户信息底表!Q:Q,,0),IFERROR(_xlfn.XLOOKUP(D52,客户信息底表!BD:BD,客户信息底表!Q:Q,,0),"底表未登记"))))) | G52: =IF(D52="","",IFERROR(_xlfn.XLOOKUP(D52,客户信息底表!B:B,客户信息底表!L:L,,0),IFERROR(_xlfn.XLOOKUP(D52,客户信息底表!BB:BB,客户信息底表!L:L,,0),IFERROR(_xlfn.XLOOKUP(D52,客户信息底表!BC:BC,客户信息底表!L:L,,0),IFERROR(_xlfn.XLOOKUP(D52,客户信息底表!BD:BD,客户信息底表!L:L,,0),"底表未登记"))))) | H52: =IF(D52="","",IFERROR(_xlfn.XLOOKUP(D52,客户信息底表!B:B,客户信息底表!G:G,,0),IFERROR(_xlfn.XLOOKUP(D52,客户信息底表!BB:BB,客户信息底表!G:G,,0),IFERROR(_xlfn.XLOOKUP(D52,客户信息底表!BC:BC,客户信息底表!G:G,,0),IFERROR(_xlfn.XLOOKUP(D52,客户信息底表!BD:BD,客户信息底表!G:G,,0),"底表未登记"))))) | I52: =IF(D52="","","整："&数据输入表!J55&"，散："&数据输入表!K55&"；重量kg："&数据输入表!L55&"，体积："&数据输入表!M55)
A53: =IF(D53<>"",$A$2,"") | C53: =IF(D53<>"",ROW()-1,"") | E53: =IF(D53="","",IFERROR(_xlfn.XLOOKUP(D53,客户信息底表!B:B,客户信息底表!Q:Q,,0),IFERROR(_xlfn.XLOOKUP(D53,客户信息底表!BB:BB,客户信息底表!Q:Q,,0),IFERROR(_xlfn.XLOOKUP(D53,客户信息底表!BC:BC,客户信息底表!Q:Q,,0),IFERROR(_xlfn.XLOOKUP(D53,客户信息底表!BD:BD,客户信息底表!Q:Q,,0),"底表未登记"))))) | G53: =IF(D53="","",IFERROR(_xlfn.XLOOKUP(D53,客户信息底表!B:B,客户信息底表!L:L,,0),IFERROR(_xlfn.XLOOKUP(D53,客户信息底表!BB:BB,客户信息底表!L:L,,0),IFERROR(_xlfn.XLOOKUP(D53,客户信息底表!BC:BC,客户信息底表!L:L,,0),IFERROR(_xlfn.XLOOKUP(D53,客户信息底表!BD:BD,客户信息底表!L:L,,0),"底表未登记"))))) | H53: =IF(D53="","",IFERROR(_xlfn.XLOOKUP(D53,客户信息底表!B:B,客户信息底表!G:G,,0),IFERROR(_xlfn.XLOOKUP(D53,客户信息底表!BB:BB,客户信息底表!G:G,,0),IFERROR(_xlfn.XLOOKUP(D53,客户信息底表!BC:BC,客户信息底表!G:G,,0),IFERROR(_xlfn.XLOOKUP(D53,客户信息底表!BD:BD,客户信息底表!G:G,,0),"底表未登记"))))) | I53: =IF(D53="","","整："&数据输入表!J56&"，散："&数据输入表!K56&"；重量kg："&数据输入表!L56&"，体积："&数据输入表!M56)
A54: =IF(D54<>"",$A$2,"") | C54: =IF(D54<>"",ROW()-1,"") | E54: =IF(D54="","",IFERROR(_xlfn.XLOOKUP(D54,客户信息底表!B:B,客户信息底表!Q:Q,,0),IFERROR(_xlfn.XLOOKUP(D54,客户信息底表!BB:BB,客户信息底表!Q:Q,,0),IFERROR(_xlfn.XLOOKUP(D54,客户信息底表!BC:BC,客户信息底表!Q:Q,,0),IFERROR(_xlfn.XLOOKUP(D54,客户信息底表!BD:BD,客户信息底表!Q:Q,,0),"底表未登记"))))) | G54: =IF(D54="","",IFERROR(_xlfn.XLOOKUP(D54,客户信息底表!B:B,客户信息底表!L:L,,0),IFERROR(_xlfn.XLOOKUP(D54,客户信息底表!BB:BB,客户信息底表!L:L,,0),IFERROR(_xlfn.XLOOKUP(D54,客户信息底表!BC:BC,客户信息底表!L:L,,0),IFERROR(_xlfn.XLOOKUP(D54,客户信息底表!BD:BD,客户信息底表!L:L,,0),"底表未登记"))))) | H54: =IF(D54="","",IFERROR(_xlfn.XLOOKUP(D54,客户信息底表!B:B,客户信息底表!G:G,,0),IFERROR(_xlfn.XLOOKUP(D54,客户信息底表!BB:BB,客户信息底表!G:G,,0),IFERROR(_xlfn.XLOOKUP(D54,客户信息底表!BC:BC,客户信息底表!G:G,,0),IFERROR(_xlfn.XLOOKUP(D54,客户信息底表!BD:BD,客户信息底表!G:G,,0),"底表未登记"))))) | I54: =IF(D54="","","整："&数据输入表!J57&"，散："&数据输入表!K57&"；重量kg："&数据输入表!L57&"，体积："&数据输入表!M57)
... A156: =IF(D156<>"",$A$2,"") | C156: =IF(D156<>"",ROW()-1,"") | E156: =IF(D156="","",IFERROR(_xlfn.XLOOKUP(D156,客户信息底表!B:B,客户信息底表!Q:Q,,0),IFERROR(_xlfn.XLOOKUP(D156,客户信息底表!BB:BB,客户信息底表!Q:Q,,0),IFERROR(_xlfn.XLOOKUP(D156,客户信息底表!BC:BC,客户信息底表!Q:Q,,0),IFERROR(_xlfn.XLOOKUP(D156,客户信息底表!BD:BD,客户信息底表!Q:Q,,0),"底表未登记"))))) | G156: =IF(D156="","",IFERROR(_xlfn.XLOOKUP(D156,客户信息底表!B:B,客户信息底表!L:L,,0),IFERROR(_xlfn.XLOOKUP(D156,客户信息底表!BB:BB,客户信息底表!L:L,,0),IFERROR(_xlfn.XLOOKUP(D156,客户信息底表!BC:BC,客户信息底表!L:L,,0),IFERROR(_xlfn.XLOOKUP(D156,客户信息底表!BD:BD,客户信息底表!L:L,,0),"底表未登记"))))) | H156: =IF(D156="","",IFERROR(_xlfn.XLOOKUP(D156,客户信息底表!B:B,客户信息底表!G:G,,0),IFERROR(_xlfn.XLOOKUP(D156,客户信息底表!BB:BB,客户信息底表!G:G,,0),IFERROR(_xlfn.XLOOKUP(D156,客户信息底表!BC:BC,客户信息底表!G:G,,0),IFERROR(_xlfn.XLOOKUP(D156,客户信息底表!BD:BD,客户信息底表!G:G,,0),"底表未登记"))))) | I156: =IF(D156="","","整："&数据输入表!J159&"，散："&数据输入表!K159&"；重量kg："&数据输入表!L159&"，体积："&数据输入表!M159)

Sheet CustomerLine
A1: 运单号 | B1: 门店节点编号 | C1: 客户编号 | D1: 客户名称 | E1: 联系人 | F1: 联系电话 | G1: 组织 | H1: 部门名称 | I1: 业务员 | J1: 渠道 | K1: 客户等级 | L1: 是否允许货到付款 | M1: 客户状态 | N1: 内部往来单位 | O1: 发票类型 | P1: 注册电话 | Q1: 注册地址 | R1: 客户序号 | S1: 客户地址 | T1: 省 | U1: 市 | V1: 区 | W1: 经度 | X1: 纬度 | Y1: 线路偏好 | Z1: 仓库偏好 | AA1: 停靠点顺序 | AB1: 开始收货时间 | AC1: 截止收货时间 | AD1: 收货时间段 | AE1: 不收货时间段 | AF1: 违停 | AG1: 免费停车时长_分钟 | AH1: 停车费_小时 | AI1: 停车位置 | AJ1: 停车方式 | AK1: 卸货入口 | AL1: 卸货位置 | AM1: 小巷子 | AN1: 手推车 | AO1: 托盘置换 | AP1: 保温箱置换 | AQ1: 上楼层数 | AR1: 地库限高 | AS1: 周一配送 | AT1: 周二配送 | AU1: 周三配送 | AV1: 周四配送 | AW1: 周五配送 | AX1: 周六配送 | AY1: 周日配送

Sheet OrderLine
A1: 订单行编号 | B1: 运单号 | C1: 门店节点编号 | D1: 单据号 | E1: 销售订单号 | F1: 来源参考号 | G1: 第三方单据号 | H1: 单据类型 | I1: 业务类型 | J1: 单据来源 | K1: 单据日期 | L1: 审核日期 | M1: 部门名称 | N1: 渠道 | O1: 业务员 | P1: 支付状态 | Q1: 结算状态 | R1: 单据状态 | S1: 物流状态 | T1: 制单人 | U1: 审核人 | V1: 创建日期 | W1: 订单备注 | X1: 自定义字段1

Sheet GoodsLine
A1: 订单行编号 | B1: 货号 | C1: 商品名称 | D1: 规格 | E1: 条码 | F1: 品牌 | G1: 类别 | H1: 基本单位 | I1: 单据单位 | J1: 小单位 | K1: 基本数量 | L1: 单据数量 | M1: 小单位数量 | N1: 箱数 | O1: 赠品数量 | P1: 换货数量 | Q1: 单据单价 | R1: 小单位单价 | S1: 金额 | T1: 已结算金额 | U1: 未结算金额 | V1: 税额 | W1: 不含税金额 | X1: 成本金额 | Y1: 毛利 | Z1: 毛利率 | AA1: 高于标准价 | AB1: 低于标准价 | AC1: 商品单件毛重 | AD1: 商品单件体积 | AE1: 总毛重 | AF1: 总体积 | AG1: 明细备注

Sheet 数据输入表
A1: 批次号（发车单号） | B1: LC20260421000980
A2: 原始数据（输入列） | H2: 汇总表
A3: 去重列 | B3: 保留列 | C3: 汇总列 | H3: 去重列 | I3: 保留列 | J3: 汇总列
A4: 收货单位 | B4: 收货地址 | C4: 整件数 | D4: 散件数 | E4: 重量 | F4: 方数 | H4: 收货单位 | J4: 整件数 | K4: 散件数 | L4: 重量 | M4: 方数
A5: 熊猫很忙（夏园店-广东广州） （直营） | B5: 广东省广州市黄埔区夏港街道临江路3号自编 102房熊猫很忙6688 | C5: 3 | D5: 39 | E5: 2.49 | F5: 0.01 | H5: {=_xlfn.UNIQUE(_xlfn._xlws.FILTER(SUBSTITUTE(SUBSTITUTE(A5:A10003,CHAR(13),""),CHAR(10),""),SUBSTITUTE(SUBSTITUTE(A5:A10003,CHAR(13),""),CHAR(10),"")<>""))} -> 熊猫很忙（夏园店-广东广州）（直营） | I5: {=IF(H5="","",_xlfn.XLOOKUP(H5,TRIM(SUBSTITUTE(SUBSTITUTE(A5:A10001,CHAR(13),""),CHAR(10),"")),B5:B10001,"报错",0))} -> 广东省广州市黄埔区夏港街道临江路3号自编 102房熊猫很忙6688 | J5: {=IF(H5="","",SUMPRODUCT((TRIM(SUBSTITUTE(SUBSTITUTE($A$5:$A$10003,CHAR(13),""),CHAR(10),""))=H5)*--$C$5:$C$10003))} -> 3 | K5: {=IF(H5="","",SUMPRODUCT((TRIM(SUBSTITUTE(SUBSTITUTE($A$5:$A$10003,CHAR(13),""),CHAR(10),""))=H5)*--$D$5:$D$10003))} -> 39 | L5: {=IF(H5="","",SUMPRODUCT((TRIM(SUBSTITUTE(SUBSTITUTE($A$5:$A$10003,CHAR(13),""),CHAR(10),""))=H5)*IFERROR(--$D$5:$D$10003,0)))} -> 39 | M5: {=IF(H5="","",SUMPRODUCT((TRIM(SUBSTITUTE(SUBSTITUTE($A$5:$A$10003,CHAR(13),""),CHAR(10),""))=H5)*IFERROR(--$F$5:$F$10003,0)))} -> 0.01
A6: 鲸选超市（广州板桥店) | B6: 广东省广州市番禺区南村镇南村镇兴南大道 902号板桥商务大厦3楼315号 | C6: 11 | D6: 190 | E6: 14.85 | F6: 0.03 | H6: 鲸选超市（广州板桥店) | I6: {=IF(H6="","",_xlfn.XLOOKUP(H6,TRIM(SUBSTITUTE(SUBSTITUTE(A6:A10002,CHAR(13),""),CHAR(10),"")),B6:B10002,"报错",0))} -> 广东省广州市番禺区南村镇南村镇兴南大道 902号板桥商务大厦3楼315号 | J6: {=IF(H6="","",SUMPRODUCT((TRIM(SUBSTITUTE(SUBSTITUTE($A$5:$A$10003,CHAR(13),""),CHAR(10),""))=H6)*--$C$5:$C$10003))} -> 11 | K6: {=IF(H6="","",SUMPRODUCT((TRIM(SUBSTITUTE(SUBSTITUTE($A$5:$A$10003,CHAR(13),""),CHAR(10),""))=H6)*--$D$5:$D$10003))} -> 190 | L6: {=IF(H6="","",SUMPRODUCT((TRIM(SUBSTITUTE(SUBSTITUTE($A$5:$A$10003,CHAR(13),""),CHAR(10),""))=H6)*IFERROR(--$D$5:$D$10003,0)))} -> 190 | M6: {=IF(H6="","",SUMPRODUCT((TRIM(SUBSTITUTE(SUBSTITUTE($A$5:$A$10003,CHAR(13),""),CHAR(10),""))=H6)*IFERROR(--$F$5:$F$10003,0)))} -> 0.03
A7: 鲸选超市（广州番禺店) | B7: 广东省广州市番禺区南村镇南村镇敏捷上城国 际【2期2座112店铺2楼京东便利店仓库】 | C7: 4 | D7: 110 | E7: 8.28 | F7: 0.01 | H7: 鲸选超市（广州番禺店) | I7: {=IF(H7="","",_xlfn.XLOOKUP(H7,TRIM(SUBSTITUTE(SUBSTITUTE(A7:A10003,CHAR(13),""),CHAR(10),"")),B7:B10003,"报错",0))} -> 广东省广州市番禺区南村镇南村镇敏捷上城国 际【2期2座112店铺2楼京东便利店仓库】 | J7: {=IF(H7="","",SUMPRODUCT((TRIM(SUBSTITUTE(SUBSTITUTE($A$5:$A$10003,CHAR(13),""),CHAR(10),""))=H7)*--$C$5:$C$10003))} -> 4 | K7: {=IF(H7="","",SUMPRODUCT((TRIM(SUBSTITUTE(SUBSTITUTE($A$5:$A$10003,CHAR(13),""),CHAR(10),""))=H7)*--$D$5:$D$10003))} -> 110 | L7: {=IF(H7="","",SUMPRODUCT((TRIM(SUBSTITUTE(SUBSTITUTE($A$5:$A$10003,CHAR(13),""),CHAR(10),""))=H7)*IFERROR(--$D$5:$D$10003,0)))} -> 110 | M7: {=IF(H7="","",SUMPRODUCT((TRIM(SUBSTITUTE(SUBSTITUTE($A$5:$A$10003,CHAR(13),""),CHAR(10),""))=H7)*IFERROR(--$F$5:$F$10003,0)))} -> 0.01
A8: 时光里便利超市（广州番禺万博店） | B8: 广东省广州市番禺区南村镇南村镇登云大路 2号之六105房 | C8: 6 | D8: 107 | E8: 20.02 | F8: 0.05 | H8: 时光里便利超市（广州番禺万博店） | I8: {=IF(H8="","",_xlfn.XLOOKUP(H8,TRIM(SUBSTITUTE(SUBSTITUTE(A8:A10004,CHAR(13),""),CHAR(10),"")),B8:B10004,"报错",0))} -> 广东省广州市番禺区南村镇南村镇登云大路 2号之六105房 | J8: {=IF(H8="","",SUMPRODUCT((TRIM(SUBSTITUTE(SUBSTITUTE($A$5:$A$10003,CHAR(13),""),CHAR(10),""))=H8)*--$C$5:$C$10003))} -> 6 | K8: {=IF(H8="","",SUMPRODUCT((TRIM(SUBSTITUTE(SUBSTITUTE($A$5:$A$10003,CHAR(13),""),CHAR(10),""))=H8)*--$D$5:$D$10003))} -> 107 | L8: {=IF(H8="","",SUMPRODUCT((TRIM(SUBSTITUTE(SUBSTITUTE($A$5:$A$10003,CHAR(13),""),CHAR(10),""))=H8)*IFERROR(--$D$5:$D$10003,0)))} -> 107 | M8: {=IF(H8="","",SUMPRODUCT((TRIM(SUBSTITUTE(SUBSTITUTE($A$5:$A$10003,CHAR(13),""),CHAR(10),""))=H8)*IFERROR(--$F$5:$F$10003,0)))} -> 0.05
A9: 熊猫很忙（大石店-广东广州） | B9: 广东省广州市番禺区大石街道大石街大山村富 山路四街1号胜文工业园2栋1楼103室 | C9: 2 | D9: 125 | E9: 4.57 | F9: 0.01 | H9: 熊猫很忙（大石店-广东广州） | I9: {=IF(H9="","",_xlfn.XLOOKUP(H9,TRIM(SUBSTITUTE(SUBSTITUTE(A9:A10005,CHAR(13),""),CHAR(10),"")),B9:B10005,"报错",0))} -> 广东省广州市番禺区大石街道大石街大山村富 山路四街1号胜文工业园2栋1楼103室 | J9: {=IF(H9="","",SUMPRODUCT((TRIM(SUBSTITUTE(SUBSTITUTE($A$5:$A$10003,CHAR(13),""),CHAR(10),""))=H9)*--$C$5:$C$10003))} -> 2 | K9: {=IF(H9="","",SUMPRODUCT((TRIM(SUBSTITUTE(SUBSTITUTE($A$5:$A$10003,CHAR(13),""),CHAR(10),""))=H9)*--$D$5:$D$10003))} -> 125 | L9: {=IF(H9="","",SUMPRODUCT((TRIM(SUBSTITUTE(SUBSTITUTE($A$5:$A$10003,CHAR(13),""),CHAR(10),""))=H9)*IFERROR(--$D$5:$D$10003,0)))} -> 125 | M9: {=IF(H9="","",SUMPRODUCT((TRIM(SUBSTITUTE(SUBSTITUTE($A$5:$A$10003,CHAR(13),""),CHAR(10),""))=H9)*IFERROR(--$F$5:$F$10003,0)))} -> 0.01
A10: 值小团（广州大石店） | B10: 广东省广州市番禺区大石街道大石街道大石镇 朝阳东路170号201房值小团超市（原玲丰服饰 ) | C10: 3 | D10: 60 | E10: 5.18 | F10: 0.01 | H10: 值小团（广州大石店） | I10: {=IF(H10="","",_xlfn.XLOOKUP(H10,TRIM(SUBSTITUTE(SUBSTITUTE(A10:A10006,CHAR(13),""),CHAR(10),"")),B10:B10006,"报错",0))} -> 广东省广州市番禺区大石街道大石街道大石镇 朝阳东路170号201房值小团超市（原玲丰服饰 ) | J10: {=IF(H10="","",SUMPRODUCT((TRIM(SUBSTITUTE(SUBSTITUTE($A$5:$A$10003,CHAR(13),""),CHAR(10),""))=H10)*--$C$5:$C$10003))} -> 3 | K10: {=IF(H10="","",SUMPRODUCT((TRIM(SUBSTITUTE(SUBSTITUTE($A$5:$A$10003,CHAR(13),""),CHAR(10),""))=H10)*--$D$5:$D$10003))} -> 60 | L10: {=IF(H10="","",SUMPRODUCT((TRIM(SUBSTITUTE(SUBSTITUTE($A$5:$A$10003,CHAR(13),""),CHAR(10),""))=H10)*IFERROR(--$D$5:$D$10003,0)))} -> 60 | M10: {=IF(H10="","",SUMPRODUCT((TRIM(SUBSTITUTE(SUBSTITUTE($A$5:$A$10003,CHAR(13),""),CHAR(10),""))=H10)*IFERROR(--$F$5:$F$10003,0)))} -> 0.01
A11: 鲸选超市（广州大石店) | B11: 广东省广州市番禺区大石街道大石街道大涌路 157号大石伟讯电子数码城4楼421铺 | C11: 9 | D11: 207 | E11: 15.23 | F11: 0.03 | H11: 鲸选超市（广州大石店) | I11: {=IF(H11="","",_xlfn.XLOOKUP(H11,TRIM(SUBSTITUTE(SUBSTITUTE(A11:A10007,CHAR(13),""),CHAR(10),"")),B11:B10007,"报错",0))} -> 广东省广州市番禺区大石街道大石街道大涌路 157号大石伟讯电子数码城4楼421铺 | J11: {=IF(H11="","",SUMPRODUCT((TRIM(SUBSTITUTE(SUBSTITUTE($A$5:$A$10003,CHAR(13),""),CHAR(10),""))=H11)*--$C$5:$C$10003))} -> 9 | K11: {=IF(H11="","",SUMPRODUCT((TRIM(SUBSTITUTE(SUBSTITUTE($A$5:$A$10003,CHAR(13),""),CHAR(10),""))=H11)*--$D$5:$D$10003))} -> 207 | L11: {=IF(H11="","",SUMPRODUCT((TRIM(SUBSTITUTE(SUBSTITUTE($A$5:$A$10003,CHAR(13),""),CHAR(10),""))=H11)*IFERROR(--$D$5:$D$10003,0)))} -> 207 | M11: {=IF(H11="","",SUMPRODUCT((TRIM(SUBSTITUTE(SUBSTITUTE($A$5:$A$10003,CHAR(13),""),CHAR(10),""))=H11)*IFERROR(--$F$5:$F$10003,0)))} -> 0.03
A12: 熊猫很忙（鹤洞店-广东广州）（直营） | B12: 广东省广州市荔湾区白鹤洞街道鹤洞路346号 218室2楼送货上门6688不放驿站 | C12: 6 | D12: 102 | E12: 6.15 | F12: 0.01 | H12: 熊猫很忙（鹤洞店-广东广州）（直营） | I12: {=IF(H12="","",_xlfn.XLOOKUP(H12,TRIM(SUBSTITUTE(SUBSTITUTE(A12:A10008,CHAR(13),""),CHAR(10),"")),B12:B10008,"报错",0))} -> 广东省广州市荔湾区白鹤洞街道鹤洞路346号 218室2楼送货上门6688不放驿站 | J12: {=IF(H12="","",SUMPRODUCT((TRIM(SUBSTITUTE(SUBSTITUTE($A$5:$A$10003,CHAR(13),""),CHAR(10),""))=H12)*--$C$5:$C$10003))} -> 6 | K12: {=IF(H12="","",SUMPRODUCT((TRIM(SUBSTITUTE(SUBSTITUTE($A$5:$A$10003,CHAR(13),""),CHAR(10),""))=H12)*--$D$5:$D$10003))} -> 102 | L12: {=IF(H12="","",SUMPRODUCT((TRIM(SUBSTITUTE(SUBSTITUTE($A$5:$A$10003,CHAR(13),""),CHAR(10),""))=H12)*IFERROR(--$D$5:$D$10003,0)))} -> 102 | M12: {=IF(H12="","",SUMPRODUCT((TRIM(SUBSTITUTE(SUBSTITUTE($A$5:$A$10003,CHAR(13),""),CHAR(10),""))=H12)*IFERROR(--$F$5:$F$10003,0)))} -> 0.01
A13: 值小团（广州芳村店） | B13: 广东省广州市荔湾区白鹤洞街道坑口大街 138 号红岗工业区1 号首层 101、102 室 | C13: 7 | D13: 114 | E13: 12.6 | F13: 0.03 | H13: 值小团（广州芳村店） | I13: {=IF(H13="","",_xlfn.XLOOKUP(H13,TRIM(SUBSTITUTE(SUBSTITUTE(A13:A10009,CHAR(13),""),CHAR(10),"")),B13:B10009,"报错",0))} -> 广东省广州市荔湾区白鹤洞街道坑口大街 138 号红岗工业区1 号首层 101、102 室 | J13: {=IF(H13="","",SUMPRODUCT((TRIM(SUBSTITUTE(SUBSTITUTE($A$5:$A$10003,CHAR(13),""),CHAR(10),""))=H13)*--$C$5:$C$10003))} -> 7 | K13: {=IF(H13="","",SUMPRODUCT((TRIM(SUBSTITUTE(SUBSTITUTE($A$5:$A$10003,CHAR(13),""),CHAR(10),""))=H13)*--$D$5:$D$10003))} -> 114 | L13: {=IF(H13="","",SUMPRODUCT((TRIM(SUBSTITUTE(SUBSTITUTE($A$5:$A$10003,CHAR(13),""),CHAR(10),""))=H13)*IFERROR(--$D$5:$D$10003,0)))} -> 114 | M13: {=IF(H13="","",SUMPRODUCT((TRIM(SUBSTITUTE(SUBSTITUTE($A$5:$A$10003,CHAR(13),""),CHAR(10),""))=H13)*IFERROR(--$F$5:$F$10003,0)))} -> 0.03
A14: 鲸选超市（广州芳村店) | B14: 广东省广州市荔湾区冲口街道花溪路3号 坑口 工业区1栋2楼215鲸选超市里面(有电梯) | C14: 6 | D14: 162 | E14: 11.57 | F14: 0.02 | H14: 鲸选超市（广州芳村店) | I14: {=IF(H14="","",_xlfn.XLOOKUP(H14,TRIM(SUBSTITUTE(SUBSTITUTE(A14:A10010,CHAR(13),""),CHAR(10),"")),B14:B10010,"报错",0))} -> 广东省广州市荔湾区冲口街道花溪路3号 坑口 工业区1栋2楼215鲸选超市里面(有电梯) | J14: {=IF(H14="","",SUMPRODUCT((TRIM(SUBSTITUTE(SUBSTITUTE($A$5:$A$10003,CHAR(13),""),CHAR(10),""))=H14)*--$C$5:$C$10003))} -> 6 | K14: {=IF(H14="","",SUMPRODUCT((TRIM(SUBSTITUTE(SUBSTITUTE($A$5:$A$10003,CHAR(13),""),CHAR(10),""))=H14)*--$D$5:$D$10003))} -> 162 | L14: {=IF(H14="","",SUMPRODUCT((TRIM(SUBSTITUTE(SUBSTITUTE($A$5:$A$10003,CHAR(13),""),CHAR(10),""))=H14)*IFERROR(--$D$5:$D$10003,0)))} -> 162 | M14: {=IF(H14="","",SUMPRODUCT((TRIM(SUBSTITUTE(SUBSTITUTE($A$5:$A$10003,CHAR(13),""),CHAR(10),""))=H14)*IFERROR(--$F$5:$F$10003,0)))} -> 0.02
A15: 畅盈到家超市（广州海珠店） | B15: 广东省广州市海珠区南石头街道南石头街道工 业大道中路385号大院11号楼224房 | C15: 8 | D15: 56 | E15: 50.61 | F15: 0.1 | H15: 畅盈到家超市（广州海珠店） | I15: {=IF(H15="","",_xlfn.XLOOKUP(H15,TRIM(SUBSTITUTE(SUBSTITUTE(A15:A10011,CHAR(13),""),CHAR(10),"")),B15:B10011,"报错",0))} -> 广东省广州市海珠区南石头街道南石头街道工 业大道中路385号大院11号楼224房 | J15: {=IF(H15="","",SUMPRODUCT((TRIM(SUBSTITUTE(SUBSTITUTE($A$5:$A$10003,CHAR(13),""),CHAR(10),""))=H15)*--$C$5:$C$10003))} -> 9 | K15: {=IF(H15="","",SUMPRODUCT((TRIM(SUBSTITUTE(SUBSTITUTE($A$5:$A$10003,CHAR(13),""),CHAR(10),""))=H15)*--$D$5:$D$10003))} -> 178 | L15: {=IF(H15="","",SUMPRODUCT((TRIM(SUBSTITUTE(SUBSTITUTE($A$5:$A$10003,CHAR(13),""),CHAR(10),""))=H15)*IFERROR(--$D$5:$D$10003,0)))} -> 178 | M15: {=IF(H15="","",SUMPRODUCT((TRIM(SUBSTITUTE(SUBSTITUTE($A$5:$A$10003,CHAR(13),""),CHAR(10),""))=H15)*IFERROR(--$F$5:$F$10003,0)))} -> 0.12
A16: 畅盈到家超市（广州海珠店） | B16: 广东省广州市海珠区南石头街道南石头街道工 业大道中路385号大院11号楼224房 | C16: 1 | D16: 122 | E16: 8.26 | F16: 0.02 | H16: 值小团（广州海珠店） | I16: {=IF(H16="","",_xlfn.XLOOKUP(H16,TRIM(SUBSTITUTE(SUBSTITUTE(A16:A10012,CHAR(13),""),CHAR(10),"")),B16:B10012,"报错",0))} -> 广东省广州市海珠区昌岗街道信雅路54 | J16: {=IF(H16="","",SUMPRODUCT((TRIM(SUBSTITUTE(SUBSTITUTE($A$5:$A$10003,CHAR(13),""),CHAR(10),""))=H16)*--$C$5:$C$10003))} -> 12 | K16: {=IF(H16="","",SUMPRODUCT((TRIM(SUBSTITUTE(SUBSTITUTE($A$5:$A$10003,CHAR(13),""),CHAR(10),""))=H16)*--$D$5:$D$10003))} -> 135 | L16: {=IF(H16="","",SUMPRODUCT((TRIM(SUBSTITUTE(SUBSTITUTE($A$5:$A$10003,CHAR(13),""),CHAR(10),""))=H16)*IFERROR(--$D$5:$D$10003,0)))} -> 135 | M16: {=IF(H16="","",SUMPRODUCT((TRIM(SUBSTITUTE(SUBSTITUTE($A$5:$A$10003,CHAR(13),""),CHAR(10),""))=H16)*IFERROR(--$F$5:$F$10003,0)))} -> 0.17
A17: 值小团（广州海珠店） | B17: 广东省广州市海珠区昌岗街道信雅路54 | C17: 7 | D17: 15 | E17: 31.75 | F17: 0.15 | I17: {=IF(H17="","",_xlfn.XLOOKUP(H17,TRIM(SUBSTITUTE(SUBSTITUTE(A17:A10013,CHAR(13),""),CHAR(10),"")),B17:B10013,"报错",0))} | J17: {=IF(H17="","",SUMPRODUCT((TRIM(SUBSTITUTE(SUBSTITUTE($A$5:$A$10003,CHAR(13),""),CHAR(10),""))=H17)*--$C$5:$C$10003))} | K17: {=IF(H17="","",SUMPRODUCT((TRIM(SUBSTITUTE(SUBSTITUTE($A$5:$A$10003,CHAR(13),""),CHAR(10),""))=H17)*--$D$5:$D$10003))} | L17: {=IF(H17="","",SUMPRODUCT((TRIM(SUBSTITUTE(SUBSTITUTE($A$5:$A$10003,CHAR(13),""),CHAR(10),""))=H17)*IFERROR(--$D$5:$D$10003,0)))} | M17: {=IF(H17="","",SUMPRODUCT((TRIM(SUBSTITUTE(SUBSTITUTE($A$5:$A$10003,CHAR(13),""),CHAR(10),""))=H17)*IFERROR(--$F$5:$F$10003,0)))}
A18: 值小团（广州海珠店） | B18: 广东省广州市海珠区昌岗街道信雅路54 | C18: 5 | D18: 120 | E18: 9.85 | F18: 0.02 | I18: {=IF(H18="","",_xlfn.XLOOKUP(H18,TRIM(SUBSTITUTE(SUBSTITUTE(A18:A10014,CHAR(13),""),CHAR(10),"")),B18:B10014,"报错",0))} | J18: {=IF(H18="","",SUMPRODUCT((TRIM(SUBSTITUTE(SUBSTITUTE($A$5:$A$10003,CHAR(13),""),CHAR(10),""))=H18)*--$C$5:$C$10003))} | K18: {=IF(H18="","",SUMPRODUCT((TRIM(SUBSTITUTE(SUBSTITUTE($A$5:$A$10003,CHAR(13),""),CHAR(10),""))=H18)*--$D$5:$D$10003))} | L18: {=IF(H18="","",SUMPRODUCT((TRIM(SUBSTITUTE(SUBSTITUTE($A$5:$A$10003,CHAR(13),""),CHAR(10),""))=H18)*IFERROR(--$D$5:$D$10003,0)))} | M18: {=IF(H18="","",SUMPRODUCT((TRIM(SUBSTITUTE(SUBSTITUTE($A$5:$A$10003,CHAR(13),""),CHAR(10),""))=H18)*IFERROR(--$F$5:$F$10003,0)))}
I19: {=IF(H19="","",_xlfn.XLOOKUP(H19,TRIM(SUBSTITUTE(SUBSTITUTE(A19:A10015,CHAR(13),""),CHAR(10),"")),B19:B10015,"报错",0))} | J19: {=IF(H19="","",SUMPRODUCT((TRIM(SUBSTITUTE(SUBSTITUTE($A$5:$A$10003,CHAR(13),""),CHAR(10),""))=H19)*--$C$5:$C$10003))} | K19: {=IF(H19="","",SUMPRODUCT((TRIM(SUBSTITUTE(SUBSTITUTE($A$5:$A$10003,CHAR(13),""),CHAR(10),""))=H19)*--$D$5:$D$10003))} | L19: {=IF(H19="","",SUMPRODUCT((TRIM(SUBSTITUTE(SUBSTITUTE($A$5:$A$10003,CHAR(13),""),CHAR(10),""))=H19)*IFERROR(--$D$5:$D$10003,0)))} | M19: {=IF(H19="","",SUMPRODUCT((TRIM(SUBSTITUTE(SUBSTITUTE($A$5:$A$10003,CHAR(13),""),CHAR(10),""))=H19)*IFERROR(--$F$5:$F$10003,0)))}
I20: {=IF(H20="","",_xlfn.XLOOKUP(H20,TRIM(SUBSTITUTE(SUBSTITUTE(A20:A10016,CHAR(13),""),CHAR(10),"")),B20:B10016,"报错",0))} | J20: {=IF(H20="","",SUMPRODUCT((TRIM(SUBSTITUTE(SUBSTITUTE($A$5:$A$10003,CHAR(13),""),CHAR(10),""))=H20)*--$C$5:$C$10003))} | K20: {=IF(H20="","",SUMPRODUCT((TRIM(SUBSTITUTE(SUBSTITUTE($A$5:$A$10003,CHAR(13),""),CHAR(10),""))=H20)*--$D$5:$D$10003))} | L20: {=IF(H20="","",SUMPRODUCT((TRIM(SUBSTITUTE(SUBSTITUTE($A$5:$A$10003,CHAR(13),""),CHAR(10),""))=H20)*IFERROR(--$D$5:$D$10003,0)))} | M20: {=IF(H20="","",SUMPRODUCT((TRIM(SUBSTITUTE(SUBSTITUTE($A$5:$A$10003,CHAR(13),""),CHAR(10),""))=H20)*IFERROR(--$F$5:$F$10003,0)))}
I21: {=IF(H21="","",_xlfn.XLOOKUP(H21,TRIM(SUBSTITUTE(SUBSTITUTE(A21:A10017,CHAR(13),""),CHAR(10),"")),B21:B10017,"报错",0))} | J21: {=IF(H21="","",SUMPRODUCT((TRIM(SUBSTITUTE(SUBSTITUTE($A$5:$A$10003,CHAR(13),""),CHAR(10),""))=H21)*--$C$5:$C$10003))} | K21: {=IF(H21="","",SUMPRODUCT((TRIM(SUBSTITUTE(SUBSTITUTE($A$5:$A$10003,CHAR(13),""),CHAR(10),""))=H21)*--$D$5:$D$10003))} | L21: {=IF(H21="","",SUMPRODUCT((TRIM(SUBSTITUTE(SUBSTITUTE($A$5:$A$10003,CHAR(13),""),CHAR(10),""))=H21)*IFERROR(--$D$5:$D$10003,0)))} | M21: {=IF(H21="","",SUMPRODUCT((TRIM(SUBSTITUTE(SUBSTITUTE($A$5:$A$10003,CHAR(13),""),CHAR(10),""))=H21)*IFERROR(--$F$5:$F$10003,0)))}
I22: {=IF(H22="","",_xlfn.XLOOKUP(H22,TRIM(SUBSTITUTE(SUBSTITUTE(A22:A10018,CHAR(13),""),CHAR(10),"")),B22:B10018,"报错",0))} | J22: {=IF(H22="","",SUMPRODUCT((TRIM(SUBSTITUTE(SUBSTITUTE($A$5:$A$10003,CHAR(13),""),CHAR(10),""))=H22)*--$C$5:$C$10003))} | K22: {=IF(H22="","",SUMPRODUCT((TRIM(SUBSTITUTE(SUBSTITUTE($A$5:$A$10003,CHAR(13),""),CHAR(10),""))=H22)*--$D$5:$D$10003))} | L22: {=IF(H22="","",SUMPRODUCT((TRIM(SUBSTITUTE(SUBSTITUTE($A$5:$A$10003,CHAR(13),""),CHAR(10),""))=H22)*IFERROR(--$D$5:$D$10003,0)))} | M22: {=IF(H22="","",SUMPRODUCT((TRIM(SUBSTITUTE(SUBSTITUTE($A$5:$A$10003,CHAR(13),""),CHAR(10),""))=H22)*IFERROR(--$F$5:$F$10003,0)))}
I23: {=IF(H23="","",_xlfn.XLOOKUP(H23,TRIM(SUBSTITUTE(SUBSTITUTE(A23:A10019,CHAR(13),""),CHAR(10),"")),B23:B10019,"报错",0))} | J23: {=IF(H23="","",SUMPRODUCT((TRIM(SUBSTITUTE(SUBSTITUTE($A$5:$A$10003,CHAR(13),""),CHAR(10),""))=H23)*--$C$5:$C$10003))} | K23: {=IF(H23="","",SUMPRODUCT((TRIM(SUBSTITUTE(SUBSTITUTE($A$5:$A$10003,CHAR(13),""),CHAR(10),""))=H23)*--$D$5:$D$10003))} | L23: {=IF(H23="","",SUMPRODUCT((TRIM(SUBSTITUTE(SUBSTITUTE($A$5:$A$10003,CHAR(13),""),CHAR(10),""))=H23)*IFERROR(--$D$5:$D$10003,0)))} | M23: {=IF(H23="","",SUMPRODUCT((TRIM(SUBSTITUTE(SUBSTITUTE($A$5:$A$10003,CHAR(13),""),CHAR(10),""))=H23)*IFERROR(--$F$5:$F$10003,0)))}
I24: {=IF(H24="","",_xlfn.XLOOKUP(H24,TRIM(SUBSTITUTE(SUBSTITUTE(A24:A10020,CHAR(13),""),CHAR(10),"")),B24:B10020,"报错",0))} | J24: {=IF(H24="","",SUMPRODUCT((TRIM(SUBSTITUTE(SUBSTITUTE($A$5:$A$10003,CHAR(13),""),CHAR(10),""))=H24)*--$C$5:$C$10003))} | K24: {=IF(H24="","",SUMPRODUCT((TRIM(SUBSTITUTE(SUBSTITUTE($A$5:$A$10003,CHAR(13),""),CHAR(10),""))=H24)*--$D$5:$D$10003))} | L24: {=IF(H24="","",SUMPRODUCT((TRIM(SUBSTITUTE(SUBSTITUTE($A$5:$A$10003,CHAR(13),""),CHAR(10),""))=H24)*IFERROR(--$D$5:$D$10003,0)))} | M24: {=IF(H24="","",SUMPRODUCT((TRIM(SUBSTITUTE(SUBSTITUTE($A$5:$A$10003,CHAR(13),""),CHAR(10),""))=H24)*IFERROR(--$F$5:$F$10003,0)))}
I25: {=IF(H25="","",_xlfn.XLOOKUP(H25,TRIM(SUBSTITUTE(SUBSTITUTE(A25:A10021,CHAR(13),""),CHAR(10),"")),B25:B10021,"报错",0))} | J25: {=IF(H25="","",SUMPRODUCT((TRIM(SUBSTITUTE(SUBSTITUTE($A$5:$A$10003,CHAR(13),""),CHAR(10),""))=H25)*--$C$5:$C$10003))} | K25: {=IF(H25="","",SUMPRODUCT((TRIM(SUBSTITUTE(SUBSTITUTE($A$5:$A$10003,CHAR(13),""),CHAR(10),""))=H25)*--$D$5:$D$10003))} | L25: {=IF(H25="","",SUMPRODUCT((TRIM(SUBSTITUTE(SUBSTITUTE($A$5:$A$10003,CHAR(13),""),CHAR(10),""))=H25)*IFERROR(--$D$5:$D$10003,0)))} | M25: {=IF(H25="","",SUMPRODUCT((TRIM(SUBSTITUTE(SUBSTITUTE($A$5:$A$10003,CHAR(13),""),CHAR(10),""))=H25)*IFERROR(--$F$5:$F$10003,0)))}
I26: {=IF(H26="","",_xlfn.XLOOKUP(H26,TRIM(SUBSTITUTE(SUBSTITUTE(A26:A10022,CHAR(13),""),CHAR(10),"")),B26:B10022,"报错",0))} | J26: {=IF(H26="","",SUMPRODUCT((TRIM(SUBSTITUTE(SUBSTITUTE($A$5:$A$10003,CHAR(13),""),CHAR(10),""))=H26)*--$C$5:$C$10003))} | K26: {=IF(H26="","",SUMPRODUCT((TRIM(SUBSTITUTE(SUBSTITUTE($A$5:$A$10003,CHAR(13),""),CHAR(10),""))=H26)*--$D$5:$D$10003))} | L26: {=IF(H26="","",SUMPRODUCT((TRIM(SUBSTITUTE(SUBSTITUTE($A$5:$A$10003,CHAR(13),""),CHAR(10),""))=H26)*IFERROR(--$D$5:$D$10003,0)))} | M26: {=IF(H26="","",SUMPRODUCT((TRIM(SUBSTITUTE(SUBSTITUTE($A$5:$A$10003,CHAR(13),""),CHAR(10),""))=H26)*IFERROR(--$F$5:$F$10003,0)))}
I27: {=IF(H27="","",_xlfn.XLOOKUP(H27,TRIM(SUBSTITUTE(SUBSTITUTE(A27:A10023,CHAR(13),""),CHAR(10),"")),B27:B10023,"报错",0))} | J27: {=IF(H27="","",SUMPRODUCT((TRIM(SUBSTITUTE(SUBSTITUTE($A$5:$A$10003,CHAR(13),""),CHAR(10),""))=H27)*--$C$5:$C$10003))} | K27: {=IF(H27="","",SUMPRODUCT((TRIM(SUBSTITUTE(SUBSTITUTE($A$5:$A$10003,CHAR(13),""),CHAR(10),""))=H27)*--$D$5:$D$10003))} | L27: {=IF(H27="","",SUMPRODUCT((TRIM(SUBSTITUTE(SUBSTITUTE($A$5:$A$10003,CHAR(13),""),CHAR(10),""))=H27)*IFERROR(--$D$5:$D$10003,0)))} | M27: {=IF(H27="","",SUMPRODUCT((TRIM(SUBSTITUTE(SUBSTITUTE($A$5:$A$10003,CHAR(13),""),CHAR(10),""))=H27)*IFERROR(--$F$5:$F$10003,0)))}
I28: {=IF(H28="","",_xlfn.XLOOKUP(H28,TRIM(SUBSTITUTE(SUBSTITUTE(A28:A10024,CHAR(13),""),CHAR(10),"")),B28:B10024,"报错",0))} | J28: {=IF(H28="","",SUMPRODUCT((TRIM(SUBSTITUTE(SUBSTITUTE($A$5:$A$10003,CHAR(13),""),CHAR(10),""))=H28)*--$C$5:$C$10003))} | K28: {=IF(H28="","",SUMPRODUCT((TRIM(SUBSTITUTE(SUBSTITUTE($A$5:$A$10003,CHAR(13),""),CHAR(10),""))=H28)*--$D$5:$D$10003))} | L28: {=IF(H28="","",SUMPRODUCT((TRIM(SUBSTITUTE(SUBSTITUTE($A$5:$A$10003,CHAR(13),""),CHAR(10),""))=H28)*IFERROR(--$D$5:$D$10003,0)))} | M28: {=IF(H28="","",SUMPRODUCT((TRIM(SUBSTITUTE(SUBSTITUTE($A$5:$A$10003,CHAR(13),""),CHAR(10),""))=H28)*IFERROR(--$F$5:$F$10003,0)))}
I29: {=IF(H29="","",_xlfn.XLOOKUP(H29,TRIM(SUBSTITUTE(SUBSTITUTE(A29:A10025,CHAR(13),""),CHAR(10),"")),B29:B10025,"报错",0))} | J29: {=IF(H29="","",SUMPRODUCT((TRIM(SUBSTITUTE(SUBSTITUTE($A$5:$A$10003,CHAR(13),""),CHAR(10),""))=H29)*--$C$5:$C$10003))} | K29: {=IF(H29="","",SUMPRODUCT((TRIM(SUBSTITUTE(SUBSTITUTE($A$5:$A$10003,CHAR(13),""),CHAR(10),""))=H29)*--$D$5:$D$10003))} | L29: {=IF(H29="","",SUMPRODUCT((TRIM(SUBSTITUTE(SUBSTITUTE($A$5:$A$10003,CHAR(13),""),CHAR(10),""))=H29)*IFERROR(--$D$5:$D$10003,0)))} | M29: {=IF(H29="","",SUMPRODUCT((TRIM(SUBSTITUTE(SUBSTITUTE($A$5:$A$10003,CHAR(13),""),CHAR(10),""))=H29)*IFERROR(--$F$5:$F$10003,0)))}
I30: {=IF(H30="","",_xlfn.XLOOKUP(H30,TRIM(SUBSTITUTE(SUBSTITUTE(A30:A10026,CHAR(13),""),CHAR(10),"")),B30:B10026,"报错",0))} | J30: {=IF(H30="","",SUMPRODUCT((TRIM(SUBSTITUTE(SUBSTITUTE($A$5:$A$10003,CHAR(13),""),CHAR(10),""))=H30)*--$C$5:$C$10003))} | K30: {=IF(H30="","",SUMPRODUCT((TRIM(SUBSTITUTE(SUBSTITUTE($A$5:$A$10003,CHAR(13),""),CHAR(10),""))=H30)*--$D$5:$D$10003))} | L30: {=IF(H30="","",SUMPRODUCT((TRIM(SUBSTITUTE(SUBSTITUTE($A$5:$A$10003,CHAR(13),""),CHAR(10),""))=H30)*IFERROR(--$D$5:$D$10003,0)))} | M30: {=IF(H30="","",SUMPRODUCT((TRIM(SUBSTITUTE(SUBSTITUTE($A$5:$A$10003,CHAR(13),""),CHAR(10),""))=H30)*IFERROR(--$F$5:$F$10003,0)))}
... I38: {=IF(H38="","",_xlfn.XLOOKUP(H38,TRIM(SUBSTITUTE(SUBSTITUTE(A38:A10034,CHAR(13),""),CHAR(10),"")),B38:B10034,"报错",0))} | J38: {=IF(H38="","",SUMPRODUCT((TRIM(SUBSTITUTE(SUBSTITUTE($A$5:$A$10003,CHAR(13),""),CHAR(10),""))=H38)*--$C$5:$C$10003))} | K38: {=IF(H38="","",SUMPRODUCT((TRIM(SUBSTITUTE(SUBSTITUTE($A$5:$A$10003,CHAR(13),""),CHAR(10),""))=H38)*--$D$5:$D$10003))} | L38: {=IF(H38="","",SUMPRODUCT((TRIM(SUBSTITUTE(SUBSTITUTE($A$5:$A$10003,CHAR(13),""),CHAR(10),""))=H38)*IFERROR(--$D$5:$D$10003,0)))} | M38: {=IF(H38="","",SUMPRODUCT((TRIM(SUBSTITUTE(SUBSTITUTE($A$5:$A$10003,CHAR(13),""),CHAR(10),""))=H38)*IFERROR(--$F$5:$F$10003,0)))}

Sheet 客户信息底表
A1: 客户编号 | B1: 客户名称 | C1: 客户等级 | D1: 所属组织 | E1: 部门 | F1: 联系人 | G1: 手机号码 | H1: 省 | I1: 市 | J1: 区 | K1: 街道 | L1: 详细地址 | M1: 业务员 | N1: 线路 | O1: 渠道 | P1: 是否允许货到付款 | Q1: 经度 | R1: 纬度 | S1: 外部编码 | T1: 标签 | U1: 状态 | V1: 客户状态 | W1: 内部往来单位 | X1: 发票类型 | Y1: 注册电话 | Z1: 注册地址 | AA1: 客户序号 | AB1: 标准客户名称 | AC1: 系统 | AD1: 小巷子 | AE1: 上楼层数 | AF1: 违停 | AG1: 地库限高 | AH1: 免费停车时长_分钟 | AI1: 停车费_小时 | AJ1: 开始收货时间 | AK1: 截止收货时间 | AL1: 收货时间段 | AM1: 不收货时间段 | AN1: 停车位置 | AO1: 停车方式 | AP1: 卸货入口 | AQ1: 卸货位置 | AR1: 手推车 | AS1: 托盘置换 | AT1: 保温箱置换 | AU1: 周一配送 | AV1: 周二配送 | AW1: 周三配送 | AX1: 周四配送 | AY1: 周五配送 | AZ1: 周六配送 | BA1: 周日配送 | BB1: 名称1 | BC1: 名称2 | BD1: 名称3
A2: KH00491 | B2: 京牛快送超市(官窑店） | D2: 广州同超贸易有限公司 | E2: 销售部 | F2: 京牛快送超市(官窑店） | G2: 18475715521 | H2: 广东省 | I2: 佛山市 | J2: 南海区 | K2: 狮山镇 | L2: 佛山市南海区狮山镇官窑京牛快送超市 | M2: 同超2号 | N2: 默认线路 | O2: 其他 | P2: 是 | Q2: 未登记 | R2: 未登记 | U2: 启用 | V2: 正常 | W2: 否 | AA2: 1 | AC2: 美宜佳
A3: KH00490 | B3: 熊猫很忙（新基-广东东莞） | D3: 广州同超贸易有限公司 | E3: 销售部 | F3: 古丽 | G3: 13600290018 | H3: 广东省 | I3: 东莞市 | J3: 东莞市 | K3: 南城街道 | L3: 南城区新基二横路三巷11号101室（熊猫很忙新基店） | M3: 同超1号 | N3: 默认线路 | O3: 其他 | P3: 是 | Q3: 未登记 | R3: 未登记 | U3: 启用 | V3: 正常 | W3: 否 | AA3: 2 | AC3: 熊猫很忙
A4: KH00489 | B4: 小罐茶曾繁梓 | D4: 广州同超贸易有限公司 | F4: 曾繁梓 | G4: 18529106745 | H4: 广东省 | I4: 广州市 | J4: 天河区 | L4: 小罐茶 | M4: 运营 | N4: 默认线路 | O4: 消费者个人 | P4: 是 | Q4: 未登记 | R4: 未登记 | U4: 启用 | V4: 正常 | W4: 否 | AA4: 3 | AC4: 小罐茶曾繁梓
A5: KH00488 | B5: 值小团（广州香江店） | D5: 广州同超贸易有限公司 | E5: 销售部 | F5: 值小团超市香江店 | G5: 18902398996 | H5: 广东省 | I5: 广州市 | J5: 增城区 | L5: 广东省广州市增城区新塘镇南安村石隆大路1号大昌荣区栋101值小团超市香江店 | M5: 爱如 | N5: 默认线路 | O5: 其他 | P5: 是 | U5: 启用 | V5: 正常 | W5: 否 | AA5: 4 | AC5: 值小团
A6: KH00487 | B6: 瑞利批发 | D6: 广州同超贸易有限公司 | E6: 销售部 | F6: 瑞利批发 | G6: 18620606797 | H6: 广东省 | I6: 广州市 | J6: 天河区 | L6: 天河区西约西边坑大街上十巷28号 | M6: 采购2号【常温】 | N6: 默认线路 | O6: 便利店 | P6: 是 | Q6: 未登记 | R6: 未登记 | U6: 启用 | V6: 正常 | W6: 否 | AA6: 5 | AC6: 瑞利批发
A7: KH00486 | B7: 蜜蜂优选超市（广州南沙湾店）24小时收货 | D7: 广州同超贸易有限公司 | E7: 销售部 | F7: 蜜蜂优选超市 | G7: 15112109392 | H7: 广东省 | I7: 广州市 | J7: 南沙区 | L7: 广州市南沙区进港大道龟山街58号1楼101铺（请送货上门，勿放驿站，送货请电联！） | M7: 爱如 | N7: 默认线路 | O7: 其他 | P7: 是 | Q7: 未登记 | R7: 未登记 | U7: 启用 | V7: 正常 | W7: 否 | AA7: 6 | AC7: 蜜蜂优选超市
A8: KH00485 | B8: 蜜蜂优选超市（广州太石店）24小时收货 | D8: 广州同超贸易有限公司 | E8: 销售部 | F8: 蜜蜂优选超市 | G8: 13189843798 | H8: 广东省 | I8: 广州市 | J8: 南沙区 | L8: 广东省广州市南沙区东涌镇太石村太石综合市场D栋2楼之一铺（请送货上二楼，勿放驿站，送货请电联！） | M8: 爱如 | N8: 默认线路 | O8: 其他 | P8: 是 | Q8: 未登记 | R8: 未登记 | U8: 启用 | V8: 正常 | W8: 否 | AA8: 7 | AC8: 蜜蜂优选超市
A9: KH00098 | B9: 美宜多【总仓】 | D9: 广州同超贸易有限公司 | E9: 销售部 | F9: 美宜多【总仓】 | G9: 13802799918 | H9: 广东省 | I9: 广州市 | J9: 天河区 | L9: 天河区棠东广棠路41号 | M9: 采购2号【常温】 | N9: 默认线路 | O9: 超市 | P9: 是 | Q9: 未登记 | R9: 未登记 | U9: 启用 | V9: 正常 | W9: 否 | AA9: 8 | AC9: 美宜佳
A10: KH00097 | B10: 熊猫很忙（梅江店-广东梅州） | D10: 广州同超贸易有限公司 | F10: 熊猫很忙梅江店 | G10: 14754591945 | H10: 广东省 | I10: 梅州市 | J10: 梅江区 | L10: 江南丽都中路恒泰花园-A7栋1号 | M10: 运营 | N10: 默认线路 | O10: 其他 | P10: 是 | Q10: 未登记 | R10: 未登记 | U10: 启用 | V10: 正常 | W10: 否 | AA10: 9 | AC10: 熊猫很忙
A11: KH00096 | B11: 熊猫很忙（富兴店-广东梅州） | D11: 广州同超贸易有限公司 | F11: 熊猫很忙富兴店 | G11: 18125512990 | H11: 广东省 | I11: 梅州市 | J11: 五华县 | L11: 水寨镇富兴花园富强路二横街16号 | M11: 运营 | N11: 默认线路 | O11: 其他 | P11: 是 | Q11: 未登记 | R11: 未登记 | U11: 启用 | V11: 正常 | W11: 否 | AA11: 10 | AC11: 熊猫很忙
A12: KH00087 | B12: 掌上E（三源色-仙湖试驾基地） | D12: 广州同超贸易有限公司 | E12: 销售部 | F12: 掌上E | G12: 13138471777 | H12: 广东省 | I12: 佛山市 | J12: 南海区 | L12: 南海区桂丹西路（三源色-仙湖试驾基地） | M12: 采购2号【常温】 | N12: 默认路线 | O12: 批发部 | P12: 是 | U12: 启用 | V12: 正常 | W12: 否 | AA12: 11 | AC12: 掌上E
A13: KH00484 | B13: 施来客（深圳香格丽湾店） | D13: 广州同超贸易有限公司 | F13: 深圳香格丽湾店 | G13: 13410336363 | H13: 广东省 | I13: 深圳市 | J13: 宝安区 | L13: 广东省/深圳市/宝安区/深圳市宝安区西乡街道香格丽湾二期6栋110、111号商铺 | M13: 同超4号 | N13: 默认线路 | O13: 其他 | P13: 是 | Q13: 未登记 | R13: 未登记 | U13: 启用 | V13: 正常 | W13: 否 | AA13: 12 | AC13: 施来客
A14: KH00483 | B14: 施来客（深圳天富安店） | D14: 广州同超贸易有限公司 | F14: 深圳天富安店 | G14: 13237070819 | H14: 广东省 | I14: 深圳市 | J14: 宝安区 | L14: 广东省/深圳市/宝安区/深圳市宝安区航城街道黄麻布社区靳竹角天富安工业园鸿都物业宿舍一楼26-28号 | M14: 同超4号 | N14: 默认线路 | O14: 其他 | P14: 是 | Q14: 未登记 | R14: 未登记 | U14: 启用 | V14: 正常 | W14: 否 | AA14: 13 | AC14: 施来客
A15: KH00482 | B15: 施来客（深圳瑞尚居店） | D15: 广州同超贸易有限公司 | F15: 深圳瑞尚居店 | G15: 13682519874 | H15: 广东省 | I15: 深圳市 | J15: 宝安区 | L15: 广东省/深圳市/宝安区/深圳市宝安区西乡街道瑞尚居3栋B单元1093栋A 单元110 | M15: 同超4号 | N15: 默认线路 | O15: 其他 | P15: 是 | Q15: 未登记 | R15: 未登记 | U15: 启用 | V15: 正常 | W15: 否 | AA15: 14 | AC15: 施来客
A16: KH00481 | B16: 施来客（深圳富通城店） | D16: 广州同超贸易有限公司 | F16: 深圳富通城店 | G16: 18520243344 | H16: 广东省 | I16: 深圳市 | J16: 宝安区 | L16: 广东省/深圳市/宝安区/深圳市宝安区西乡街道西乡大道西北侧碧海富通城17栋109-113房屋 | M16: 同超4号 | N16: 默认线路 | O16: 其他 | P16: 是 | Q16: 未登记 | R16: 未登记 | U16: 启用 | V16: 正常 | W16: 否 | AA16: 15 | AC16: 施来客
A17: KH00480 | B17: 施来客（东莞中银花园店） | D17: 广州同超贸易有限公司 | F17: 东莞中银花园店 | G17: 13556673781 | H17: 广东省 | I17: 东莞市 | J17: 东莞市 | L17: 广东省/东莞市/东莞市/东莞市南城区新中路1号新中银花园107号铺 | M17: 同超4号 | N17: 默认线路 | O17: 其他 | P17: 是 | Q17: 未登记 | R17: 未登记 | U17: 启用 | V17: 正常 | W17: 否 | AA17: 16 | AC17: 施来客
A18: KH00479 | B18: 施来客（东莞阳光海岸店） | D18: 广州同超贸易有限公司 | F18: 东莞阳光海岸店 | G18: 13009633248 | H18: 广东省 | I18: 东莞市 | J18: 东莞市 | L18: 广东省/东莞市/东莞市/东莞市万江阳光海岸晶岸4-6栋商铺42号商铺 | M18: 同超4号 | N18: 默认线路 | O18: 其他 | P18: 是 | Q18: 未登记 | R18: 未登记 | U18: 启用 | V18: 正常 | W18: 否 | AA18: 17 | AC18: 施来客
A19: KH00478 | B19: 施来客（东莞市松山湖店） | D19: 广州同超贸易有限公司 | F19: 东莞市松山湖店 | G19: 13240549937 | H19: 广东省 | I19: 东莞市 | J19: 东莞市 | L19: 广东省/东莞市/东莞市/东莞市松山湖高新技术产业开发区工业北四路2号收货仓库万科金域松湖花园39号楼商铺108、109 | M19: 同超4号 | N19: 默认线路 | O19: 其他 | P19: 是 | Q19: 未登记 | R19: 未登记 | U19: 启用 | V19: 正常 | W19: 否 | AA19: 18 | AC19: 施来客
A20: KH00477 | B20: 施来客（东莞庆峰花园店） | D20: 广州同超贸易有限公司 | F20: 东莞庆峰花园店 | G20: 13922904519 | H20: 广东省 | I20: 东莞市 | J20: 东莞市 | L20: 广东省/东莞市/东莞市/东莞市东城区温塘庆峰花园三期666768号商铺 | M20: 同超4号 | N20: 默认线路 | O20: 其他 | P20: 是 | Q20: 未登记 | R20: 未登记 | U20: 启用 | V20: 正常 | W20: 否 | AA20: 19 | AC20: 施来客
A21: KH00476 | B21: 施来客（东莞大朗里悦里店） | D21: 广州同超贸易有限公司 | F21: 东莞大朗里悦里店 | G21: 15570152796 | H21: 广东省 | I21: 东莞市 | J21: 东莞市 | L21: 广东省/东莞市/东莞市/东莞市大朗镇富民中路193号碧桂园名座广场18号商铺104一楼 | M21: 同超4号 | N21: 默认线路 | O21: 其他 | P21: 是 | Q21: 未登记 | R21: 未登记 | U21: 启用 | V21: 正常 | W21: 否 | AA21: 20 | AC21: 施来客
A22: KH00076 | B22: 熊猫很忙（梅塘店-广东东莞） | D22: 广州同超贸易有限公司 | E22: 销售部 | F22: 熊猫很忙（梅塘店-广东东莞） | G22: 13798813989 | H22: 广东省 | I22: 东莞市 | J22: 东莞市 | L22: 黄江镇聚龙巷51号201室熊猫很忙梅塘店（麻烦送上门，放驿站投诉） | M22: 同超1号 | N22: 默认线路 | O22: 其他 | P22: 是 | Q22: 未登记 | R22: 未登记 | U22: 启用 | V22: 正常 | W22: 否 | AA22: 21 | AC22: 熊猫很忙
A23: CUS00312 | B23: 龙岗店1688（提前电话联系） | D23: 广州同超贸易有限公司 | E23: 销售部 | F23: 沃玛希龙岗店 | G23: 18819418881 | H23: 广东省 | I23: 深圳市 | J23: 龙岗区 | L23: 南约社区南同大道11号南汉商业街锦东公寓一楼沃玛希超市 | M23: 同超4号 | N23: 默认路线 | O23: 其他 | P23: 是 | Q23: 114.29 | R23: 22.7 | U23: 启用 | V23: 正常 | W23: 否 | AA23: 22 | AB23: 沃玛希精品超市 | AC23: 美宜佳
A24: KH00475 | B24: 粤32915美宜佳湛江市遂溪县 | D24: 广州同超贸易有限公司 | E24: 销售部 | F24: 王女士 | G24: 19126637159 | H24: 广东省 | I24: 湛江市 | J24: 遂溪县 | L24: 广东省湛江市遂溪县黄略镇校友路中心小学北侧 | M24: 同超2号 | N24: 默认线路 | O24: 其他 | P24: 是 | Q24: 110.3236 | R24: 21.320904 | S24: 20260201145621265336636-1 | U24: 启用 | V24: 正常 | W24: 否 | AA24: 23 | AC24: 美宜佳
A25: KH00474 | B25: 粤31952美宜佳湛江市遂溪县 | D25: 广州同超贸易有限公司 | E25: 销售部 | F25: 李女士 | G25: 13536371393 | H25: 广东省 | I25: 湛江市 | J25: 遂溪县 | L25: 广东省湛江市遂溪县遂城镇建设路外贸综合楼首层 | M25: 同超2号 | N25: 默认线路 | O25: 其他 | P25: 是 | Q25: 110.25685 | R25: 21.377718 | S25: 20260126212522278552244-1 | U25: 启用 | V25: 正常 | W25: 否 | AA25: 24 | AC25: 美宜佳
A26: KH00473 | B26: 粤31540美宜佳湛江市遂溪县 | D26: 广州同超贸易有限公司 | E26: 销售部 | F26: 李女士 | G26: 13714424451 | H26: 广东省 | I26: 湛江市 | J26: 遂溪县 | L26: 广东省湛江市遂溪县遂城镇遂海路南苑小区东圩河东片E1号 | M26: 同超2号 | N26: 默认线路 | O26: 其他 | P26: 是 | Q26: 110.24872 | R26: 21.366958 | S26: 20260126212017521536719-1 | U26: 启用 | V26: 正常 | W26: 否 | AA26: 25 | AC26: 美宜佳
A27: KH00472 | B27: 粤30202美宜佳湛江市赤坎区 | D27: 广州同超贸易有限公司 | E27: 销售部 | F27: 杨先生 | G27: 15382620323 | H27: 广东省 | I27: 湛江市 | J27: 赤坎区 | L27: 广东省湛江市赤坎区沙湾街道海田路28号海田创意广场5栋之二 | M27: 同超2号 | N27: 默认线路 | O27: 其他 | P27: 是 | Q27: 110.37865 | R27: 21.275911 | S27: 20260126213815600547702-1 | U27: 启用 | V27: 正常 | W27: 否 | AA27: 26 | AC27: 美宜佳
A28: KH00471 | B28: 粤27658美宜佳湛江市遂溪县店家 | D28: 广州同超贸易有限公司 | E28: 销售部 | F28: 李女士 | G28: 18028438552 | H28: 广东省 | I28: 湛江市 | J28: 遂溪县 | L28: 广东省湛江市遂溪县遂城镇站南路锐达豪苑一区B栋首层9号 | M28: 同超2号 | N28: 默认线路 | O28: 其他 | P28: 是 | Q28: 110.26448 | R28: 21.386207 | S28: 20260126211808006664604-1 | U28: 启用 | V28: 正常 | W28: 否 | AA28: 27 | AC28: 美宜佳
A29: KH00470 | B29: 粤20693美宜佳湛江市遂溪县 | D29: 广州同超贸易有限公司 | E29: 销售部 | F29: 郑女士 | G29: 13727892690 | H29: 广东省 | I29: 湛江市 | J29: 遂溪县 | L29: 广东省湛江市遂溪县遂城镇城南市场湛兴路一横东2号一楼 | M29: 同超2号 | N29: 默认线路 | O29: 其他 | P29: 是 | Q29: 110.24564 | R29: 21.357352 | S29: 20260130091004255620621-1 | U29: 启用 | V29: 正常 | W29: 否 | AA29: 28 | AC29: 美宜佳
A30: KH00469 | B30: 粤39971美宜佳江门开平 | D30: 广州同超贸易有限公司 | E30: 销售部 | F30: 李启宏 | G30: 15917815916 | H30: 广东省 | I30: 江门市 | J30: 开平市 | L30: 广东省江门市开平市三埠街道富强路8号新外滩南门13幢115号 | M30: 同超2号 | N30: 默认线路 | O30: 其他 | P30: 是 | Q30: 112.70659 | R30: 22.34687 | S30: 20260130155423754519372-1 | U30: 启用 | V30: 正常 | W30: 否 | AA30: 29 | AC30: 美宜佳
A31: KH00468 | B31: 粤37573美宜佳江门台山 | D31: 广州同超贸易有限公司 | E31: 销售部 | F31: 李华娣 | G31: 13555663648 | H31: 广东省 | I31: 江门市 | J31: 台山市 | L31: 广东省江门市台山市台城街道万达大都会二期S8-153 | M31: 同超2号 | N31: 默认线路 | O31: 其他 | P31: 是 | Q31: 112.81896 | R31: 22.228125 | S31: 20260205202440245701317-1 | U31: 启用 | V31: 正常 | W31: 否 | AA31: 30 | AC31: 美宜佳
A32: KH00467 | B32: 粤37292美宜佳江门台山 | D32: 广州同超贸易有限公司 | E32: 销售部 | F32: 刘嘉欣 | G32: 17727033356 | H32: 广东省 | I32: 江门市 | J32: 台山市 | L32: 广东省江门市台山市台城街道德政路2号翰林雅苑（1栋）107室 | M32: 同超2号 | N32: 默认线路 | O32: 其他 | P32: 是 | Q32: 112.8145 | R32: 22.218711 | S32: 20260130155036177067267-1 | U32: 启用 | V32: 正常 | W32: 否 | AA32: 31 | AC32: 美宜佳
A33: KH00466 | B33: 粤36235美宜佳江门开平 | D33: 广州同超贸易有限公司 | E33: 销售部 | F33: 蔡燕虹 | G33: 18688488639 | H33: 广东省 | I33: 江门市 | J33: 开平市 | L33: 广东省江门市开平市三埠街道百润花园北门134-135号铺位 | M33: 同超2号 | N33: 默认线路 | O33: 其他 | P33: 是 | Q33: 112.70412 | R33: 22.349543 | S33: 20260201160655892995604-1 | U33: 启用 | V33: 正常 | W33: 否 | AA33: 32 | AC33: 美宜佳
A34: KH00465 | B34: 粤28846美宜佳江门开平水口 | D34: 广州同超贸易有限公司 | E34: 销售部 | F34: 沈少全 | G34: 18336254831 | H34: 广东省 | I34: 江门市 | J34: 开平市 | L34: 广东省江门市开平市水口镇外环北路8号第一幢10-11号 | M34: 同超2号 | N34: 默认线路 | O34: 其他 | P34: 是 | Q34: 112.77359 | R34: 22.460644 | S34: 20260130160124486492876-1 | U34: 启用 | V34: 正常 | W34: 否 | AA34: 33 | AC34: 美宜佳
A35: KH00464 | B35: 粤22289美宜佳江门开平 | D35: 广州同超贸易有限公司 | E35: 销售部 | F35: 刘付国辉 | G35: 13450622761 | H35: 广东省 | I35: 江门市 | J35: 开平市 | L35: 广东省江门市开平市长沙街道曙光东路152号102卡 | M35: 同超2号 | N35: 默认线路 | O35: 其他 | P35: 是 | Q35: 112.70724 | R35: 22.375526 | S35: 20260130190216649955285-1 | U35: 启用 | V35: 正常 | W35: 否 | AA35: 34 | AC35: 美宜佳
... A40: KH00459 | B40: 粤40039美宜佳珠海市香洲区前山街道翠微海宏苑店 | D40: 广州同超贸易有限公司 | E40: 销售部 | F40: 陈小姐 | G40: 13431724014 | H40: 广东省 | I40: 珠海市 | J40: 香洲区 | L40: 广东省珠海市香洲区前山街道翠微西路海宏苑美宜佳 | M40: 同超2号 | N40: 默认线路 | O40: 其他 | P40: 是 | Q40: 113.52142 | R40: 22.255365 | S40: 20260129211211930694151-1 | U40: 启用 | V40: 正常 | W40: 否 | AA40: 39 | AC40: 美宜佳
A41: KH00458 | B41: 39709（AB）广东中山三乡雅居乐万象郡1期美宜佳 | D41: 广州同超贸易有限公司 | E41: 销售部 | F41: 黄先生 | G41: 18148801060 | H41: 广东省 | I41: 中山市 | J41: 中山市 | K41: 三乡镇 | L41: 广东省中山市三乡镇金涌大道590号 | M41: 同超2号 | N41: 默认线路 | O41: 其他 | P41: 是 | Q41: 113.45883 | R41: 22.333865 | S41: 20260123125242955219452-1 | U41: 启用 | V41: 正常 | W41: 否 | AA41: 40 | AC41: 美宜佳
A42: KH00457 | B42: 粤38048美宜佳珠海市唐家湾 | D42: 广州同超贸易有限公司 | E42: 销售部 | F42: 林嘉利 | G42: 13798979783 | H42: 广东省 | I42: 珠海市 | J42: 香洲区 | L42: 广东省珠海市香洲区唐家湾镇金峰中路165号1幢 | M42: 同超2号 | N42: 默认线路 | O42: 其他 | P42: 是 | Q42: 113.54012 | R42: 22.38003 | S42: 20260131183810434793135-1 | U42: 启用 | V42: 正常 | W42: 否 | AA42: 41 | AC42: 美宜佳
A43: KH00456 | B43: 粤28525美宜佳中山市三乡镇 | D43: 广州同超贸易有限公司 | E43: 销售部 | F43: 吴先生 | G43: 18924998886 | H43: 广东省 | I43: 中山市 | J43: 中山市 | K43: 三乡镇 | L43: 广东省中山市三乡镇万象郡二期12幢46卡 | M43: 同超2号 | N43: 默认线路 | O43: 其他 | P43: 是 | Q43: 113.45894 | R43: 22.339414 | S43: 20260129210530416501339-1 | U43: 启用 | V43: 正常 | W43: 否 | AA43: 42 | AC43: 美宜佳
A44: KH00455 | B44: 粤21383美宜佳珠海市香洲区拱北口岸 | D44: 广州同超贸易有限公司 | E44: 销售部 | F44: 钟华 | G44: 15000928809 | H44: 广东省 | I44: 珠海市 | J44: 香洲区 | L44: 广东省珠海市香洲区拱北街道围基路28号和园大厦12号 | M44: 同超2号 | N44: 默认线路 | O44: 其他 | P44: 是 | Q44: 113.55112 | R44: 22.217373 | S44: 20260129210747973326894-1 | U44: 启用 | V44: 正常 | W44: 否 | AA44: 43 | AC44: 美宜佳
A45: KH00454 | B45: 17245（AB）广东珠海香洲中之华大厦美宜佳 | D45: 广州同超贸易有限公司 | E45: 销售部 | F45: 黄志锋 | G45: 15338187458 | H45: 广东省 | I45: 珠海市 | J45: 香洲区 | L45: 广东省珠海市香洲区前山街道华威路112号 | M45: 同超2号 | N45: 默认线路 | O45: 其他 | P45: 是 | Q45: 113.4967 | R45: 22.285717 | S45: 20260123110753545556613-1 | U45: 启用 | V45: 正常 | W45: 否 | AA45: 44 | AC45: 美宜佳
A46: KH00453 | B46: M140美宜佳中山坦洲金碧路美宜佳 | D46: 广州同超贸易有限公司 | E46: 销售部 | F46: 刘小燕 | G46: 18028367082 | H46: 广东省 | I46: 中山市 | J46: 中山市 | K46: 坦洲镇 | L46: 广东省中山市坦洲镇德溪路10号 | M46: 同超2号 | N46: 默认线路 | O46: 其他 | P46: 是 | Q46: 113.46395 | R46: 22.267238 | S46: 20260131150313083454358-1 | U46: 启用 | V46: 正常 | W46: 否 | AA46: 45 | AC46: 美宜佳
A47: KH00452 | B47: 粤22782美宜佳江门市蓬江区远航店 | D47: 广州同超贸易有限公司 | E47: 销售部 | F47: 许大大 | G47: 13536138427 | H47: 广东省 | I47: 江门市 | J47: 蓬江区 | L47: 广东省江门市蓬江区白沙街道远航水产交易中心综合楼首层11号美宜佳 | M47: 同超2号 | N47: 默认线路 | O47: 其他 | P47: 是 | Q47: 113.06064 | R47: 22.573228 | S47: 20260128131406304350368-1 | U47: 启用 | V47: 正常 | W47: 否 | AA47: 46 | AC47: 美宜佳
A48: KH00451 | B48: M360美宜佳江门市江海区星海湾花园店 | D48: 广州同超贸易有限公司 | E48: 销售部 | F48: 姚姗姗 | G48: 13555616010 | H48: 广东省 | I48: 江门市 | J48: 江海区 | L48: 广东省江门市江海区滘头街道星海湾花园125号商铺 | M48: 同超2号 | N48: 默认线路 | O48: 其他 | P48: 是 | Q48: 113.08984 | R48: 22.570604 | S48: 20260128204741205104208-1 | U48: 启用 | V48: 正常 | W48: 否 | AA48: 47 | AC48: 美宜佳
A49: KH00450 | B49: 0172天福珠海市高栏港经济区 | D49: 广州同超贸易有限公司 | E49: 销售部 | F49: 王先生 | G49: 13686006155 | H49: 广东省 | I49: 珠海市 | J49: 金湾区 | K49: 南水镇 | L49: 珠海市高栏港经济区南水镇铁炉北路港城花园(金湾区铁路北路133号2栋) | M49: 同超2号 | N49: 默认线路 | O49: 其他 | P49: 是 | Q49: 113.1988 | R49: 22.004372 | S49: 20260204145426395564445-1 | U49: 启用 | V49: 正常 | W49: 否 | AA49: 48 | AC49: 0172天福珠海市高栏港经济区
A50: KH00449 | B50: 粤37862美宜佳珠海市斗门区白藤街道店 | D50: 广州同超贸易有限公司 | E50: 销售部 | F50: 吴先生 | G50: 13085810277 | H50: 广东省 | I50: 珠海市 | J50: 斗门区 | L50: 广东省珠海市斗门区白藤街道白藤一路东187号 | M50: 同超2号 | N50: 默认线路 | O50: 其他 | P50: 是 | Q50: 113.36268 | R50: 22.149343 | S50: 20260128150335567621264-1 | U50: 启用 | V50: 正常 | W50: 否 | AA50: 49 | AC50: 美宜佳
A51: KH00448 | B51: 粤33899美宜佳珠海市金湾区南水镇店 | D51: 广州同超贸易有限公司 | E51: 销售部 | F51: 王先生 | G51: 13326693860 | H51: 广东省 | I51: 珠海市 | J51: 金湾区 | L51: 广东省珠海市金湾区南水镇金都二街65号商铺 | M51: 同超2号 | N51: 默认线路 | O51: 其他 | P51: 是 | Q51: 113.2401 | R51: 22.027318 | S51: 20260128150926815786244-1 | U51: 启用 | V51: 正常 | W51: 否 | AA51: 50 | AC51: 美宜佳
A52: KH00447 | B52: 粤33371美宜佳珠海市斗门区井岸镇店 | D52: 广州同超贸易有限公司 | E52: 销售部 | F52: 罗先生 | G52: 15876657667 | H52: 广东省 | I52: 珠海市 | J52: 斗门区 | L52: 广东省珠海市斗门区井岸镇鸡嘴路 | M52: 同超2号 | N52: 默认线路 | O52: 其他 | P52: 是 | Q52: 113.27369 | R52: 22.160747 | S52: 20260128151106471709992-1 | U52: 启用 | V52: 正常 | W52: 否 | AA52: 51 | AC52: 美宜佳
A53: KH00446 | B53: 粤19151美宜佳珠海市金湾区红旗镇 | D53: 广州同超贸易有限公司 | E53: 销售部 | F53: 王女士 | G53: 18671506208 | H53: 广东省 | I53: 珠海市 | J53: 金湾区 | L53: 广东省珠海市金湾区红旗镇矿山路口金山花园二期21栋商业广场10~11号商铺 | M53: 同超2号 | N53: 默认线路 | O53: 其他 | P53: 是 | Q53: 113.28991 | R53: 22.090721 | S53: 20260127144129134616169-1 | U53: 启用 | V53: 正常 | W53: 否 | AA53: 52 | AC53: 美宜佳
A54: KH00445 | B54: 18573（AB）广东珠海斗门西浦光明路美宜佳 | D54: 广州同超贸易有限公司 | E54: 销售部 | F54: 李女士 | G54: 13821590450 | H54: 广东省 | I54: 珠海市 | J54: 斗门区 | L54: 广东省珠海市斗门区井岸镇西埔村光明路五港26号 | M54: 同超2号 | N54: 默认线路 | O54: 其他 | P54: 是 | Q54: 113.2679 | R54: 22.164 | S54: 20260120185358126894531-1 | U54: 启用 | V54: 正常 | W54: 否 | AA54: 53 | AC54: 美宜佳
A55: KH00444 | B55: K150美宜佳珠海市斗门区乾务镇店 | D55: 广州同超贸易有限公司 | E55: 销售部 | F55: 李女士 | G55: 13326693860 | H55: 广东省 | I55: 珠海市 | J55: 斗门区 | L55: 广东省珠海市斗门区乾务镇乾南中路130号 | M55: 同超2号 | N55: 默认线路 | O55: 其他 | P55: 是 | Q55: 113.22922 | R55: 22.153936 | S55: 20260128150111172797535-1 | U55: 启用 | V55: 正常 | W55: 否 | AA55: 54 | AC55: 美宜佳
A56: KH00443 | B56: 粤g180美宜佳珠海市斗门区井岸镇店 | D56: 广州同超贸易有限公司 | E56: 销售部 | F56: 杨先生 | G56: 18902864220 | H56: 广东省 | I56: 珠海市 | J56: 斗门区 | L56: 广东省珠海市斗门区井岸镇西埔南厂桥头 | M56: 同超2号 | N56: 默认线路 | O56: 其他 | P56: 是 | Q56: 113.26845 | R56: 22.165211 | S56: 20260126212218323617934-1 | U56: 启用 | V56: 正常 | W56: 否 | AA56: 55 | AC56: 美宜佳
A57: KH00442 | B57: D932美宜佳珠海市斗门区井岸镇鸡咀路 | D57: 广州同超贸易有限公司 | E57: 销售部 | F57: 李女士 | G57: 18028769831 | H57: 广东省 | I57: 珠海市 | J57: 斗门区 | L57: 广东省珠海市斗门区井岸镇鸡咀村综合楼第B2栋第一号铺 | M57: 同超2号 | N57: 默认线路 | O57: 其他 | P57: 是 | Q57: 113.27717 | R57: 22.158228 | S57: 20260128150756951006923-1 | U57: 启用 | V57: 正常 | W57: 否 | AA57: 56 | AC57: 美宜佳
A58: KH00441 | B58: B125美宜佳井岸西埔 | D58: 广州同超贸易有限公司 | E58: 销售部 | F58: 郑女士 | G58: 18871511799 | H58: 广东省 | I58: 珠海市 | J58: 斗门区 | L58: 广东省珠海市斗门区井岸镇新青村路南一巷四号 | M58: 同超2号 | N58: 默认线路 | O58: 其他 | P58: 是 | Q58: 113.28803 | R58: 22.160998 | S58: 20260126105450799991094-1 | U58: 启用 | V58: 正常 | W58: 否 | AA58: 57 | AC58: 美宜佳
A59: KH00440 | B59: 粤2103合家欢珠海市斗门区井岸镇店 | D59: 广州同超贸易有限公司 | E59: 销售部 | F59: 邱全林 | G59: 15207561053 | H59: 广东省 | I59: 珠海市 | J59: 斗门区 | L59: 广东省珠海市斗门区井岸西铺大三角C22号店合家欢 | M59: 同超2号 | N59: 默认线路 | O59: 其他 | P59: 是 | S59: 20260205235545098498460-1 | U59: 启用 | V59: 正常 | W59: 否 | AA59: 58 | AC59: 美宜佳
A60: KH00439 | B60: 合家欢2020珠海市金湾区红旗镇店 | D60: 广州同超贸易有限公司 | E60: 销售部 | F60: 陈先生 | G60: 17688177121 | H60: 广东省 | I60: 珠海市 | J60: 金湾区 | L60: 广东省珠海市金湾区红旗虹晖路合家欢虹晖路店 | M60: 同超2号 | N60: 默认线路 | O60: 其他 | P60: 是 | Q60: 未登记 | R60: 未登记 | S60: 20260203135903848000152-1 | U60: 启用 | V60: 正常 | W60: 否 | AA60: 59 | AC60: 美宜佳
A61: KH00438 | B61: 粤1879合家欢珠海市金湾区三灶镇店 | D61: 广州同超贸易有限公司 | E61: 销售部 | F61: 王先生 | G61: 13326918808 | H61: 广东省 | I61: 珠海市 | J61: 金湾区 | L61: 广东省珠海市金湾区保利香槟国际花园90号铺 | M61: 同超2号 | N61: 默认线路 | O61: 其他 | P61: 是 | S61: 20260125185431984499059-1 | U61: 启用 | V61: 正常 | W61: 否 | AA61: 60 | AC61: 美宜佳
A62: KH00437 | B62: 粤39603美宜佳中山市南朗镇岭南小区店 | D62: 广州同超贸易有限公司 | E62: 销售部 | F62: 李小姐 | G62: 18381608530 | H62: 广东省 | I62: 中山市 | J62: 中山市 | K62: 南朗街道 | L62: 广东省中山市南朗街道南朗俊景路49号 | M62: 同超2号 | N62: 默认线路 | O62: 其他 | P62: 是 | Q62: 113.52777 | R62: 22.496057 | S62: 20260123225955598371967-1 | U62: 启用 | V62: 正常 | W62: 否 | AA62: 61 | AC62: 美宜佳
A63: KH00436 | B63: 粤35952美宜佳中山市民众镇浪网大道中 | D63: 广州同超贸易有限公司 | E63: 销售部 | F63: 刘芬 | G63: 13424528545 | H63: 广东省 | I63: 中山市 | J63: 中山市 | K63: 民众街道 | L63: 广东省中山市民众镇浪网大道256号 | M63: 同超2号 | N63: 默认线路 | O63: 其他 | P63: 是 | Q63: 113.45538 | R63: 22.631947 | S63: 20260205195741381885160-1 | U63: 启用 | V63: 正常 | W63: 否 | AA63: 62 | AC63: 美宜佳
A64: KH00435 | B64: 粤35536美宜佳中山市火炬开发区幸福天禧店 | D64: 广州同超贸易有限公司 | E64: 销售部 | F64: 尹朝勇 | G64: 14789316693 | H64: 广东省 | I64: 中山市 | J64: 中山市 | K64: 中山港街道 | L64: 广东省中山市火炬开发区街道火炬开发区幸福公寓伟盛路12号 | M64: 同超2号 | N64: 默认线路 | O64: 其他 | P64: 是 | Q64: 113.45499 | R64: 22.56117 | S64: 20260205195630170815329-1 | U64: 启用 | V64: 正常 | W64: 否 | AA64: 63 | AC64: 美宜佳
A65: KH00434 | B65: 粤40245美宜佳中山市民众镇政通路美宜佳 | D65: 广州同超贸易有限公司 | E65: 销售部 | F65: 刘芬 | G65: 13424528545 | H65: 广东省 | I65: 中山市 | J65: 中山市 | K65: 民众街道 | L65: 广东省中山市民众镇政通路美宜佳 | M65: 同超2号 | N65: 默认线路 | O65: 其他 | P65: 是 | Q65: 113.49421 | R65: 22.620016 | S65: 20260202100859520107119-1 | U65: 启用 | V65: 正常 | W65: 否 | AA65: 64 | AC65: 美宜佳
A66: KH00433 | B66: 粤27879美宜佳中山市火炬开发区广盛店 | D66: 广州同超贸易有限公司 | E66: 销售部 | F66: 林先生 | G66: 13726028503 | H66: 广东省 | I66: 中山市 | J66: 中山市 | K66: 中山港街道 | L66: 广东省中山市火炬开发区街道沙边村广盛厂里 | M66: 同超2号 | N66: 默认线路 | O66: 其他 | P66: 是 | Q66: 113.43975 | R66: 22.554877 | S66: 20260129092404624699438-1 | U66: 启用 | V66: 正常 | W66: 否 | AA66: 65 | AC66: 美宜佳
A67: KH00432 | B67: 粤26835美宜佳中山市民众镇锦标市场店 | D67: 广州同超贸易有限公司 | E67: 销售部 | F67: 刘芬 | G67: 13424528545 | H67: 广东省 | I67: 中山市 | J67: 中山市 | K67: 民众街道 | L67: 广东省中山市民众镇锦丰东路47号 | M67: 同超2号 | N67: 默认线路 | O67: 其他 | P67: 是 | Q67: 113.49029 | R67: 22.602059 | S67: 20260205200046469845573-1 | U67: 启用 | V67: 正常 | W67: 否 | AA67: 66 | AC67: 美宜佳
A68: KH00431 | B68: 粤22892美宜佳中山市东升镇美誉诚品店 | D68: 广州同超贸易有限公司 | E68: 销售部 | F68: 刘芬 | G68: 13424528545 | H68: 广东省 | I68: 中山市 | J68: 中山市 | K68: 东升镇 | L68: 广东省中山市东升镇美誉诚品花园 | M68: 同超2号 | N68: 默认线路 | O68: 其他 | P68: 是 | Q68: 113.32228 | R68: 22.587348 | S68: 20260129091420674918201-1 | U68: 启用 | V68: 正常 | W68: 否 | AA68: 67 | AC68: 美宜佳
A69: KH00430 | B69: D185(AB)广东中山沙溪隆墟美宜佳 | D69: 广州同超贸易有限公司 | E69: 销售部 | F69: 王徳应 | G69: 13432103972 | H69: 广东省 | I69: 中山市 | J69: 中山市 | K69: 沙溪镇 | L69: 广东省中山市沙溪镇隆都路115号 | M69: 同超2号 | N69: 默认线路 | O69: 其他 | P69: 是 | Q69: 113.31632 | R69: 22.516433 | S69: 20260130103159834365632-1 | U69: 启用 | V69: 正常 | W69: 否 | AA69: 68 | AC69: 美宜佳
A70: KH00429 | B70: 9585(AB)广东中山火炬开发民康西美宜佳 | D70: 广州同超贸易有限公司 | E70: 销售部 | F70: 郑女士 | G70: 18928150193 | H70: 广东省 | I70: 中山市 | J70: 中山市 | K70: 中山港街道 | L70: 广东省中山市火炬开发区街道东利市场后侧商住楼A栋1卡 | M70: 同超2号 | N70: 默认线路 | O70: 其他 | P70: 是 | Q70: 113.52861 | R70: 22.562779 | S70: 20260123225909231463897-1 | U70: 启用 | V70: 正常 | W70: 否 | AA70: 69 | AC70: 美宜佳
A71: KH00428 | B71: 16230美宜佳中山市三角镇锦城西三街美宜佳 | D71: 广州同超贸易有限公司 | E71: 销售部 | F71: 刘芬 | G71: 13424528545 | H71: 广东省 | I71: 中山市 | J71: 中山市 | K71: 三角镇 | L71: 广东省中山市三角镇锦城西三街美宜佳 | M71: 同超2号 | N71: 默认线路 | O71: 其他 | P71: 是 | Q71: 113.41819 | R71: 22.676817 | S71: 20260202100412529960665-1 | U71: 启用 | V71: 正常 | W71: 否 | AA71: 70 | AC71: 美宜佳
A72: KH00427 | B72: 30286天福及时中山市东升镇俊廷居店 | D72: 广州同超贸易有限公司 | E72: 销售部 | F72: 潘老板 | G72: 19178323106 | H72: 广东省 | I72: 中山市 | J72: 中山市 | K72: 小榄镇 | L72: 广东省中山市小榄镇绩东一社区阜安路82号之 | M72: 同超2号 | N72: 默认线路 | O72: 其他 | P72: 是 | Q72: 113.26173 | R72: 22.649425 | S72: 20260205110614552713812-1 | U72: 启用 | V72: 正常 | W72: 否 | AA72: 71 | AC72: 美宜佳
A73: KH00426 | B73: 粤33565美宜佳中山市东升镇美宜佳便利店 | D73: 广州同超贸易有限公司 | E73: 销售部 | F73: 何老板 | G73: 17820496689 | H73: 广东省 | I73: 中山市 | J73: 中山市 | K73: 小榄镇 | L73: 广东省中山市小榄镇阳光美加小区二期商铺32卡 | M73: 同超2号 | N73: 默认线路 | O73: 其他 | P73: 是 | Q73: 113.26155 | R73: 22.642876 | S73: 20260126090706979331703-1 | U73: 启用 | V73: 正常 | W73: 否 | AA73: 72 | AC73: 美宜佳
... A86: KH00413 | B86: 粤11978美宜佳中山市黄圃镇同济东路店 | D86: 广州同超贸易有限公司 | E86: 销售部 | F86: 老板 | G86: 18029903709 | H86: 广东省 | I86: 中山市 | J86: 中山市 | K86: 南头镇 | L86: 广东省中山市南头镇将军社区华翠楼商铺第七卡 | M86: 同超2号 | N86: 默认线路 | O86: 其他 | P86: 是 | Q86: 113.31244 | R86: 22.712362 | S86: 20260131091201179137946-1 | U86: 启用 | V86: 正常 | W86: 否 | AA86: 85 | AC86: 美宜佳
A87: KH00412 | B87: 30703-及时便利古镇为民北店 | D87: 广州同超贸易有限公司 | E87: 销售部 | F87: 罗美丽 | G87: 15875080265 | H87: 广东省 | I87: 中山市 | J87: 中山市 | K87: 古镇镇 | L87: 广东省中山市古镇镇新兴村古一新兴村北一路11号 | M87: 同超2号 | N87: 默认线路 | O87: 其他 | P87: 是 | Q87: 未登记 | R87: 未登记 | S87: 20260123212155333061402-1 | U87: 启用 | V87: 正常 | W87: 否 | AA87: 86 | AC87: 美宜佳
A88: KH00411 | B88: 粤2148合家欢中山市南头镇将军市场店 | D88: 广州同超贸易有限公司 | E88: 销售部 | F88: 胡老板 | G88: 15307604074 | H88: 广东省 | I88: 中山市 | J88: 中山市 | K88: 南头镇 | L88: 广东省中山市南头镇合胜东路102号 | M88: 同超2号 | N88: 默认线路 | O88: 其他 | P88: 是 | S88: 20260125122718614381499-1 | U88: 启用 | V88: 正常 | W88: 否 | AA88: 87 | AC88: 美宜佳
A89: KH00410 | B89: 粤38311美宜佳阳江市繁华里 | D89: 广州同超贸易有限公司 | E89: 销售部 | F89: 雷换英 | G89: 19068100188 | H89: 广东省 | I89: 阳江市 | J89: 江城区 | L89: 广东省阳江市江城区城东街道湖湾路6号漠江花园B5栋9号铺 | M89: 同超2号 | N89: 默认线路 | O89: 其他 | P89: 是 | Q89: 112.00249 | R89: 21.859052 | S89: 20260128104946827627967-1 | U89: 启用 | V89: 正常 | W89: 否 | AA89: 88 | AC89: 美宜佳
A90: KH00409 | B90: 30882天福及时中山市古镇冈东狮盾工厂店 | D90: 广州同超贸易有限公司 | E90: 销售部 | F90: 杨天江 | G90: 15362902959 | H90: 广东省 | I90: 中山市 | J90: 中山市 | K90: 古镇镇 | L90: 广东省中山市古镇镇冈东狮盾工厂内及时（盛丰街10号） | M90: 同超2号 | N90: 默认线路 | O90: 其他 | P90: 是 | Q90: 113.18809 | R90: 22.594654 | S90: 20260203090518934832400-1 | U90: 启用 | V90: 正常 | W90: 否 | AA90: 89 | AC90: 美宜佳
A91: KH00408 | B91: 粤39132美宜佳中山市横栏镇横栏路 | D91: 广州同超贸易有限公司 | E91: 销售部 | F91: 马旺红 | G91: 13528298233 | H91: 广东省 | I91: 中山市 | J91: 中山市 | K91: 横栏镇 | L91: 广东省中山市横栏镇德龙中路33号 | M91: 同超2号 | N91: 默认线路 | O91: 其他 | P91: 是 | Q91: 113.23705 | R91: 22.569755 | S91: 20260130081221371945696-1 | U91: 启用 | V91: 正常 | W91: 否 | AA91: 90 | AC91: 美宜佳
A92: KH00407 | B92: 粤18782美宜佳横栏镇乐丰六路店 | D92: 广州同超贸易有限公司 | E92: 销售部 | F92: 蒙海燕 | G92: 15728661059 | H92: 广东省 | I92: 中山市 | J92: 中山市 | K92: 横栏镇 | L92: 广东省中山市横栏镇茂辉工业区乐丰六路3号首层第8之1 | M92: 同超2号 | N92: 默认线路 | O92: 其他 | P92: 是 | Q92: 113.22951 | R92: 22.565125 | S92: 20260128130917800246486-1 | U92: 启用 | V92: 正常 | W92: 否 | AA92: 91 | AC92: 美宜佳
A93: KH00406 | B93: 粤10362美宜佳中山市横栏镇三沙牌坊店 | D93: 广州同超贸易有限公司 | E93: 销售部 | F93: 戴全耀 | G93: 13527158073 | H93: 广东省 | I93: 中山市 | J93: 中山市 | K93: 横栏镇 | L93: 广东省中山市横栏镇横栏三沙综合市场 | M93: 同超2号 | N93: 默认线路 | O93: 其他 | P93: 是 | Q93: 113.2142 | R93: 22.580803 | S93: 20260130083434333368735-1 | U93: 启用 | V93: 正常 | W93: 否 | AA93: 92 | AC93: 美宜佳
A94: KH00405 | B94: 粤10286美宜佳中山市横栏镇三沙牌坊路店 | D94: 广州同超贸易有限公司 | E94: 销售部 | F94: 李世伟 | G94: 17328153918 | H94: 广东省 | I94: 中山市 | J94: 中山市 | K94: 横栏镇 | L94: 广东省中山市横栏镇三沙牌坊路42号 | M94: 同超2号 | N94: 默认线路 | O94: 其他 | P94: 是 | Q94: 113.21433 | R94: 22.583091 | S94: 20260126105906932040967-1 | U94: 启用 | V94: 正常 | W94: 否 | AA94: 93 | AC94: 美宜佳
A95: KH00404 | B95: 4153(AB)中山大涌南新北路美宜佳 | D95: 广州同超贸易有限公司 | E95: 销售部 | F95: 梁红 | G95: 18239632684 | H95: 广东省 | I95: 中山市 | J95: 中山市 | K95: 大涌镇 | L95: 广东省中山市大涌镇街道旗山路南兴商住楼4栋第四商铺(2503搬) | M95: 同超2号 | N95: 默认线路 | O95: 其他 | P95: 是 | Q95: 113.29409 | R95: 22.466296 | S95: 20260127073445899843757-1 | U95: 启用 | V95: 正常 | W95: 否 | AA95: 94 | AC95: 美宜佳
A96: KH00403 | B96: 15833天福茂名市信宜市 | D96: 广州同超贸易有限公司 | E96: 销售部 | F96: 邱店长 | G96: 13686736612 | H96: 广东省 | I96: 茂名市 | J96: 信宜市 | L96: 广东省信宣市玉都街道书香二路1号3号楼首层1号铺 | M96: 同超2号 | N96: 默认线路 | O96: 其他 | P96: 是 | Q96: 110.94645 | R96: 22.316791 | S96: 20260208103239498387353-1 | U96: 启用 | V96: 正常 | W96: 否 | AA96: 95 | AC96: 美宜佳
A97: KH00402 | B97: 粤27930美宜佳茂名市高州市 | D97: 广州同超贸易有限公司 | E97: 销售部 | F97: 珍店长 | G97: 13924384175 | H97: 广东省 | I97: 茂名市 | J97: 高州市 | L97: 广东省茂名市高州市石仔岭街道石仔岭街道红荔路 | M97: 同超2号 | N97: 默认线路 | O97: 其他 | P97: 是 | Q97: 110.82991 | R97: 21.88959 | S97: 20260202211125344209790-1 | U97: 启用 | V97: 正常 | W97: 否 | AA97: 96 | AC97: 美宜佳
A98: KH00401 | B98: 粤23413美宜佳茂名市高州市 | D98: 广州同超贸易有限公司 | E98: 销售部 | F98: 钟杰花 | G98: 13580037215 | H98: 广东省 | I98: 茂名市 | J98: 高州市 | L98: 广东省茂名市高州市泗水镇和平路 | M98: 同超2号 | N98: 默认线路 | O98: 其他 | P98: 是 | Q98: 110.96026 | R98: 21.848748 | S98: 20260127140651726162325-1 | U98: 启用 | V98: 正常 | W98: 否 | AA98: 97 | AC98: 美宜佳
A99: KH00400 | B99: 粤E621美宜佳茂名市高州市 | D99: 广州同超贸易有限公司 | E99: 销售部 | F99: 梁郁妹 | G99: 18476560680 | H99: 广东省 | I99: 茂名市 | J99: 高州市 | L99: 广东省茂名市高州市潘州街道茂名大道南侧住宅楼１号商铺（鼎豪精品酒店对面） | M99: 同超2号 | N99: 默认线路 | O99: 其他 | P99: 是 | Q99: 110.85542 | R99: 21.89834 | S99: 20260127140223870395670-1 | U99: 启用 | V99: 正常 | W99: 否 | AA99: 98 | AC99: 美宜佳
A100: KH00399 | B100: E195（AB）广东茂名信宜新尚路美宜佳 | D100: 广州同超贸易有限公司 | E100: 销售部 | F100: 潘国均 | G100: 18218681108 | H100: 广东省 | I100: 茂名市 | J100: 信宜市 | L100: 广东省茂名市信宜市东镇街道新尚路鸿泰豪庭首层商铺6号 | M100: 同超2号 | N100: 默认线路 | O100: 其他 | P100: 是 | Q100: 110.93489 | R100: 22.353044 | S100: 20260201084049370111510-1 | U100: 启用 | V100: 正常 | W100: 否 | AA100: 99 | AC100: 美宜佳
A101: KH00398 | B101: 粤D485美宜佳茂名市高州市 | D101: 广州同超贸易有限公司 | E101: 销售部 | F101: 媚姐 | G101: 15218299580 | H101: 广东省 | I101: 茂名市 | J101: 高州市 | L101: 广东省茂名市高州市潘州街道茂名大道182号(2号商铺) | M101: 同超2号 | N101: 默认线路 | O101: 其他 | P101: 是 | Q101: 110.85254 | R101: 21.900596 | S101: 20260201161331261780668-1 | U101: 启用 | V101: 正常 | W101: 否 | AA101: 100 | AC101: 美宜佳
A102: KH00397 | B102: 37162（AB）广东韶关曲江石堡美宜佳 | D102: 广州同超贸易有限公司 | E102: 销售部 | F102: 江莹 | G102: 15113420340 | H102: 广东省 | I102: 韶关市 | J102: 曲江区 | L102: 广东省韶关市曲江区马坝镇慧能路10号 | M102: 同超2号 | N102: 默认线路 | O102: 其他 | P102: 是 | Q102: 113.60606 | R102: 24.680138 | S102: 20260209095742523495708-1 | U102: 启用 | V102: 正常 | W102: 否 | AA102: 101 | AC102: 美宜佳
A103: KH00396 | B103: G775（AB）广东韶关江启明北路美宜佳 | D103: 广州同超贸易有限公司 | E103: 销售部 | F103: 莫小小 | G103: 13580131093 | H103: 广东省 | I103: 韶关市 | J103: 浈江区 | L103: 广东省韶关市浈江区东河街道启明北路启明大厦7-8号铺 | M103: 同超2号 | N103: 默认线路 | O103: 其他 | P103: 是 | Q103: 113.6039 | R103: 24.812306 | S103: 20260203144754616210663-1 | U103: 启用 | V103: 正常 | W103: 否 | AA103: 102 | AC103: 美宜佳
A104: KH00395 | B104: 粤17166美宜佳广州市番禺区洛浦街道沿沙路口店 | D104: 广州同超贸易有限公司 | E104: 销售部 | F104: 张世颖 | G104: 18924015602 | H104: 广东省 | I104: 广州市 | J104: 番禺区 | L104: 广东省广州市番禺区洛浦街道沿沙路7号 | M104: 同超2号 | N104: 默认线路 | O104: 其他 | P104: 是 | Q104: 113.29462 | R104: 23.037853 | S104: 20260209125202294056632-1 | U104: 启用 | V104: 正常 | W104: 否 | AA104: 103 | AC104: 美宜佳
A105: KH00394 | B105: 粤15381美宜佳广州市番禺区 | D105: 广州同超贸易有限公司 | E105: 销售部 | F105: 杨先生 | G105: 18027162431 | H105: 广东省 | I105: 广州市 | J105: 番禺区 | L105: 广东省广州市番禺区洛浦街道康宁西路35号 | M105: 同超2号 | N105: 默认线路 | O105: 其他 | P105: 是 | Q105: 113.29346 | R105: 23.046729 | S105: 20260205155332056048261-1 | U105: 启用 | V105: 正常 | W105: 否 | AA105: 104 | AC105: 美宜佳
A106: KH00393 | B106: 粤37268美宜佳佛山市顺德区大良五沙 | D106: 广州同超贸易有限公司 | E106: 销售部 | F106: 余建南 | G106: 13687908155 | H106: 广东省 | I106: 佛山市 | J106: 顺德区 | L106: 广东省佛山市顺德区大良街道新汇路6号 | M106: 同超2号 | N106: 默认线路 | O106: 其他 | P106: 是 | Q106: 113.36008 | R106: 22.803935 | S106: 20260202113320545357276-1 | U106: 启用 | V106: 正常 | W106: 否 | AA106: 105 | AC106: 美宜佳
A107: KH00392 | B107: 粤33875美宜佳伦教保利中央公园20栋1601 | D107: 广州同超贸易有限公司 | E107: 销售部 | F107: 陈生 | G107: 13106701510 | H107: 广东省 | I107: 佛山市 | J107: 顺德区 | L107: 广东省佛山市顺德区伦教保利中央公园20栋1601 | M107: 同超2号 | N107: 默认线路 | O107: 其他 | P107: 是 | Q107: 113.22828 | R107: 22.866102 | S107: 20260127131617508082435-1 | U107: 启用 | V107: 正常 | W107: 否 | AA107: 106 | AC107: 美宜佳
... A120: KH00379 | B120: 粤39190美宜佳广州增城新塘 | D120: 广州同超贸易有限公司 | E120: 销售部 | F120: 陈李兵 | G120: 13144266213 | H120: 广东省 | I120: 广州市 | J120: 增城区 | L120: 广东省广州市增城区新塘镇港口大道北339号 | M120: 同超2号 | N120: 默认线路 | O120: 其他 | P120: 是 | Q120: 113.60443 | R120: 23.125605 | S120: 20260303191812749834124-1 | U120: 启用 | V120: 正常 | W120: 否 | AA120: 119 | AC120: 美宜佳
A121: KH00378 | B121: 粤38506美宜佳东莞市洪梅达瑞电子厂 | D121: 广州同超贸易有限公司 | E121: 销售部 | F121: 李老板 | G121: 13829270166 | H121: 广东省 | I121: 东莞市 | J121: 东莞市 | K121: 洪梅镇 | L121: 广东省东莞市洪梅镇乌沙村洪金路49号 | M121: 同超2号 | N121: 默认线路 | O121: 其他 | P121: 是 | Q121: 113.61727 | R121: 22.972087 | S121: 20260204232208039551580-1 | U121: 启用 | V121: 正常 | W121: 否 | AA121: 120 | AC121: 美宜佳
A122: KH00377 | B122: 粤34478美宜佳广州新塘 | D122: 广州同超贸易有限公司 | E122: 销售部 | F122: 江先生 | G122: 18659329538 | H122: 广东省 | I122: 广州市 | J122: 增城区 | L122: 广东省广州市增城区新塘镇民营大道西3号 | M122: 同超2号 | N122: 默认线路 | O122: 其他 | P122: 是 | Q122: 113.62731 | R122: 23.146109 | S122: 20260131135425680036134-1 | U122: 启用 | V122: 正常 | W122: 否 | AA122: 121 | AC122: 美宜佳
A123: KH00376 | B123: 粤33108美宜佳广州增城区新塘 | D123: 广州同超贸易有限公司 | E123: 销售部 | F123: 李先生 | G123: 13601085068 | H123: 广东省 | I123: 广州市 | J123: 增城区 | L123: 广东省广州市增城区新塘镇豪泮街一巷3-1 | M123: 同超2号 | N123: 默认线路 | O123: 其他 | P123: 是 | Q123: 113.61977 | R123: 23.119445 | S123: 20260127184953888644178-1 | U123: 启用 | V123: 正常 | W123: 否 | AA123: 122 | AC123: 美宜佳
A124: KH00375 | B124: 粤31155美宜佳广州增城新塘官湖 | D124: 广州同超贸易有限公司 | E124: 销售部 | F124: 蒋先生 | G124: 13902389873 | H124: 广东省 | I124: 广州市 | J124: 增城区 | L124: 广东省广州市增城区新塘镇三角水路10号 | M124: 同超2号 | N124: 默认线路 | O124: 其他 | P124: 是 | Q124: 113.63367 | R124: 23.137807 | S124: 20260131205121802220952-1 | U124: 启用 | V124: 正常 | W124: 否 | AA124: 123 | AC124: 美宜佳
A125: KH00374 | B125: 粤30810美宜佳增城区新塘镇大墩 | D125: 广州同超贸易有限公司 | E125: 销售部 | F125: 魏先生 | G125: 18026420377 | H125: 广东省 | I125: 广州市 | J125: 增城区 | L125: 广东省广州市增城区新塘镇广荔路60号 | M125: 同超2号 | N125: 默认线路 | O125: 其他 | P125: 是 | Q125: 113.65577 | R125: 23.121516 | S125: 20260131135735397672120-1 | U125: 启用 | V125: 正常 | W125: 否 | AA125: 124 | AC125: 美宜佳
A126: KH00373 | B126: 粤30773美宜佳增城新塘东坑三横路 | D126: 广州同超贸易有限公司 | E126: 销售部 | F126: 大眉 | G126: 13760608281 | H126: 广东省 | I126: 广州市 | J126: 增城区 | L126: 广东省广州市增城区新塘镇三横路85号 | M126: 同超2号 | N126: 默认线路 | O126: 其他 | P126: 是 | Q126: 113.60564 | R126: 23.122791 | S126: 20260302153804739597049-1 | U126: 启用 | V126: 正常 | W126: 否 | AA126: 125 | AC126: 美宜佳
A127: KH00372 | B127: 粤30375美宜佳增城创新大道永荟商铺 | D127: 广州同超贸易有限公司 | E127: 销售部 | F127: 谢先生 | G127: 15914080377 | H127: 广东省 | I127: 广州市 | J127: 增城区 | L127: 广东省广州市增城区永宁街道永旺公寓B1-101号 | M127: 同超2号 | N127: 默认线路 | O127: 其他 | P127: 是 | Q127: 113.57724 | R127: 23.125914 | S127: 20260201211251817818677-1 | U127: 启用 | V127: 正常 | W127: 否 | AA127: 126 | AC127: 美宜佳
A128: KH00371 | B128: 粤29476新塘美宜佳新塘华兴公寓 | D128: 广州同超贸易有限公司 | E128: 销售部 | F128: 杨小姐 | G128: 13332863517 | H128: 广东省 | I128: 广州市 | J128: 增城区 | L128: 广东省广州市增城区新塘镇东坑四横路2号 | M128: 同超2号 | N128: 默认线路 | O128: 其他 | P128: 是 | Q128: 113.61242 | R128: 23.126077 | S128: 20260202215838969924718-1 | U128: 启用 | V128: 正常 | W128: 否 | AA128: 127 | AC128: 美宜佳
...
